Workbook

Sheet PFM
C2: 公牛集团 PFM 经营驱动模型
C3: r4b · Post-demo revision 2026-09-07 · 2026H1 actuals + Jul2026-Dec2028 monthly forecasts.
G7: 2026E | H7: 2027E | I7: 2028E
C9: Revenue 收入 | G9: =Annual!G9 -> 16533.137 | H9: =Annual!H9 -> 17127.709 | I9: =Annual!I9 -> 17753.04
C10: Gross profit 毛利 | G10: =Annual!G11 -> 6669.0324 | H10: =Annual!H11 -> 7085.4886 | I10: =Annual!I11 -> 7174.0035
C11: Gross margin 毛利率 | G11: =Annual!G64 -> 0.40337368 | H11: =Annual!H64 -> 0.41368572 | I11: =Annual!I64 -> 0.40410001
C12: Net income 净利润 | G12: =Annual!G23 -> 3929.6811 | H12: =Annual!H23 -> 4115.1327 | I12: =Annual!I23 -> 4132.7821
C14: Operating cash flow 经营现金流 | G14: =Annual!G56 -> 3559.4628 | H14: =Annual!H56 -> 4061.6758 | I14: =Annual!I56 -> 4091.7066
C15: Closing cash 期末现金 | G15: =Annual!G61 -> 2313.6962 | H15: =Annual!H61 -> 2495.3179 | I15: =Annual!I61 -> 2533.478
C16: Balance sheet difference 资产负债差额 | G16: =Annual!G53 -> 0 | H16: =Annual!H53 -> 0 | I16: =Annual!I53 -> 0
C19: Minimum monthly cash 月度现金低点 | G19: =MIN(Monthly_BS!J10:O10) -> 1139.6766 | H19: =MIN(Monthly_BS!P10:AA10) -> 947.77897 | I19: =MIN(Monthly_BS!AB10:AM10) -> 981.08402
C20: Maximum monthly BS difference 月度平衡差额 | G20: =MAX(MAX(Checks!J9:O9),-MIN(Checks!J9:O9)) -> 0 | H20: =MAX(MAX(Checks!P9:AA9),-MIN(Checks!P9:AA9)) -> 0 | I20: =MAX(MAX(Checks!AB9:AM9),-MIN(Checks!AB9:AM9)) -> 0
C21: Invalid input count 输入错误数 | G21: =SUM(Checks!J27:O27)+SUM(Liquidity!J57:O57) -> 0 | H21: =SUM(Checks!P27:AA27)+SUM(Liquidity!P57:AA57) -> 0 | I21: =SUM(Checks!AB27:AM27)+SUM(Liquidity!AB57:AM57) -> 0
C22: Investment redemptions 投资赎回 | G22: =SUM(Liquidity!J34:O34) -> 0 | H22: =SUM(Liquidity!P34:AA34) -> 0 | I22: =SUM(Liquidity!AB34:AM34) -> 0
C23: Peak standby RCF 备用融资峰值 | G23: =MAX(Liquidity!J48:O48) -> 0 | H23: =MAX(Liquidity!P48:AA48) -> 0 | I23: =MAX(Liquidity!AB48:AM48) -> 0
C24: Monthly operating build
C25: Product sales / net ASP; production requirement; physical FG; material consumption and purchases; weighted-average FG cost; source stock-category rolls.
C28: Payroll and Opex
C29: Four functional headcount rolls; remuneration/person; disclosed selling/admin/R&D expense lines. Production payroll and manufacturing D&A flow through inventory.
C32: Treasury and accounting
C33: Separate pledged/credit/long loans and leases; requested/effective funding; taxes, DTA/DTL, reserves/NCI; direct and indirect monthly CFO.
C36: Source and scope boundary
C37: H1 2026 PL/BS/CFS are reported actuals. Forecast starts July from the actual balance sheet. Investment windows and standby RCF remain planning assumptions.
C40: What remains unbuilt
C41: Open: product-level maturity and redemption terms, committed facility contracts, monthly management accounts, HKFRS and filing sufficiency work.
C47: → Revenue
C48: → Production
C49: → Payroll | L49: Year | M49: Revenue | N49: Net income
C50: → ExpenseDetail | L50: 2023A | M50: =Annual!D9 -> 15694.756 | N50: =Annual!D23 -> 3864.3265
C51: → Inventory | L51: 2024A | M51: =Annual!E9 -> 16830.541 | N51: =Annual!E23 -> 4269.1759
C52: → Assets | L52: 2025A | M52: =Annual!F9 -> 16026.313 | N52: =Annual!F23 -> 4076.302
C53: → Funding | L53: 2026E | M53: =Annual!G9 -> 16533.137 | N53: =Annual!G23 -> 3929.6811
C54: → Checks | L54: 2027E | M54: =Annual!H9 -> 17127.709 | N54: =Annual!H23 -> 4115.1327
C55: → ReadMe | L55: 2028E | M55: =Annual!I9 -> 17753.04 | N55: =Annual!I23 -> 4132.7821
L58: Month | M58: Closing cash | N58: CFO
L59: 2026-01 | M59: =Monthly_CF!D51 -> 0 | N59: =Monthly_CF!D24 -> 0
L60: 2026-02 | M60: =Monthly_CF!E51 -> 0 | N60: =Monthly_CF!E24 -> 0
L61: 2026-03 | M61: =Monthly_CF!F51 -> 0 | N61: =Monthly_CF!F24 -> 0
L62: 2026-04 | M62: =Monthly_CF!G51 -> 0 | N62: =Monthly_CF!G24 -> 0
L63: 2026-05 | M63: =Monthly_CF!H51 -> 0 | N63: =Monthly_CF!H24 -> 0
L64: 2026-06 | M64: =Monthly_CF!I51 -> 1058.4987 | N64: =Monthly_CF!I24 -> 2235.8824
L65: 2026-07 | M65: =Monthly_CF!J51 -> 1139.6766 | N65: =Monthly_CF!J24 -> 92.221836
L66: 2026-08 | M66: =Monthly_CF!K51 -> 1516.9441 | N66: =Monthly_CF!K24 -> 388.30705
L67: 2026-09 | M67: =Monthly_CF!L51 -> 1609.8743 | N67: =Monthly_CF!L24 -> 105.05724
L68: 2026-10 | M68: =Monthly_CF!M51 -> 1761.0473 | N68: =Monthly_CF!M24 -> 162.20412
L69: 2026-11 | M69: =Monthly_CF!N51 -> 2381.0452 | N69: =Monthly_CF!N24 -> 632.11671
L70: 2026-12 | M70: =Monthly_CF!O51 -> 2313.6962 | N70: =Monthly_CF!O24 -> -56.326546
L71: 2027-01 | M71: =Monthly_CF!P51 -> 3137.8529 | N71: =Monthly_CF!P24 -> 837.36313
L72: 2027-02 | M72: =Monthly_CF!Q51 -> 3861.9133 | N72: =Monthly_CF!Q24 -> 740.5397
L73: 2027-03 | M73: =Monthly_CF!R51 -> 3227.1663 | N73: =Monthly_CF!R24 -> -621.54915
L74: 2027-04 | M74: =Monthly_CF!S51 -> 4120.0297 | N74: =Monthly_CF!S24 -> 907.14964
L75: 2027-05 | M75: =Monthly_CF!T51 -> 4235.3579 | N75: =Monthly_CF!T24 -> 128.5175
L76: 2027-06 | M76: =Monthly_CF!U51 -> 947.77897 | N76: =Monthly_CF!U24 -> 447.8391
L77: 2027-07 | M77: =Monthly_CF!V51 -> 948.14618 | N77: =Monthly_CF!V24 -> 12.740617
L78: 2027-08 | M78: =Monthly_CF!W51 -> 1501.2196 | N78: =Monthly_CF!W24 -> 565.44257
L79: 2027-09 | M79: =Monthly_CF!X51 -> 1803.6313 | N79: =Monthly_CF!X24 -> 315.89595
L80: 2027-10 | M80: =Monthly_CF!Y51 -> 1942.9134 | N80: =Monthly_CF!Y24 -> 151.64276
L81: 2027-11 | M81: =Monthly_CF!Z51 -> 2579.4234 | N81: =Monthly_CF!Z24 -> 648.96013
L82: 2027-12 | M82: =Monthly_CF!AA51 -> 2495.3179 | N82: =Monthly_CF!AA24 -> -72.866197
L83: 2028-01 | M83: =Monthly_CF!AB51 -> 3345.7562 | N83: =Monthly_CF!AB24 -> 864.06985
L84: 2028-02 | M84: =Monthly_CF!AC51 -> 3887.0928 | N84: =Monthly_CF!AC24 -> 557.20147
L85: 2028-03 | M85: =Monthly_CF!AD51 -> 3526.0922 | N85: =Monthly_CF!AD24 -> -347.369
L86: 2028-04 | M86: =Monthly_CF!AE51 -> 4320.8352 | N86: =Monthly_CF!AE24 -> 809.49129
L87: 2028-05 | M87: =Monthly_CF!AF51 -> 4433.9875 | N87: =Monthly_CF!AF24 -> 126.78391
L88: 2028-06 | M88: =Monthly_CF!AG51 -> 995.39617 | N88: =Monthly_CF!AG24 -> 464.20332
L89: 2028-07 | M89: =Monthly_CF!AH51 -> 981.08402 | N89: =Monthly_CF!AH24 -> -1.4856926
L90: 2028-08 | M90: =Monthly_CF!AI51 -> 1541.791 | N90: =Monthly_CF!AI24 -> 573.53342
L91: 2028-09 | M91: =Monthly_CF!AJ51 -> 1853.4254 | N91: =Monthly_CF!AJ24 -> 325.60349
L92: 2028-10 | M92: =Monthly_CF!AK51 -> 1979.9156 | N92: =Monthly_CF!AK24 -> 139.31664
L93: 2028-11 | M93: =Monthly_CF!AL51 -> 2632.302 | N93: =Monthly_CF!AL24 -> 666.3555
L94: 2028-12 | M94: =Monthly_CF!AM51 -> 2533.478 | N94: =Monthly_CF!AM24 -> -85.997571

Sheet Annual
C2: 公牛集团 Annual
C3: RMB million except units, people, RMB/person and explicit rates. Monthly forecasts, not monthly actuals.
D7: 2023A | E7: 2024A | F7: 2025A | G7: 2026E | H7: 2027E | I7: 2028E
C9: Revenue | D9: =SourceHistory!D9 -> 15694.756 | E9: =SourceHistory!E9 -> 16830.541 | F9: =SourceHistory!F9 -> 16026.313 | G9: =H1Actual!D9+(SUM(Monthly_PL!J10:O10)) -> 16533.137 | H9: =SUM(Monthly_PL!P10:AA10) -> 17127.709 | I9: =SUM(Monthly_PL!AB10:AM10) -> 17753.04
C10: COGS | D10: =SourceHistory!D10 -> 8914.1845 | E10: =SourceHistory!E10 -> 9551.8091 | F10: =SourceHistory!F10 -> 9113.1866 | G10: =H1Actual!D10+(SUM(Monthly_PL!J14:O14)) -> 9864.1046 | H10: =SUM(Monthly_PL!P14:AA14) -> 10042.22 | I10: =SUM(Monthly_PL!AB14:AM14) -> 10579.036
C11: Gross profit | D11: =D9-D10 -> 6780.5711 | E11: =E9-E10 -> 7278.732 | F11: =F9-F10 -> 6913.1259 | G11: =H1Actual!D11+(SUM(Monthly_PL!J15:O15)) -> 6669.0324 | H11: =SUM(Monthly_PL!P15:AA15) -> 7085.4886 | I11: =SUM(Monthly_PL!AB15:AM15) -> 7174.0035
C13: Selling expenses | D13: =SourceHistory!D11 -> 1070.4382 | E13: =SourceHistory!E11 -> 1369.4149 | F13: =SourceHistory!F11 -> 1183.4786 | G13: =H1Actual!D13+(SUM(Monthly_PL!J18:O18)) -> 1187.5263 | H13: =SUM(Monthly_PL!P18:AA18) -> 1250.9533 | I13: =SUM(Monthly_PL!AB18:AM18) -> 1287.8886
C14: Administration | D14: =SourceHistory!D12 -> 626.19855 | E14: =SourceHistory!E12 -> 732.04584 | F14: =SourceHistory!F12 -> 712.37518 | G14: =H1Actual!D14+(SUM(Monthly_PL!J19:O19)) -> 667.40903 | H14: =SUM(Monthly_PL!P19:AA19) -> 744.38039 | I14: =SUM(Monthly_PL!AB19:AM19) -> 766.80012
C15: R&D | D15: =SourceHistory!D13 -> 673.42739 | E15: =SourceHistory!E13 -> 745.51022 | F15: =SourceHistory!F13 -> 643.96378 | G15: =H1Actual!D15+(SUM(Monthly_PL!J20:O20)) -> 615.89423 | H15: =SUM(Monthly_PL!P20:AA20) -> 682.96445 | I15: =SUM(Monthly_PL!AB20:AM20) -> 704.69346
C16: Surcharges | D16: =SourceHistory!D14 -> 132.79617 | E16: =SourceHistory!E14 -> 133.17808 | F16: =SourceHistory!F14 -> 153.5287 | G16: =H1Actual!D16+(SUM(Monthly_PL!J21:O21)) -> 154.45554 | H16: =SUM(Monthly_PL!P21:AA21) -> 164.07985 | I16: =SUM(Monthly_PL!AB21:AM21) -> 170.07039
C17: Credit and asset impairment | D17: not mapped separately | E17: not mapped separately | F17: not mapped separately | G17: =H1Actual!D17+(SUM(Monthly_PL!J22:O22)+SUM(Monthly_PL!J23:O23)) -> 14.648504 | H17: =SUM(Monthly_PL!P22:AA22)+SUM(Monthly_PL!P23:AA23) -> 0.9843459 | I17: =SUM(Monthly_PL!AB22:AM22)+SUM(Monthly_PL!AB23:AM23) -> 1.0359089
C18: Other pretax/investment income | D18: =SourceHistory!D17 -> 150.1138 | E18: =SourceHistory!E17 -> 663.70528 | F18: =SourceHistory!F17 -> 588.91613 | G18: =H1Actual!D18+(SUM(Monthly_PL!J24:O24)+SUM(Monthly_PL!J25:O25)+SUM(Monthly_PL!J26:O26)) -> 652.48068 | H18: =SUM(Monthly_PL!P24:AA24)+SUM(Monthly_PL!P25:AA25)+SUM(Monthly_PL!P26:AA26) -> 658.17361 | I18: =SUM(Monthly_PL!AB24:AM24)+SUM(Monthly_PL!AB25:AM25)+SUM(Monthly_PL!AB26:AM26) -> 665.89385
C19: Net finance expense | D19: =SourceHistory!D15 -> -108.51035 | E19: =SourceHistory!E15 -> -118.16772 | F19: =SourceHistory!F15 -> -96.686209 | G19: =H1Actual!D19+(SUM(Monthly_PL!J28:O28)+-SUM(Monthly_PL!J27:O27)) -> -67.192569 | H19: =SUM(Monthly_PL!P28:AA28)+-SUM(Monthly_PL!P27:AA27) -> -91.620505 | I19: =SUM(Monthly_PL!AB28:AM28)+-SUM(Monthly_PL!AB27:AM27) -> -103.92139
C21: Profit before tax | D21: =SourceHistory!D18 -> 4536.335 | E21: =SourceHistory!E18 -> 5080.4559 | F21: =SourceHistory!F18 -> 4905.382 | G21: =H1Actual!D21+(SUM(Monthly_PL!J29:O29)) -> 4748.7721 | H21: =SUM(Monthly_PL!P29:AA29) -> 4991.9203 | I21: =SUM(Monthly_PL!AB29:AM29) -> 5013.3302
C22: Income tax | D22: =SourceHistory!D19 -> 672.00846 | E22: =SourceHistory!E19 -> 811.28001 | F22: =SourceHistory!F19 -> 829.07993 | G22: =H1Actual!D22+(SUM(Monthly_PL!J30:O30)) -> 819.09097 | H22: =SUM(Monthly_PL!P30:AA30) -> 876.78767 | I22: =SUM(Monthly_PL!AB30:AM30) -> 880.54812
C23: Consolidated net income | D23: =SourceHistory!D20 -> 3864.3265 | E23: =SourceHistory!E20 -> 4269.1759 | F23: =SourceHistory!F20 -> 4076.302 | G23: =H1Actual!D23+(SUM(Monthly_PL!J31:O31)) -> 3929.6811 | H23: =SUM(Monthly_PL!P31:AA31) -> 4115.1327 | I23: =SUM(Monthly_PL!AB31:AM31) -> 4132.7821
C24: Parent net income | D24: =SourceHistory!D21 -> 3870.1354 | E24: =SourceHistory!E21 -> 4272.2046 | F24: =SourceHistory!F21 -> 4070.6327 | G24: =H1Actual!D24+(SUM(Monthly_PL!J32:O32)) -> 3923.2026 | H24: =SUM(Monthly_PL!P32:AA32) -> 4109.4094 | I24: =SUM(Monthly_PL!AB32:AM32) -> 4127.0342
C25: NCI net income | D25: =SourceHistory!D22 -> -5.8088851 | E25: =SourceHistory!E22 -> -3.0286538 | F25: =SourceHistory!F22 -> 5.6692836 | G25: =H1Actual!D25+(SUM(Monthly_PL!J33:O33)) -> 6.4784522 | H25: =SUM(Monthly_PL!P33:AA33) -> 5.723289 | I25: =SUM(Monthly_PL!AB33:AM33) -> 5.7478356
C28: Cash equivalents | D28: =SourceHistory!D29 -> 1332.1862 | E28: =SourceHistory!E29 -> 836.3144 | F28: =SourceHistory!F29 -> 721.04459 | G28: =Monthly_BS!O10 -> 2313.6962 | H28: =Monthly_BS!AA10 -> 2495.3179 | I28: =Monthly_BS!AM10 -> 2533.478
C29: Other monetary balances | D29: =SourceHistory!D32 -> 3411.5282 | E29: =SourceHistory!E32 -> 4184.0659 | F29: =SourceHistory!F32 -> 3446.2746 | G29: =Monthly_BS!O11 -> 3480.0156 | H29: =Monthly_BS!AA11 -> 3480.0156 | I29: =Monthly_BS!AM11 -> 3480.0156
C30: Receivables and contract assets | D30: =SourceHistory!D33 -> 270.11345 | E30: =SourceHistory!E33 -> 308.26795 | F30: =SourceHistory!F33 -> 327.3602 | G30: =Monthly_BS!O12 -> 326.36872 | H30: =Monthly_BS!AA12 -> 337.48118 | I30: =Monthly_BS!AM12 -> 349.17574
C31: Inventory | D31: =SourceHistory!D34 -> 1421.0781 | E31: =SourceHistory!E34 -> 1573.6728 | F31: =SourceHistory!F34 -> 1630.8262 | G31: =Monthly_BS!O13 -> 1364.4977 | H31: =Monthly_BS!AA13 -> 1404.5994 | I31: =Monthly_BS!AM13 -> 1452.0644
C32: PPE / CIP / property | D32: =SourceHistory!D35 -> 2792.7544 | E32: =SourceHistory!E35 -> 3541.0394 | F32: =SourceHistory!F35 -> 3593.7711 | G32: =Monthly_BS!O14 -> 3685.854 | H32: =Monthly_BS!AA14 -> 3877.8143 | I32: =Monthly_BS!AM14 -> 4067.5683
C33: Intangibles/deferred costs | D33: =SourceHistory!D36 -> 357.58366 | E33: =SourceHistory!E36 -> 368.71448 | F33: =SourceHistory!F36 -> 359.98872 | G33: =Monthly_BS!O15 -> 363.87075 | H33: =Monthly_BS!AA15 -> 392.02983 | I33: =Monthly_BS!AM15 -> 417.30554
C34: ROU | D34: =SourceHistory!D37 -> 18.802452 | E34: =SourceHistory!E37 -> 31.309235 | F34: =SourceHistory!F37 -> 25.219574 | G34: =Monthly_BS!O16 -> 10.095861 | H34: =Monthly_BS!AA16 -> 0 | I34: =Monthly_BS!AM16 -> 0
C35: Investments | D35: =SourceHistory!D38 -> 9735.2638 | E35: =SourceHistory!E38 -> 9225.0107 | F35: =SourceHistory!F38 -> 12068.473 | G35: =Monthly_BS!O17 -> 10538.02 | H35: =Monthly_BS!AA17 -> 10538.02 | I35: =Monthly_BS!AM17 -> 10538.02
C36: Other assets incl DTA and interest cohort | D36: =SourceHistory!D39 -> 422.89552 | E36: =SourceHistory!E39 -> 425.63951 | F36: =SourceHistory!F39 -> 383.28421 | G36: =Monthly_BS!O18+Monthly_BS!O19+Monthly_BS!O20 -> 484.72476 | H36: =Monthly_BS!AA18+Monthly_BS!AA19+Monthly_BS!AA20 -> 609.69943 | I36: =Monthly_BS!AM18+Monthly_BS!AM19+Monthly_BS!AM20 -> 737.06534
C38: Total assets | D38: =SourceHistory!D40 -> 19762.206 | E38: =SourceHistory!E40 -> 20494.034 | F38: =SourceHistory!F40 -> 22556.243 | G38: =Monthly_BS!O22 -> 22567.144 | H38: =Monthly_BS!AA22 -> 23134.978 | I38: =Monthly_BS!AM22 -> 23574.693
C40: Trade payables | D40: =SourceHistory!D41 -> 2056.6578 | E40: =SourceHistory!E41 -> 2392.0469 | F40: =SourceHistory!F41 -> 2455.3959 | G40: =Monthly_BS!O25 -> 2408.3982 | H40: =Monthly_BS!AA25 -> 2526.8622 | I40: =Monthly_BS!AM25 -> 2654.0833
C41: Customer advances | D41: =SourceHistory!D42 -> 528.49323 | E41: =SourceHistory!E42 -> 254.24995 | F41: =SourceHistory!F42 -> 592.67224 | G41: =Monthly_BS!O26 -> 590.67747 | H41: =Monthly_BS!AA26 -> 612.10871 | I41: =Monthly_BS!AM26 -> 634.66259
C42: Borrowings and leases | D42: =SourceHistory!D43 -> 1000.0467 | E42: =SourceHistory!E43 -> 314.62101 | F42: =SourceHistory!F43 -> 800.77562 | G42: =Monthly_BS!O27+Monthly_BS!O28 -> 934.87669 | H42: =Monthly_BS!AA27+Monthly_BS!AA28 -> 739.19139 | I42: =Monthly_BS!AM27+Monthly_BS!AM28 -> 554.76439
C43: Taxes payable | D43: =SourceHistory!D44 -> 311.19085 | E43: =SourceHistory!E44 -> 393.46764 | F43: =SourceHistory!F44 -> 444.24881 | G43: =Monthly_BS!O29+Monthly_BS!O30 -> 132.89806 | H43: =Monthly_BS!AA29+Monthly_BS!AA30 -> 132.89806 | I43: =Monthly_BS!AM29+Monthly_BS!AM30 -> 132.89806
C44: Other liabilities incl DTL | D44: =SourceHistory!D46 -> 1405.4056 | E44: =SourceHistory!E46 -> 1264.6687 | F44: =SourceHistory!F46 -> 1454.5799 | G44: =Monthly_BS!O31+Monthly_BS!O32 -> 1494.7807 | H44: =Monthly_BS!AA31+Monthly_BS!AA32 -> 1494.7807 | I44: =Monthly_BS!AM31+Monthly_BS!AM32 -> 1494.7807
C45: Finance company deposits | D45: =SourceHistory!D45 -> 0 | E45: =SourceHistory!E45 -> 0 | F45: =SourceHistory!F45 -> 0 | G45: =Monthly_BS!O33 -> 0 | H45: =Monthly_BS!AA33 -> 0 | I45: =Monthly_BS!AM33 -> 0
C47: Total liabilities | D47: =SourceHistory!D47 -> 5301.7942 | E47: =SourceHistory!E47 -> 4619.0541 | F47: =SourceHistory!F47 -> 5747.6725 | G47: =Monthly_BS!O35 -> 5561.6312 | H47: =Monthly_BS!AA35 -> 5505.8411 | I47: =Monthly_BS!AM35 -> 5471.1891
C49: Retained earnings | D49: =SourceHistory!D48 -> 9383.7349 | E49: =SourceHistory!E48 -> 10808.301 | F49: =SourceHistory!F48 -> 11553.52 | G49: =Monthly_BS!O38 -> 12041.695 | H49: =Monthly_BS!AA38 -> 12620.222 | I49: =Monthly_BS!AM38 -> 13048.788
C50: Share capital and reserves | D50: =D52-D49-D51 -> 5062.1871 | E50: =E52-E49-E51 -> 5057.8144 | F50: =F52-F49-F51 -> 5244.0948 | G50: =Monthly_BS!O39 -> 4946.3842 | H50: =Monthly_BS!AA39 -> 4991.5887 | I50: =Monthly_BS!AM39 -> 5036.7933
C51: NCI equity | D51: =SourceHistory!D49 -> 14.489582 | E51: =SourceHistory!E49 -> 8.8646797 | F51: =SourceHistory!F49 -> 10.954817 | G51: =Monthly_BS!O40 -> 17.433269 | H51: =Monthly_BS!AA40 -> 17.325951 | I51: =Monthly_BS!AM40 -> 17.922826
C52: Total equity | D52: =SourceHistory!D50 -> 14460.412 | E52: =SourceHistory!E50 -> 15874.98 | F52: =SourceHistory!F50 -> 16808.57 | G52: =Monthly_BS!O42 -> 17005.512 | H52: =Monthly_BS!AA42 -> 17629.137 | I52: =Monthly_BS!AM42 -> 18103.504
C53: BS difference | D53: =D38-D47-D52 -> 0 | E53: =E38-E47-E52 -> 0 | F53: =F38-F47-F52 -> 0 | G53: =Monthly_BS!O44 -> 0 | H53: =Monthly_BS!AA44 -> 0 | I53: =Monthly_BS!AM44 -> 0
C56: Operating cash flow | D56: =SourceHistory!D24 -> 4827.2821 | E56: =SourceHistory!E24 -> 3730.3469 | F56: =SourceHistory!F24 -> 4743.6924 | G56: =H1Actual!D56+(SUM(Monthly_CF!J24:O24)) -> 3559.4628 | H56: =SUM(Monthly_CF!P24:AA24) -> 4061.6758 | I56: =SUM(Monthly_CF!AB24:AM24) -> 4091.7066
C57: Investing cash flow | D57: =SourceHistory!D25 -> -3434.3835 | E57: =SourceHistory!E25 -> -706.30976 | F57: =SourceHistory!F25 -> -2062.2526 | G57: =H1Actual!D57+(SUM(Monthly_CF!J34:O34)) -> 1574.6508 | H57: =SUM(Monthly_CF!P34:AA34) -> -104.6859 | I57: =SUM(Monthly_CF!AB34:AM34) -> -132.25607
C58: Financing cash flow | D58: =SourceHistory!D26 -> -1987.0462 | E58: =SourceHistory!E26 -> -3522.305 | F58: =SourceHistory!F26 -> -2798.8845 | G58: =H1Actual!D58+(SUM(Monthly_CF!J45:O45)) -> -3534.3633 | H58: =SUM(Monthly_CF!P45:AA45) -> -3775.3681 | I58: =SUM(Monthly_CF!AB45:AM45) -> -3921.2905
C59: FX on cash | D59: =SourceHistory!D27 -> 0.99063394 | E59: =SourceHistory!E27 -> 2.396099 | F59: =SourceHistory!F27 -> 2.1749313 | G59: =H1Actual!D59+(SUM(Monthly_CF!J47:O47)) -> -7.0988049 | H59: =SUM(Monthly_CF!P47:AA47) -> 0 | I59: =SUM(Monthly_CF!AB47:AM47) -> 0
C60: Opening cash | D60: =SourceHistory!D28 -> 1925.3432 | E60: =SourceHistory!E28 -> 1332.1862 | F60: =SourceHistory!F28 -> 836.3144 | G60: =H1Data!D108 -> 721.04459 | H60: =Monthly_CF!P50 -> 2313.6962 | I60: =Monthly_CF!AB50 -> 2495.3179
C61: Closing cash | D61: =SourceHistory!D29 -> 1332.1862 | E61: =SourceHistory!E29 -> 836.3144 | F61: =SourceHistory!F29 -> 721.04459 | G61: =Monthly_CF!O51 -> 2313.6962 | H61: =Monthly_CF!AA51 -> 2495.3179 | I61: =Monthly_CF!AM51 -> 2533.478
C62: Cash roll-forward difference | D62: =D60+SUM(D56:D59)-D61 -> 0 | E62: =E60+SUM(E56:E59)-E61 -> 0 | F62: =F60+SUM(F56:F59)-F61 -> 0 | G62: =G60+SUM(G56:G59)-G61 -> 0 | H62: =SUM(Monthly_CF!P62:AA62) -> 0 | I62: =SUM(Monthly_CF!AB62:AM62) -> 0
C64: Gross margin | D64: =D11/D9 -> 0.43202782 | E64: =E11/E9 -> 0.43247166 | F64: =F11/F9 -> 0.43136098 | G64: =G11/G9 -> 0.40337368 | H64: =H11/H9 -> 0.41368572 | I64: =I11/I9 -> 0.40410001
C68: Historical noncore classifications are inherited source mappings; detailed forecast ECL/impairment is not retroactively fabricated. Forecasts are rebuilt from monthly operations and may differ from the prior annual model.

Sheet Monthly_PL
C2: 公牛集团 Monthly_PL
C3: RMB million except stated units. H1 2026 actual aggregate is separate; monthly forecast begins July 2026.
D6: Not disclosed | E6: Not disclosed | F6: Not disclosed | G6: Not disclosed | H6: Not disclosed | I6: 2026H1A / 30-Jun | J6: Forecast | K6: Forecast | L6: Forecast | M6: Forecast | N6: Forecast | O6: Forecast | P6: Forecast | Q6: Forecast | R6: Forecast | S6: Forecast | T6: Forecast | U6: Forecast | V6: Forecast | W6: Forecast | X6: Forecast | Y6: Forecast | Z6: Forecast | AA6: Forecast | AB6: Forecast | AC6: Forecast | AD6: Forecast | AE6: Forecast | AF6: Forecast | AG6: Forecast | AH6: Forecast | AI6: Forecast | AJ6: Forecast | AK6: Forecast | AL6: Forecast | AM6: Forecast
D7: 46053 | E7: 46081 | F7: 46112 | G7: 46142 | H7: 46173 | I7: 46203 | J7: 46234 | K7: 46265 | L7: 46295 | M7: 46326 | N7: 46356 | O7: 46387 | P7: 46418 | Q7: 46446 | R7: 46477 | S7: 46507 | T7: 46538 | U7: 46568 | V7: 46599 | W7: 46630 | X7: 46660 | Y7: 46691 | Z7: 46721 | AA7: 46752 | AB7: 46783 | AC7: 46812 | AD7: 46843 | AE7: 46873 | AF7: 46904 | AG7: 46934 | AH7: 46965 | AI7: 46996 | AJ7: 47026 | AK7: 47057 | AL7: 47087 | AM7: 47118
C10: Revenue | I10: =H1Data!D83 -> 8393.7911 | J10: =Revenue!J40 -> 1356.5576 | K10: =Revenue!K40 -> 1356.5576 | L10: =Revenue!L40 -> 1356.5576 | M10: =Revenue!M40 -> 1356.5576 | N10: =Revenue!N40 -> 1356.5576 | O10: =Revenue!O40 -> 1356.5576 | P10: =Revenue!P40 -> 1448.8412 | Q10: =Revenue!Q40 -> 1448.8412 | ... AM10: =Revenue!AM40 -> 1457.5744
C11: Cost of goods released from FG | J11: =Production!J88 -> 934.96438 | K11: =Production!K88 -> 849.74845 | L11: =Production!L88 -> 811.31093 | M11: =Production!M88 -> 797.21891 | N11: =Production!N88 -> 788.59336 | O11: =Production!O88 -> 786.86144 | P11: =Production!P88 -> 841.68936 | Q11: =Production!Q88 -> 841.92267 | ... AM11: =Production!AM88 -> 870.90581
C12: Unabsorbed manufacturing cost | J12: =Production!J90 -> 0 | K12: =Production!K90 -> 0 | L12: =Production!L90 -> 0 | M12: =Production!M90 -> 0 | N12: =Production!N90 -> 0 | O12: =Production!O90 -> 0 | P12: =Production!P90 -> 0 | Q12: =Production!Q90 -> 0 | ... AM12: =Production!AM90 -> 0
C13: Other-business COGS | J13: =ExpenseDetail!J62 -> 0.45875339 | K13: =ExpenseDetail!K62 -> 0.45875339 | L13: =ExpenseDetail!L62 -> 0.45875339 | M13: =ExpenseDetail!M62 -> 0.45875339 | N13: =ExpenseDetail!N62 -> 0.45875339 | O13: =ExpenseDetail!O62 -> 0.45875339 | P13: =ExpenseDetail!P62 -> 2.8642473 | Q13: =ExpenseDetail!Q62 -> 2.8642473 | ... AM13: =ExpenseDetail!AM62 -> 0.45875339
C14: Total COGS | I14: =H1Data!D84 -> 4892.6546 | J14: =SUM(J11:J13) -> 935.42313 | K14: =SUM(K11:K13) -> 850.2072 | L14: =SUM(L11:L13) -> 811.76968 | M14: =SUM(M11:M13) -> 797.67766 | N14: =SUM(N11:N13) -> 789.05211 | O14: =SUM(O11:O13) -> 787.32019 | P14: =SUM(P11:P13) -> 844.5536 | Q14: =SUM(Q11:Q13) -> 844.78692 | ... AM14: =SUM(AM11:AM13) -> 871.36456
C15: Gross profit | I15: =H1Data!D83-H1Data!D84 -> 3501.1365 | J15: =J10-J14 -> 421.13451 | K15: =K10-K14 -> 506.35044 | L15: =L10-L14 -> 544.78796 | M15: =M10-M14 -> 558.87998 | N15: =N10-N14 -> 567.50553 | O15: =O10-O14 -> 569.23746 | P15: =P10-P14 -> 604.28759 | Q15: =Q10-Q14 -> 604.05427 | ... AM15: =AM10-AM14 -> 586.20989
C16: Gross margin | I16: =I15/I10 -> 0.41711027 | J16: =IF(J10=0,0,J15/J10) -> 0.31044351 | K16: =IF(K10=0,0,K15/K10) -> 0.37326128 | L16: =IF(L10=0,0,L15/L10) -> 0.40159588 | M16: =IF(M10=0,0,M15/M10) -> 0.41198396 | N16: =IF(N10=0,0,N15/N10) -> 0.41834236 | O16: =IF(O10=0,0,O15/O10) -> 0.41961907 | P16: =IF(P10=0,0,P15/P10) -> 0.41708338 | Q16: =IF(Q10=0,0,Q15/Q10) -> 0.41692235 | ... AM16: =IF(AM10=0,0,AM15/AM10) -> 0.40218178
C18: Selling expenses by nature | I18: =H1Data!D85 -> 584.11762 | J18: =ExpenseDetail!J17 -> 100.56811 | K18: =ExpenseDetail!K17 -> 100.56811 | L18: =ExpenseDetail!L17 -> 100.56811 | M18: =ExpenseDetail!M17 -> 100.56811 | N18: =ExpenseDetail!N17 -> 100.56811 | O18: =ExpenseDetail!O17 -> 100.56811 | P18: =ExpenseDetail!P17 -> 104.98134 | Q18: =ExpenseDetail!Q17 -> 104.98134 | ... AM18: =ExpenseDetail!AM17 -> 106.57812
C19: Administrative expenses by nature | I19: =H1Data!D86 -> 305.54311 | J19: =ExpenseDetail!J31 -> 60.136822 | K19: =ExpenseDetail!K31 -> 60.206488 | L19: =ExpenseDetail!L31 -> 60.276154 | M19: =ExpenseDetail!M31 -> 60.34582 | N19: =ExpenseDetail!N31 -> 60.415486 | O19: =ExpenseDetail!O31 -> 60.485152 | P19: =ExpenseDetail!P31 -> 61.767488 | Q19: =ExpenseDetail!Q31 -> 61.840637 | ... AM19: =ExpenseDetail!AM31 -> 64.322447
C20: R&D expenses by nature | I20: =H1Data!D87 -> 286.28158 | J20: =ExpenseDetail!J39 -> 54.911311 | K20: =ExpenseDetail!K39 -> 54.920963 | L20: =ExpenseDetail!L39 -> 54.930615 | M20: =ExpenseDetail!M39 -> 54.940268 | N20: =ExpenseDetail!N39 -> 54.94992 | O20: =ExpenseDetail!O39 -> 54.959572 | P20: =ExpenseDetail!P39 -> 57.125277 | Q20: =ExpenseDetail!Q39 -> 57.135412 | ... AM20: =ExpenseDetail!AM39 -> 58.531193
C21: Business taxes and surcharges | I21: =H1Data!D88 -> 76.482317 | J21: =ExpenseDetail!J61 -> 12.995537 | K21: =ExpenseDetail!K61 -> 12.995537 | L21: =ExpenseDetail!L61 -> 12.995537 | M21: =ExpenseDetail!M61 -> 12.995537 | N21: =ExpenseDetail!N61 -> 12.995537 | O21: =ExpenseDetail!O61 -> 12.995537 | P21: =ExpenseDetail!P61 -> 13.879594 | Q21: =ExpenseDetail!Q61 -> 13.879594 | ... AM21: =ExpenseDetail!AM61 -> 13.963257
C22: Credit impairment expense / (release) | I22: =-H1Data!D94 -> -0.11522692 | J22: =Receivables!J16 -> 0.56120476 | K22: =Receivables!K16 -> 0 | L22: =Receivables!L16 -> 0.90433539 | M22: =Receivables!M16 -> -0.90433539 | N22: =Receivables!N16 -> 0.90433539 | O22: =Receivables!O16 -> -0.90433539 | P22: =Receivables!P16 -> 1.8455967 | Q22: =Receivables!Q16 -> 3.1045348 | ... AM22: =Receivables!AM16 -> -0.97167721
C23: Asset impairment expense | I23: =H1Data!D95 -> 14.202526 | J23: =Assets!J103 -> 0 | K23: =Assets!K103 -> 0 | L23: =Assets!L103 -> 0 | M23: =Assets!M103 -> 0 | N23: =Assets!N103 -> 0 | O23: =Assets!O103 -> 0 | P23: =Assets!P103 -> 0 | Q23: =Assets!Q103 -> 0 | ... AM23: =Assets!AM103 -> 0
C24: Other pretax income / (expense) | I24: =H1Data!D92-H1Data!D96+H1Data!D97-H1Data!D98 -> 69.741335 | J24: =J10*Inputs!J80 -> 16.747859 | K24: =K10*Inputs!K80 -> 16.747859 | L24: =L10*Inputs!L80 -> 16.747859 | M24: =M10*Inputs!M80 -> 16.747859 | N24: =N10*Inputs!N80 -> 16.747859 | O24: =O10*Inputs!O80 -> 16.747859 | P24: =P10*Inputs!P80 -> 17.887178 | Q24: =Q10*Inputs!Q80 -> 17.887178 | ... AM24: =AM10*Inputs!AM80 -> 17.994997
C25: Investment cash income | I25: =H1Data!D93 -> 257.05764 | J25: =Funding!J59 -> 37.940387 | K25: =Funding!K59 -> 37.940387 | L25: =Funding!L59 -> 36.716504 | M25: =Funding!M59 -> 37.940387 | N25: =Funding!N59 -> 36.716504 | O25: =Funding!O59 -> 37.940387 | P25: =Funding!P59 -> 37.940387 | Q25: =Funding!Q59 -> 34.268737 | ... AM25: =Funding!AM59 -> 37.836725
C26: Investment FV gain/(loss) | J26: =Funding!J56 -> 0 | K26: =Funding!K56 -> 0 | L26: =Funding!L56 -> 0 | M26: =Funding!M56 -> 0 | N26: =Funding!N56 -> 0 | O26: =Funding!O56 -> 0 | P26: =Funding!P56 -> 0 | Q26: =Funding!Q56 -> 0 | ... AM26: =Funding!AM56 -> 0
C27: Monetary interest income | I27: =H1Data!D91 -> 45.193908 | J27: =Funding!J62 -> 8.6108962 | K27: =Funding!K62 -> 8.7649146 | L27: =Funding!L62 -> 9.1748728 | M27: =Funding!M62 -> 9.6570178 | N27: =Funding!N62 -> 9.6230686 | O27: =Funding!O62 -> 11.120156 | P27: =Funding!P62 -> 10.992375 | Q27: =Funding!Q62 -> 11.340942 | ... AM27: =Funding!AM62 -> 11.565178
C28: Finance costs excluding interest income | I28: =H1Data!D89+H1Data!D91 -> 10.648267 | J28: =Funding!J67+Funding!J49 -> 4.1053422 | K28: =Funding!K67+Funding!K49 -> 4.1010741 | L28: =Funding!L67+Funding!L49 -> 3.964651 | M28: =Funding!M67+Funding!M49 -> 4.0925379 | N28: =Funding!N67+Funding!N49 -> 3.9563902 | O28: =Funding!O67+Funding!O49 -> 4.0840017 | P28: =Funding!P67+Funding!P49 -> 4.0797336 | Q28: =Funding!Q67+Funding!Q49 -> 3.6810656 | ... AM28: =Funding!AM67+Funding!AM49 -> 2.4153845
C29: Profit before tax | I29: =H1Data!D99 -> 2595.9692 | J29: =J15-SUM(J18:J23)+SUM(J24:J27)-J28 -> 251.15533 | K29: =K15-SUM(K18:K23)+SUM(K24:K27)-K28 -> 337.01144 | L29: =L15-SUM(L18:L23)+SUM(L24:L27)-L28 -> 373.7878 | M29: =M15-SUM(M18:M23)+SUM(M24:M27)-M28 -> 391.18732 | N29: =N15-SUM(N18:N23)+SUM(N24:N27)-N28 -> 396.80319 | O29: =O15-SUM(O18:O23)+SUM(O24:O27)-O28 -> 402.85783 | P29: =P15-SUM(P18:P23)+SUM(P24:P27)-P28 -> 427.4285 | Q29: =Q15-SUM(Q18:Q23)+SUM(Q24:Q27)-Q28 -> 422.92854 | ... AM29: =AM15-SUM(AM18:AM23)+SUM(AM24:AM27)-AM28 -> 408.76807
C30: Income-tax expense | I30: =H1Data!D100 -> 440.96975 | J30: =TaxEquity!J24 -> 44.113264 | K30: =TaxEquity!K24 -> 59.193146 | L30: =TaxEquity!L24 -> 65.652596 | M30: =TaxEquity!M24 -> 68.708671 | N30: =TaxEquity!N24 -> 69.695051 | O30: =TaxEquity!O24 -> 70.758495 | P30: =TaxEquity!P24 -> 75.074122 | Q30: =TaxEquity!Q24 -> 74.283744 | ... AM30: =TaxEquity!AM24 -> 71.796578
C31: Consolidated net income | I31: =H1Data!D101 -> 2154.9994 | J31: =J29-J30 -> 207.04207 | K31: =K29-K30 -> 277.81829 | L31: =L29-L30 -> 308.1352 | M31: =M29-M30 -> 322.47864 | N31: =N29-N30 -> 327.10814 | O31: =O29-O30 -> 332.09933 | P31: =P29-P30 -> 352.35438 | Q31: =Q29-Q30 -> 348.6448 | ... AM31: =AM29-AM30 -> 336.97149
C32: Parent net income | I32: =H1Data!D102 -> 2150.9892 | J32: =J31-J33 -> 206.75412 | K32: =K31-K33 -> 277.4319 | L32: =L31-L33 -> 307.70665 | M32: =M31-M33 -> 322.03014 | N32: =N31-N33 -> 326.6532 | O32: =O31-O33 -> 331.63745 | P32: =P31-P33 -> 351.86433 | Q32: =Q31-Q33 -> 348.15991 | ... AM32: =AM31-AM33 -> 336.50283
C33: NCI net income | I33: =H1Data!D103 -> 4.0102411 | J33: =J31*SourceHistory!F22/SourceHistory!F20 -> 0.28795222 | K33: =K31*SourceHistory!F22/SourceHistory!F20 -> 0.38638714 | L33: =L31*SourceHistory!F22/SourceHistory!F20 -> 0.42855163 | M33: =M31*SourceHistory!F22/SourceHistory!F20 -> 0.44850035 | N33: =N31*SourceHistory!F22/SourceHistory!F20 -> 0.45493901 | O33: =O31*SourceHistory!F22/SourceHistory!F20 -> 0.46188072 | P33: =P31*SourceHistory!F22/SourceHistory!F20 -> 0.49005125 | Q33: =Q31*SourceHistory!F22/SourceHistory!F20 -> 0.48489201 | R33: =R31*SourceHistory!F22/SourceHistory!F20 -> 0.49181979 | S33: =S31*SourceHistory!F22/SourceHistory!F20 -> 0.48537355 | T33: =T31*SourceHistory!F22/SourceHistory!F20 -> 0.48946009 | U33: =U31*SourceHistory!F22/SourceHistory!F20 -> 0.48701434 | V33: =V31*SourceHistory!F22/SourceHistory!F20 -> 0.46590835 | W33: =W31*SourceHistory!F22/SourceHistory!F20 -> 0.46387626 | X33: =X31*SourceHistory!F22/SourceHistory!F20 -> 0.46440787 | Y33: =Y31*SourceHistory!F22/SourceHistory!F20 -> 0.46713397 | Z33: =Z31*SourceHistory!F22/SourceHistory!F20 -> 0.46497742 | AA33: =AA31*SourceHistory!F22/SourceHistory!F20 -> 0.46837406 | AB33: =AB31*SourceHistory!F22/SourceHistory!F20 -> 0.49437733 | AC33: =AC31*SourceHistory!F22/SourceHistory!F20 -> 0.48999091 | AD33: =AD31*SourceHistory!F22/SourceHistory!F20 -> 0.49370187 | AE33: =AE31*SourceHistory!F22/SourceHistory!F20 -> 0.48836538 | AF33: =AF31*SourceHistory!F22/SourceHistory!F20 -> 0.49201019 | AG33: =AG31*SourceHistory!F22/SourceHistory!F20 -> 0.48934677 | AH33: =AH31*SourceHistory!F22/SourceHistory!F20 -> 0.46779887 | AI33: =AI31*SourceHistory!F22/SourceHistory!F20 -> 0.46562969 | AJ33: =AJ31*SourceHistory!F22/SourceHistory!F20 -> 0.46508996 | AK33: =AK31*SourceHistory!F22/SourceHistory!F20 -> 0.46760275 | AL33: =AL31*SourceHistory!F22/SourceHistory!F20 -> 0.46526501 | AM33: =AM31*SourceHistory!F22/SourceHistory!F20 -> 0.46865687
C35: Total D&A (memo) | J35: =Assets!J100 -> 26.380476 | K35: =Assets!K100 -> 26.591641 | L35: =Assets!L100 -> 26.802806 | M35: =Assets!M100 -> 27.013971 | N35: =Assets!N100 -> 27.225136 | O35: =Assets!O100 -> 27.436302 | P35: =Assets!P100 -> 27.647467 | Q35: =Assets!Q100 -> 27.86919 | ... AM35: =Assets!AM100 -> 31.609107
C36: EBITDA calculation proxy | J36: =J29+J28-J27+J35 -> 273.03025 | K36: =K29+K28-K27+K35 -> 358.93924 | L36: =L29+L28-L27+L35 -> 395.38038 | M36: =M29+M28-M27+M35 -> 412.63681 | N36: =N29+N28-N27+N35 -> 418.36165 | O36: =O29+O28-O27+O35 -> 423.25797 | P36: =P29+P28-P27+P35 -> 448.16332 | Q36: =Q29+Q28-Q27+Q35 -> 443.13786 | ... AM36: =AM29+AM28-AM27+AM35 -> 431.22738
C37: H1 finance costs exclude interest income and include other finance charges; forecast costs here are loan/lease/RCF interest. H1 asset impairment includes inventory and contract-performance costs. Forecast other pretax income uses a separately stated cash assumption.
C41: EBITDA is a calculation proxy, not an issuer-defined KPI; it includes investment/other pretax income. Monthly positive-profit tax accrual does not model entity-level loss carryforwards. Interim revenue anchors do not make the monthly P&L an actual management account.

Sheet Monthly_BS
C2: 公牛集团 Monthly_BS
C3: RMB million except stated units. H1 2026 actual aggregate is separate; monthly forecast begins July 2026.
D6: Not disclosed | E6: Not disclosed | F6: Not disclosed | G6: Not disclosed | H6: Not disclosed | I6: 2026H1A / 30-Jun | J6: Forecast | K6: Forecast | L6: Forecast | M6: Forecast | N6: Forecast | O6: Forecast | P6: Forecast | Q6: Forecast | R6: Forecast | S6: Forecast | T6: Forecast | U6: Forecast | V6: Forecast | W6: Forecast | X6: Forecast | Y6: Forecast | Z6: Forecast | AA6: Forecast | AB6: Forecast | AC6: Forecast | AD6: Forecast | AE6: Forecast | AF6: Forecast | AG6: Forecast | AH6: Forecast | AI6: Forecast | AJ6: Forecast | AK6: Forecast | AL6: Forecast | AM6: Forecast
D7: 46053 | E7: 46081 | F7: 46112 | G7: 46142 | H7: 46173 | I7: 46203 | J7: 46234 | K7: 46265 | L7: 46295 | M7: 46326 | N7: 46356 | O7: 46387 | P7: 46418 | Q7: 46446 | R7: 46477 | S7: 46507 | T7: 46538 | U7: 46568 | V7: 46599 | W7: 46630 | X7: 46660 | Y7: 46691 | Z7: 46721 | AA7: 46752 | AB7: 46783 | AC7: 46812 | AD7: 46843 | AE7: 46873 | AF7: 46904 | AG7: 46934 | AH7: 46965 | AI7: 46996 | AJ7: 47026 | AK7: 47057 | AL7: 47087 | AM7: 47118
C10: Cash and cash equivalents | I10: =H1Data!D9 -> 1058.4987 | J10: =Monthly_CF!J51 -> 1139.6766 | K10: =Monthly_CF!K51 -> 1516.9441 | L10: =Monthly_CF!L51 -> 1609.8743 | M10: =Monthly_CF!M51 -> 1761.0473 | N10: =Monthly_CF!N51 -> 2381.0452 | O10: =Monthly_CF!O51 -> 2313.6962 | P10: =Monthly_CF!P51 -> 3137.8529 | Q10: =Monthly_CF!Q51 -> 3861.9133 | ... AM10: =Monthly_CF!AM51 -> 2533.478
C11: Other monetary balances outside CE | I11: =H1Data!D11 -> 3480.0156 | J11: =H1Data!D11 -> 3480.0156 | K11: =H1Data!D11 -> 3480.0156 | L11: =H1Data!D11 -> 3480.0156 | M11: =H1Data!D11 -> 3480.0156 | N11: =H1Data!D11 -> 3480.0156 | O11: =H1Data!D11 -> 3480.0156 | P11: =H1Data!D11 -> 3480.0156 | Q11: =H1Data!D11 -> 3480.0156 | R11: =H1Data!D11 -> 3480.0156 | S11: =H1Data!D11 -> 3480.0156 | T11: =H1Data!D11 -> 3480.0156 | U11: =H1Data!D11 -> 3480.0156 | V11: =H1Data!D11 -> 3480.0156 | W11: =H1Data!D11 -> 3480.0156 | X11: =H1Data!D11 -> 3480.0156 | Y11: =H1Data!D11 -> 3480.0156 | Z11: =H1Data!D11 -> 3480.0156 | AA11: =H1Data!D11 -> 3480.0156 | AB11: =H1Data!D11 -> 3480.0156 | AC11: =H1Data!D11 -> 3480.0156 | AD11: =H1Data!D11 -> 3480.0156 | AE11: =H1Data!D11 -> 3480.0156 | AF11: =H1Data!D11 -> 3480.0156 | AG11: =H1Data!D11 -> 3480.0156 | AH11: =H1Data!D11 -> 3480.0156 | AI11: =H1Data!D11 -> 3480.0156 | AJ11: =H1Data!D11 -> 3480.0156 | AK11: =H1Data!D11 -> 3480.0156 | AL11: =H1Data!D11 -> 3480.0156 | AM11: =H1Data!D11 -> 3480.0156
C12: Trade receivables net / bills / contract assets | I12: =H1Data!D17+H1Data!D16+H1Data!D19 -> 330.98513 | J12: =Receivables!J19 -> 326.36872 | K12: =Receivables!K19 -> 326.36872 | L12: =Receivables!L19 -> 336.57792 | M12: =Receivables!M19 -> 326.36872 | N12: =Receivables!N19 -> 336.57792 | O12: =Receivables!O19 -> 326.36872 | P12: =Receivables!P19 -> 347.20399 | Q12: =Receivables!Q19 -> 382.25164 | ... AM12: =Receivables!AM19 -> 349.17574
C13: Inventories by category | I13: =H1Data!D22 -> 1636.9642 | J13: =Inventory!J30 -> 1485.8057 | K13: =Inventory!K30 -> 1418.6729 | L13: =Inventory!L30 -> 1415.2734 | M13: =Inventory!M30 -> 1373.4713 | N13: =Inventory!N30 -> 1395.6786 | O13: =Inventory!O30 -> 1364.4977 | P13: =Inventory!P30 -> 1424.0643 | Q13: =Inventory!Q30 -> 1512.0266 | ... AM13: =Inventory!AM30 -> 1452.0644
C14: PPE/CIP/investment property group | I14: =H1Data!D24+H1Data!D25 -> 3591.9678 | J14: =Assets!J99 -> 3608.0523 | K14: =Assets!K99 -> 3623.962 | L14: =Assets!L99 -> 3639.6971 | M14: =Assets!M99 -> 3655.2574 | N14: =Assets!N99 -> 3670.6431 | O14: =Assets!O99 -> 3685.854 | P14: =Assets!P99 -> 3702.8596 | Q14: =Assets!Q99 -> 3719.6817 | ... AM14: =Assets!AM99 -> 4067.5683
C15: Intangible and deferred cost group | I15: =H1Data!D27+H1Data!D28 -> 349.0746 | J15: =Assets!J76 -> 351.63179 | K15: =Assets!K76 -> 354.15252 | L15: =Assets!L76 -> 356.63678 | M15: =Assets!M76 -> 359.08457 | N15: =Assets!N76 -> 361.49589 | O15: =Assets!O76 -> 363.87075 | P15: =Assets!P76 -> 366.42794 | Q15: =Assets!Q76 -> 368.94685 | ... AM15: =Assets!AM76 -> 417.30554
C16: ROU assets | I16: =H1Data!D26 -> 17.655538 | J16: =Assets!J88 -> 16.395592 | K16: =Assets!K88 -> 15.135646 | L16: =Assets!L88 -> 13.8757 | M16: =Assets!M88 -> 12.615754 | N16: =Assets!N88 -> 11.355807 | O16: =Assets!O88 -> 10.095861 | P16: =Assets!P88 -> 8.835915 | Q16: =Assets!Q88 -> 7.5759688 | ... AM16: =Assets!AM88 -> 0
C17: Financial investments | I17: =H1Data!D12 -> 10538.02 | J17: =Funding!J58 -> 10538.02 | K17: =Funding!K58 -> 10538.02 | L17: =Funding!L58 -> 10538.02 | M17: =Funding!M58 -> 10538.02 | N17: =Funding!N58 -> 10538.02 | O17: =Funding!O58 -> 10538.02 | P17: =Funding!P58 -> 10538.02 | Q17: =Funding!Q58 -> 10538.02 | ... AM17: =Funding!AM58 -> 10538.02
C18: Named other assets excluding DTA | I18: =H1Data!D20+H1Data!D21+H1Data!D23+H1Data!D30 -> 186.15963 | J18: =OtherBalances!J19 -> 186.15963 | K18: =OtherBalances!K19 -> 186.15963 | L18: =OtherBalances!L19 -> 186.15963 | M18: =OtherBalances!M19 -> 186.15963 | N18: =OtherBalances!N19 -> 186.15963 | O18: =OtherBalances!O19 -> 186.15963 | P18: =OtherBalances!P19 -> 186.15963 | Q18: =OtherBalances!Q19 -> 186.15963 | ... AM18: =OtherBalances!AM19 -> 186.15963
C19: Post-2025 accrued interest cohort | J19: =OtherBalances!J45 -> 7.9957033 | K19: =OtherBalances!K45 -> 16.134421 | L19: =OtherBalances!L45 -> 24.653809 | M19: =OtherBalances!M45 -> 33.620895 | N19: =OtherBalances!N45 -> 42.556458 | O19: =OtherBalances!O45 -> 52.88215 | P19: =OtherBalances!P45 -> 63.089191 | Q19: =OtherBalances!Q45 -> 73.619896 | ... AM19: =OtherBalances!AM45 -> 305.22273
C20: DTA | I20: =H1Data!D29 -> 245.68298 | J20: =TaxEquity!J18 -> 245.68298 | K20: =TaxEquity!K18 -> 245.68298 | L20: =TaxEquity!L18 -> 245.68298 | M20: =TaxEquity!M18 -> 245.68298 | N20: =TaxEquity!N18 -> 245.68298 | O20: =TaxEquity!O18 -> 245.68298 | P20: =TaxEquity!P18 -> 245.68298 | Q20: =TaxEquity!Q18 -> 245.68298 | ... AM20: =TaxEquity!AM18 -> 245.68298
C22: Total assets | I22: =H1Data!D31 -> 21435.024 | J22: =SUM(J10:J20) -> 21385.805 | K22: =SUM(K10:K20) -> 21721.249 | L22: =SUM(L10:L20) -> 21846.467 | M22: =SUM(M10:M20) -> 21971.344 | N22: =SUM(N10:N20) -> 22649.231 | O22: =SUM(O10:O20) -> 22567.144 | P22: =SUM(P10:P20) -> 23500.212 | Q22: =SUM(Q10:Q20) -> 24375.894 | ... AM22: =SUM(AM10:AM20) -> 23574.693
C25: Goods/construction/expense payables | I25: =H1Data!D36 -> 2564.4435 | J25: =Receivables!J30 -> 2502.1074 | K25: =Receivables!K30 -> 2497.8895 | L25: =Receivables!L30 -> 2657.6696 | M25: =Receivables!M30 -> 2408.3982 | N25: =Receivables!N30 -> 2667.1426 | O25: =Receivables!O30 -> 2408.3982 | P25: =Receivables!P30 -> 2871.2055 | Q25: =Receivables!Q30 -> 3253.7166 | ... AM25: =Receivables!AM30 -> 2654.0833
C26: Customer advances | I26: =H1Data!D40 -> 831.36657 | J26: =Receivables!J40 -> 590.67747 | K26: =Receivables!K40 -> 590.67747 | L26: =Receivables!L40 -> 610.36672 | M26: =Receivables!M40 -> 590.67747 | N26: =Receivables!N40 -> 610.36672 | O26: =Receivables!O40 -> 590.67747 | P26: =Receivables!P40 -> 630.85992 | Q26: =Receivables!Q40 -> 698.45205 | ... AM26: =Receivables!AM40 -> 634.66259
C27: Loan principal and historic accrued interest | I27: =H1Data!D32+H1Data!D47 -> 923.61839 | J27: =Funding!J68 -> 923.61839 | K27: =Funding!K68 -> 923.61839 | L27: =Funding!L68 -> 923.61839 | M27: =Funding!M68 -> 923.61839 | N27: =Funding!N68 -> 923.61839 | O27: =Funding!O68 -> 923.61839 | P27: =Funding!P68 -> 923.61839 | Q27: =Funding!Q68 -> 923.61839 | ... AM27: =Funding!AM68 -> 554.76439
C28: Lease liabilities | I28: =H1Data!D45+H1Data!D48 -> 17.958773 | J28: =Funding!J48 -> 16.842029 | K28: =Funding!K48 -> 15.725284 | L28: =Funding!L48 -> 14.608539 | M28: =Funding!M48 -> 13.491795 | N28: =Funding!N48 -> 12.37505 | O28: =Funding!O48 -> 11.258306 | P28: =Funding!P48 -> 10.141561 | Q28: =Funding!Q48 -> 9.0248167 | ... AM28: =Funding!AM48 -> 0
C29: Income-tax payable | I29: =H1Data!D43 -> 261.72983 | J29: =TaxEquity!J13 -> 305.84309 | K29: =TaxEquity!K13 -> 365.03624 | L29: =TaxEquity!L13 -> 0 | M29: =TaxEquity!M13 -> 68.708671 | N29: =TaxEquity!N13 -> 138.40372 | O29: =TaxEquity!O13 -> 0 | P29: =TaxEquity!P13 -> 75.074122 | Q29: =TaxEquity!Q13 -> 149.35787 | ... AM29: =TaxEquity!AM13 -> 0
C30: Other taxes payable | I30: =H1Data!D42-H1Data!D43 -> 132.89806 | J30: =TaxEquity!J26 -> 132.89806 | K30: =TaxEquity!K26 -> 132.89806 | L30: =TaxEquity!L26 -> 132.89806 | M30: =TaxEquity!M26 -> 132.89806 | N30: =TaxEquity!N26 -> 132.89806 | O30: =TaxEquity!O26 -> 132.89806 | P30: =TaxEquity!P26 -> 132.89806 | Q30: =TaxEquity!Q26 -> 132.89806 | ... AM30: =TaxEquity!AM26 -> 132.89806
C31: Named other liabilities excluding DTL | I31: =H1Data!D41+H1Data!D44+H1Data!D46+H1Data!D49+H1Data!D51+H1Data!D35 -> 1408.6786 | J31: =OtherBalances!J39 -> 1408.6786 | K31: =OtherBalances!K39 -> 1408.6786 | L31: =OtherBalances!L39 -> 1408.6786 | M31: =OtherBalances!M39 -> 1408.6786 | N31: =OtherBalances!N39 -> 1408.6786 | O31: =OtherBalances!O39 -> 1408.6786 | P31: =OtherBalances!P39 -> 1408.6786 | Q31: =OtherBalances!Q39 -> 1408.6786 | ... AM31: =OtherBalances!AM39 -> 1408.6786
C32: DTL | I32: =H1Data!D50 -> 86.102097 | J32: =TaxEquity!J22 -> 86.102097 | K32: =TaxEquity!K22 -> 86.102097 | L32: =TaxEquity!L22 -> 86.102097 | M32: =TaxEquity!M22 -> 86.102097 | N32: =TaxEquity!N22 -> 86.102097 | O32: =TaxEquity!O22 -> 86.102097 | P32: =TaxEquity!P22 -> 86.102097 | Q32: =TaxEquity!Q22 -> 86.102097 | ... AM32: =TaxEquity!AM22 -> 86.102097
C33: Finance-company deposits source balance | J33: =SourceHistory!F45 -> 0 | K33: =SourceHistory!F45 -> 0 | L33: =SourceHistory!F45 -> 0 | M33: =SourceHistory!F45 -> 0 | N33: =SourceHistory!F45 -> 0 | O33: =SourceHistory!F45 -> 0 | P33: =SourceHistory!F45 -> 0 | Q33: =SourceHistory!F45 -> 0 | R33: =SourceHistory!F45 -> 0 | S33: =SourceHistory!F45 -> 0 | T33: =SourceHistory!F45 -> 0 | U33: =SourceHistory!F45 -> 0 | V33: =SourceHistory!F45 -> 0 | W33: =SourceHistory!F45 -> 0 | X33: =SourceHistory!F45 -> 0 | Y33: =SourceHistory!F45 -> 0 | Z33: =SourceHistory!F45 -> 0 | AA33: =SourceHistory!F45 -> 0 | AB33: =SourceHistory!F45 -> 0 | AC33: =SourceHistory!F45 -> 0 | AD33: =SourceHistory!F45 -> 0 | AE33: =SourceHistory!F45 -> 0 | AF33: =SourceHistory!F45 -> 0 | AG33: =SourceHistory!F45 -> 0 | AH33: =SourceHistory!F45 -> 0 | AI33: =SourceHistory!F45 -> 0 | AJ33: =SourceHistory!F45 -> 0 | AK33: =SourceHistory!F45 -> 0 | AL33: =SourceHistory!F45 -> 0 | AM33: =SourceHistory!F45 -> 0
C35: Total liabilities | I35: =H1Data!D52 -> 6226.7958 | J35: =SUM(J25:J33) -> 5966.7671 | K35: =SUM(K25:K33) -> 6020.6256 | L35: =SUM(L25:L33) -> 5833.942 | M35: =SUM(M25:M33) -> 5632.5734 | N35: =SUM(N25:N33) -> 5979.5852 | O35: =SUM(O25:O33) -> 5561.6312 | P35: =SUM(P25:P33) -> 6138.5783 | Q35: =SUM(Q25:Q33) -> 6661.8485 | ... AM35: =SUM(AM25:AM33) -> 5471.1891
C38: Retained earnings | I38: =H1Data!D58 -> 10269.482 | J38: =TaxEquity!J35 -> 10476.236 | K38: =TaxEquity!K35 -> 10753.668 | L38: =TaxEquity!L35 -> 11061.374 | M38: =TaxEquity!M35 -> 11383.404 | N38: =TaxEquity!N35 -> 11710.058 | O38: =TaxEquity!O35 -> 12041.695 | P38: =TaxEquity!P35 -> 12393.559 | Q38: =TaxEquity!Q35 -> 12741.719 | ... AM38: =TaxEquity!AM35 -> 13048.788
C39: Share capital and reserves | I39: =H1Data!D53+H1Data!D54-H1Data!D55+H1Data!D56+H1Data!D57 -> 4923.7819 | J39: =TaxEquity!J46 -> 4927.549 | K39: =TaxEquity!K46 -> 4931.316 | L39: =TaxEquity!L46 -> 4935.0831 | M39: =TaxEquity!M46 -> 4938.8501 | N39: =TaxEquity!N46 -> 4942.6171 | O39: =TaxEquity!O46 -> 4946.3842 | P39: =TaxEquity!P46 -> 4950.1512 | Q39: =TaxEquity!Q46 -> 4953.9183 | ... AM39: =TaxEquity!AM46 -> 5036.7933
C40: NCI equity | I40: =H1Data!D59 -> 14.965058 | J40: =TaxEquity!J39 -> 15.25301 | K40: =TaxEquity!K39 -> 15.639397 | L40: =TaxEquity!L39 -> 16.067949 | M40: =TaxEquity!M39 -> 16.516449 | N40: =TaxEquity!N39 -> 16.971388 | O40: =TaxEquity!O39 -> 17.433269 | P40: =TaxEquity!P39 -> 17.92332 | Q40: =TaxEquity!Q39 -> 18.408212 | ... AM40: =TaxEquity!AM39 -> 17.922826
C42: Total equity | I42: =H1Data!D60 -> 15208.228 | J42: =SUM(J38:J40) -> 15419.038 | K42: =SUM(K38:K40) -> 15700.623 | L42: =SUM(L38:L40) -> 16012.525 | M42: =SUM(M38:M40) -> 16338.771 | N42: =SUM(N38:N40) -> 16669.646 | O42: =SUM(O38:O40) -> 17005.512 | P42: =SUM(P38:P40) -> 17361.634 | Q42: =SUM(Q38:Q40) -> 17714.046 | ... AM42: =SUM(AM38:AM40) -> 18103.504
C43: Total liabilities and equity | I43: =H1Data!D52+H1Data!D60 -> 21435.024 | J43: =J35+J42 -> 21385.805 | K43: =K35+K42 -> 21721.249 | L43: =L35+L42 -> 21846.467 | M43: =M35+M42 -> 21971.344 | N43: =N35+N42 -> 22649.231 | O43: =O35+O42 -> 22567.144 | P43: =P35+P42 -> 23500.212 | Q43: =Q35+Q42 -> 24375.894 | ... AM43: =AM35+AM42 -> 23574.693
C44: Balance-sheet difference | I44: =I22-I43 -> 0 | J44: =J22-J43 -> 0 | K44: =K22-K43 -> 0 | L44: =L22-L43 -> 0 | M44: =M22-M43 -> 0 | N44: =N22-N43 -> 0 | O44: =O22-O43 -> 0 | P44: =P22-P43 -> 0 | ... AM44: =AM22-AM43 -> 0
C46: Cash-to-CFS difference | I46: =I10-H1Actual!D61 -> 0 | J46: =J10-Monthly_CF!J51 -> 0 | K46: =K10-Monthly_CF!K51 -> 0 | L46: =L10-Monthly_CF!L51 -> 0 | M46: =M10-Monthly_CF!M51 -> 0 | N46: =N10-Monthly_CF!N51 -> 0 | O46: =O10-Monthly_CF!O51 -> 0 | P46: =P10-Monthly_CF!P51 -> 0 | Q46: =Q10-Monthly_CF!Q51 -> 0 | ... AM46: =AM10-Monthly_CF!AM51 -> 0

Sheet Monthly_CF
C2: 公牛集团 Monthly_CF
C3: RMB million except stated units. H1 2026 actual aggregate is separate; monthly forecast begins July 2026.
D6: Not disclosed | E6: Not disclosed | F6: Not disclosed | G6: Not disclosed | H6: Not disclosed | I6: 2026H1A / 30-Jun | J6: Forecast | K6: Forecast | L6: Forecast | M6: Forecast | N6: Forecast | O6: Forecast | P6: Forecast | Q6: Forecast | R6: Forecast | S6: Forecast | T6: Forecast | U6: Forecast | V6: Forecast | W6: Forecast | X6: Forecast | Y6: Forecast | Z6: Forecast | AA6: Forecast | AB6: Forecast | AC6: Forecast | AD6: Forecast | AE6: Forecast | AF6: Forecast | AG6: Forecast | AH6: Forecast | AI6: Forecast | AJ6: Forecast | AK6: Forecast | AL6: Forecast | AM6: Forecast
D7: 46053 | E7: 46081 | F7: 46112 | G7: 46142 | H7: 46173 | I7: 46203 | J7: 46234 | K7: 46265 | L7: 46295 | M7: 46326 | N7: 46356 | O7: 46387 | P7: 46418 | Q7: 46446 | R7: 46477 | S7: 46507 | T7: 46538 | U7: 46568 | V7: 46599 | W7: 46630 | X7: 46660 | Y7: 46691 | Z7: 46721 | AA7: 46752 | AB7: 46783 | AC7: 46812 | AD7: 46843 | AE7: 46873 | AF7: 46904 | AG7: 46934 | AH7: 46965 | AI7: 46996 | AJ7: 47026 | AK7: 47057 | AL7: 47087 | AM7: 47118
C9: Direct operating cash flow
C10: Cash collections incl customer advances | J10: =Receivables!J43 -> 1119.9238 | K10: =Receivables!K43 -> 1356.5576 | L10: =Receivables!L43 -> 1365.1334 | M10: =Receivables!M43 -> 1347.9819 | N10: =Receivables!N43 -> 1365.1334 | O10: =Receivables!O43 -> 1347.9819 | P10: =Receivables!P43 -> 1466.3428 | Q10: =Receivables!Q43 -> 1478.2811 | ... AM10: =Receivables!AM43 -> 1448.3601
C11: Cash other pretax income | J11: =Monthly_PL!J24 -> 16.747859 | K11: =Monthly_PL!K24 -> 16.747859 | L11: =Monthly_PL!L24 -> 16.747859 | M11: =Monthly_PL!M24 -> 16.747859 | N11: =Monthly_PL!N24 -> 16.747859 | O11: =Monthly_PL!O24 -> 16.747859 | P11: =Monthly_PL!P24 -> 17.887178 | Q11: =Monthly_PL!Q24 -> 17.887178 | ... AM11: =Monthly_PL!AM24 -> 17.994997
C12: Cash interest income received | J12: =Funding!J63 -> 0.61519284 | K12: =Funding!K63 -> 0.62619647 | L12: =Funding!L63 -> 0.65548533 | M12: =Funding!M63 -> 0.68993147 | N12: =Funding!N63 -> 0.68750601 | O12: =Funding!O63 -> 0.79446322 | P12: =Funding!P63 -> 0.78533409 | Q12: =Funding!Q63 -> 0.81023694 | ... AM12: =Funding!AM63 -> 0.8262572
C14: Cash payments to material suppliers | J14: =-1*Receivables!J27 -> -713.10258 | K14: =-1*Receivables!K27 -> -653.77635 | L14: =-1*Receivables!L27 -> -513.11069 | M14: =-1*Receivables!M27 -> -873.19893 | N14: =-1*Receivables!N27 -> -416.77208 | O14: =-1*Receivables!O27 -> -882.67191 | P14: =-1*Receivables!P27 -> -293.67123 | Q14: =-1*Receivables!Q27 -> -399.71144 | ... AM14: =-1*Receivables!AM27 -> -985.13601
C15: Production payroll cash | J15: =-1*Production!J87 -> -47.012986 | K15: =-1*Production!K87 -> -47.012986 | L15: =-1*Production!L87 -> -47.012986 | M15: =-1*Production!M87 -> -47.012986 | N15: =-1*Production!N87 -> -47.012986 | O15: =-1*Production!O87 -> -47.012986 | P15: =-1*Production!P87 -> -48.423375 | Q15: =-1*Production!Q87 -> -48.423375 | ... AM15: =-1*Production!AM87 -> -49.876076
C16: Cash manufacturing overhead | J16: =-1*Production!J86 -> -69.554971 | K16: =-1*Production!K86 -> -69.440885 | L16: =-1*Production!L86 -> -71.272514 | M16: =-1*Production!M86 -> -67.609256 | N16: =-1*Production!N86 -> -71.272514 | O16: =-1*Production!O86 -> -67.609256 | P16: =-1*Production!P86 -> -79.091612 | Q16: =-1*Production!Q86 -> -81.838098 | ... AM16: =-1*Production!AM86 -> -75.244571
C17: Additional WIP cash cost | J17: =-1*Inventory!J17 -> 0 | K17: =-1*Inventory!K17 -> 0 | L17: =-1*Inventory!L17 -> 0 | M17: =-1*Inventory!M17 -> 0 | N17: =-1*Inventory!N17 -> 0 | O17: =-1*Inventory!O17 -> 0 | P17: =-1*Inventory!P17 -> 0 | Q17: =-1*Inventory!Q17 -> 0 | ... AM17: =-1*Inventory!AM17 -> 0
C18: Cash selling/admin/R&D | J18: =-1*ExpenseDetail!J60 -> -201.94014 | K18: =-1*ExpenseDetail!K60 -> -201.94014 | L18: =-1*ExpenseDetail!L60 -> -201.94014 | M18: =-1*ExpenseDetail!M60 -> -201.94014 | N18: =-1*ExpenseDetail!N60 -> -201.94014 | O18: =-1*ExpenseDetail!O60 -> -201.94014 | P18: =-1*ExpenseDetail!P60 -> -209.72209 | Q18: =-1*ExpenseDetail!Q60 -> -209.72209 | ... AM18: =-1*ExpenseDetail!AM60 -> -213.79168
C19: Business taxes and surcharges cash | J19: =-1*ExpenseDetail!J61 -> -12.995537 | K19: =-1*ExpenseDetail!K61 -> -12.995537 | L19: =-1*ExpenseDetail!L61 -> -12.995537 | M19: =-1*ExpenseDetail!M61 -> -12.995537 | N19: =-1*ExpenseDetail!N61 -> -12.995537 | O19: =-1*ExpenseDetail!O61 -> -12.995537 | P19: =-1*ExpenseDetail!P61 -> -13.879594 | Q19: =-1*ExpenseDetail!Q61 -> -13.879594 | ... AM19: =-1*ExpenseDetail!AM61 -> -13.963257
C20: Other business COGS cash | J20: =-1*ExpenseDetail!J62 -> -0.45875339 | K20: =-1*ExpenseDetail!K62 -> -0.45875339 | L20: =-1*ExpenseDetail!L62 -> -0.45875339 | M20: =-1*ExpenseDetail!M62 -> -0.45875339 | N20: =-1*ExpenseDetail!N62 -> -0.45875339 | O20: =-1*ExpenseDetail!O62 -> -0.45875339 | P20: =-1*ExpenseDetail!P62 -> -2.8642473 | Q20: =-1*ExpenseDetail!Q62 -> -2.8642473 | ... AM20: =-1*ExpenseDetail!AM62 -> -0.45875339
C21: Income taxes paid | J21: =-1*TaxEquity!J12 -> 0 | K21: =-1*TaxEquity!K12 -> 0 | L21: =-1*TaxEquity!L12 -> -430.68883 | M21: =-1*TaxEquity!M12 -> 0 | N21: =-1*TaxEquity!N12 -> 0 | O21: =-1*TaxEquity!O12 -> -209.16222 | P21: =-1*TaxEquity!P12 -> 0 | Q21: =-1*TaxEquity!Q12 -> 0 | ... AM21: =-1*TaxEquity!AM12 -> -214.70863
C22: Named other asset cash movement | J22: =-1*OtherBalances!J20 -> 0 | K22: =-1*OtherBalances!K20 -> 0 | L22: =-1*OtherBalances!L20 -> 0 | M22: =-1*OtherBalances!M20 -> 0 | N22: =-1*OtherBalances!N20 -> 0 | O22: =-1*OtherBalances!O20 -> 0 | P22: =-1*OtherBalances!P20 -> 0 | Q22: =-1*OtherBalances!Q20 -> 0 | ... AM22: =-1*OtherBalances!AM20 -> 0
C23: Named other liability cash movement | J23: =1*OtherBalances!J40 -> 0 | K23: =1*OtherBalances!K40 -> 0 | L23: =1*OtherBalances!L40 -> 0 | M23: =1*OtherBalances!M40 -> 0 | N23: =1*OtherBalances!N40 -> 0 | O23: =1*OtherBalances!O40 -> 0 | P23: =1*OtherBalances!P40 -> 0 | Q23: =1*OtherBalances!Q40 -> 0 | ... AM23: =1*OtherBalances!AM40 -> 0
C24: Direct CFO | I24: =H1Data!D104 -> 2235.8824 | J24: =SUM(J10:J23) -> 92.221836 | K24: =SUM(K10:K23) -> 388.30705 | L24: =SUM(L10:L23) -> 105.05724 | M24: =SUM(M10:M23) -> 162.20412 | N24: =SUM(N10:N23) -> 632.11671 | O24: =SUM(O10:O23) -> -56.326546 | P24: =SUM(P10:P23) -> 837.36313 | Q24: =SUM(Q10:Q23) -> 740.5397 | ... AM24: =SUM(AM10:AM23) -> -85.997571
C27: Cash capital expenditure | I27: =-H1Data!D111 -> -164.97009 | J27: =-1*Assets!J101 -> -43.762172 | K27: =-1*Assets!K101 -> -43.762172 | L27: =-1*Assets!L101 -> -43.762172 | M27: =-1*Assets!M101 -> -43.762172 | N27: =-1*Assets!N101 -> -43.762172 | O27: =-1*Assets!O101 -> -43.762172 | P27: =-1*Assets!P101 -> -45.950281 | Q27: =-1*Assets!Q101 -> -45.950281 | ... AM27: =-1*Assets!AM101 -> -48.247795
C28: PPE disposal proceeds | J28: =1*Assets!J102 -> 0 | K28: =1*Assets!K102 -> 0 | L28: =1*Assets!L102 -> 0 | M28: =1*Assets!M102 -> 0 | N28: =1*Assets!N102 -> 0 | O28: =1*Assets!O102 -> 0 | P28: =1*Assets!P102 -> 0 | Q28: =1*Assets!Q102 -> 0 | ... AM28: =1*Assets!AM102 -> 0
C29: Investment purchases | I29: =-H1Data!D110 -> -10452.63 | J29: =-1*Funding!J54 -> 0 | K29: =-1*Funding!K54 -> 0 | L29: =-1*Funding!L54 -> 0 | M29: =-1*Funding!M54 -> 0 | N29: =-1*Funding!N54 -> 0 | O29: =-1*Funding!O54 -> 0 | P29: =-1*Funding!P54 -> 0 | Q29: =-1*Funding!Q54 -> 0 | ... AM29: =-1*Funding!AM54 -> 0
C30: Investment redemptions | I30: =H1Data!D109 -> 11980.878 | J30: =1*Funding!J55 -> 0 | K30: =1*Funding!K55 -> 0 | L30: =1*Funding!L55 -> 0 | M30: =1*Funding!M55 -> 0 | N30: =1*Funding!N55 -> 0 | O30: =1*Funding!O55 -> 0 | P30: =1*Funding!P55 -> 0 | Q30: =1*Funding!Q55 -> 0 | ... AM30: =1*Funding!AM55 -> 0
C31: Cash investment income | I31: =H1Data!D93 -> 257.05764 | J31: =1*Funding!J59 -> 37.940387 | K31: =1*Funding!K59 -> 37.940387 | L31: =1*Funding!L59 -> 36.716504 | M31: =1*Funding!M59 -> 37.940387 | N31: =1*Funding!N59 -> 36.716504 | O31: =1*Funding!O59 -> 37.940387 | P31: =1*Funding!P59 -> 37.940387 | Q31: =1*Funding!Q59 -> 34.268737 | ... AM31: =1*Funding!AM59 -> 37.836725
C34: Net investing cash flow | I34: =H1Data!D105 -> 1612.0293 | J34: =SUM(J27:J31) -> -5.8217847 | K34: =SUM(K27:K31) -> -5.8217847 | L34: =SUM(L27:L31) -> -7.0456682 | M34: =SUM(M27:M31) -> -5.8217847 | N34: =SUM(N27:N31) -> -7.0456682 | O34: =SUM(O27:O31) -> -5.8217847 | P34: =SUM(P27:P31) -> -8.0098933 | Q34: =SUM(Q27:Q31) -> -11.681544 | ... AM34: =SUM(AM27:AM31) -> -10.41107
C37: Effective loan draw | I37: =H1Data!D112 -> 1975.8432 | J37: =1*Funding!J65 -> 0 | K37: =1*Funding!K65 -> 0 | L37: =1*Funding!L65 -> 0 | M37: =1*Funding!M65 -> 0 | N37: =1*Funding!N65 -> 0 | O37: =1*Funding!O65 -> 0 | P37: =1*Funding!P65 -> 0 | Q37: =1*Funding!Q65 -> 0 | ... AM37: =1*Funding!AM65 -> 0
C38: Effective loan principal repayment | I38: =-H1Data!D113 -> -1829.95 | J38: =-1*Funding!J66 -> 0 | K38: =-1*Funding!K66 -> 0 | L38: =-1*Funding!L66 -> 0 | M38: =-1*Funding!M66 -> 0 | N38: =-1*Funding!N66 -> 0 | O38: =-1*Funding!O66 -> 0 | P38: =-1*Funding!P66 -> 0 | Q38: =-1*Funding!Q66 -> 0 | ... AM38: =-1*Funding!AM66 -> 0
C39: Effective lease principal repayment | J39: =-1*Funding!J47 -> -1.1167446 | K39: =-1*Funding!K47 -> -1.1167446 | L39: =-1*Funding!L47 -> -1.1167446 | M39: =-1*Funding!M47 -> -1.1167446 | N39: =-1*Funding!N47 -> -1.1167446 | O39: =-1*Funding!O47 -> -1.1167446 | P39: =-1*Funding!P47 -> -1.1167446 | Q39: =-1*Funding!Q47 -> -1.1167446 | ... AM39: =-1*Funding!AM47 -> 0
C40: Loan and lease interest cash paid | J40: =-1*Monthly_PL!J28 -> -4.1053422 | K40: =-1*Monthly_PL!K28 -> -4.1010741 | L40: =-1*Monthly_PL!L28 -> -3.964651 | M40: =-1*Monthly_PL!M28 -> -4.0925379 | N40: =-1*Monthly_PL!N28 -> -3.9563902 | O40: =-1*Monthly_PL!O28 -> -4.0840017 | P40: =-1*Monthly_PL!P28 -> -4.0797336 | Q40: =-1*Monthly_PL!Q28 -> -3.6810656 | ... AM40: =-1*Monthly_PL!AM28 -> -2.4153845
C41: Gross new equity proceeds | J41: =1*TaxEquity!J40 -> 0 | K41: =1*TaxEquity!K40 -> 0 | L41: =1*TaxEquity!L40 -> 0 | M41: =1*TaxEquity!M40 -> 0 | N41: =1*TaxEquity!N40 -> 0 | O41: =1*TaxEquity!O40 -> 0 | P41: =1*TaxEquity!P40 -> 0 | Q41: =1*TaxEquity!Q40 -> 0 | ... AM41: =1*TaxEquity!AM40 -> 0
C42: Equity issuance fee | J42: =-1*TaxEquity!J41 -> 0 | K42: =-1*TaxEquity!K41 -> 0 | L42: =-1*TaxEquity!L41 -> 0 | M42: =-1*TaxEquity!M41 -> 0 | N42: =-1*TaxEquity!N41 -> 0 | O42: =-1*TaxEquity!O41 -> 0 | P42: =-1*TaxEquity!P41 -> 0 | Q42: =-1*TaxEquity!Q41 -> 0 | ... AM42: =-1*TaxEquity!AM41 -> 0
C43: Parent and NCI cash dividends | J43: =-1*Funding!J72 -> 0 | K43: =-1*Funding!K72 -> 0 | L43: =-1*Funding!L72 -> 0 | M43: =-1*Funding!M72 -> 0 | N43: =-1*Funding!N72 -> 0 | O43: =-1*Funding!O72 -> 0 | P43: =-1*Funding!P72 -> 0 | Q43: =-1*Funding!Q72 -> 0 | ... AM43: =-1*Funding!AM72 -> 0
C44: Share repurchase cash | J44: =-TaxEquity!J53 -> 0 | K44: =-TaxEquity!K53 -> 0 | L44: =-TaxEquity!L53 -> 0 | M44: =-TaxEquity!M53 -> 0 | N44: =-TaxEquity!N53 -> 0 | O44: =-TaxEquity!O53 -> 0 | P44: =-TaxEquity!P53 -> 0 | Q44: =-TaxEquity!Q53 -> 0 | ... AM44: =-TaxEquity!AM53 -> 0
C45: Net financing cash flow | I45: =H1Data!D106 -> -3503.3588 | J45: =SUM(J37:J44) -> -5.2220868 | K45: =SUM(K37:K44) -> -5.2178187 | L45: =SUM(L37:L44) -> -5.0813956 | M45: =SUM(M37:M44) -> -5.2092825 | N45: =SUM(N37:N44) -> -5.0731347 | O45: =SUM(O37:O44) -> -5.2007463 | P45: =SUM(P37:P44) -> -5.1964782 | Q45: =SUM(Q37:Q44) -> -4.7978102 | ... AM45: =SUM(AM37:AM44) -> -2.4153845
C47: Cash FX | I47: =H1Data!D107 -> -7.0988049 | J47: =Inputs!J61 -> 0 | K47: =Inputs!K61 -> 0 | L47: =Inputs!L61 -> 0 | M47: =Inputs!M61 -> 0 | N47: =Inputs!N61 -> 0 | O47: =Inputs!O61 -> 0 | P47: =Inputs!P61 -> 0 | Q47: =Inputs!Q61 -> 0 | ... AM47: =Inputs!AM61 -> 0
C48: Net change in cash | I48: =SUM(I24,I34,I45,I47) -> 337.4541 | J48: =J24+J34+J45+J47 -> 81.177965 | K48: =K24+K34+K45+K47 -> 377.26745 | L48: =L24+L34+L45+L47 -> 92.93018 | M48: =M24+M34+M45+M47 -> 151.17306 | N48: =N24+N34+N45+N47 -> 619.9979 | O48: =O24+O34+O45+O47 -> -67.349077 | P48: =P24+P34+P45+P47 -> 824.15676 | Q48: =Q24+Q34+Q45+Q47 -> 724.06035 | ... AM48: =AM24+AM34+AM45+AM47 -> -98.824025
C50: Opening cash equivalents | I50: =H1Data!D108 -> 721.04459 | J50: =H1Data!D9 -> 1058.4987 | K50: =Monthly_CF!J51 -> 1139.6766 | L50: =Monthly_CF!K51 -> 1516.9441 | M50: =Monthly_CF!L51 -> 1609.8743 | N50: =Monthly_CF!M51 -> 1761.0473 | O50: =Monthly_CF!N51 -> 2381.0452 | P50: =Monthly_CF!O51 -> 2313.6962 | Q50: =Monthly_CF!P51 -> 3137.8529 | R50: =Monthly_CF!Q51 -> 3861.9133 | ... AM50: =Monthly_CF!AL51 -> 2632.302
C51: Closing cash equivalents | I51: =H1Data!D9 -> 1058.4987 | J51: =J50+J48 -> 1139.6766 | K51: =K50+K48 -> 1516.9441 | L51: =L50+L48 -> 1609.8743 | M51: =M50+M48 -> 1761.0473 | N51: =N50+N48 -> 2381.0452 | O51: =O50+O48 -> 2313.6962 | P51: =P50+P48 -> 3137.8529 | Q51: =Q50+Q48 -> 3861.9133 | ... AM51: =AM50+AM48 -> 2533.478
C53: Indirect CFO: consolidated NI | J53: =Monthly_PL!J31 -> 207.04207 | K53: =Monthly_PL!K31 -> 277.81829 | L53: =Monthly_PL!L31 -> 308.1352 | M53: =Monthly_PL!M31 -> 322.47864 | N53: =Monthly_PL!N31 -> 327.10814 | O53: =Monthly_PL!O31 -> 332.09933 | P53: =Monthly_PL!P31 -> 352.35438 | Q53: =Monthly_PL!Q31 -> 348.6448 | ... AM53: =Monthly_PL!AM31 -> 336.97149
C54: Add total D&A | J54: =Assets!J100 -> 26.380476 | K54: =Assets!K100 -> 26.591641 | L54: =Assets!L100 -> 26.802806 | M54: =Assets!M100 -> 27.013971 | N54: =Assets!N100 -> 27.225136 | O54: =Assets!O100 -> 27.436302 | P54: =Assets!P100 -> 27.647467 | Q54: =Assets!Q100 -> 27.86919 | ... AM54: =Assets!AM100 -> 31.609107
C55: Add share compensation / impairment / ECL | J55: =TaxEquity!J44+Assets!J103+Receivables!J16 -> 4.3282512 | K55: =TaxEquity!K44+Assets!K103+Receivables!K16 -> 3.7670464 | L55: =TaxEquity!L44+Assets!L103+Receivables!L16 -> 4.6713818 | M55: =TaxEquity!M44+Assets!M103+Receivables!M16 -> 2.8627111 | N55: =TaxEquity!N44+Assets!N103+Receivables!N16 -> 4.6713818 | O55: =TaxEquity!O44+Assets!O103+Receivables!O16 -> 2.8627111 | P55: =TaxEquity!P44+Assets!P103+Receivables!P16 -> 5.6126431 | Q55: =TaxEquity!Q44+Assets!Q103+Receivables!Q16 -> 6.8715812 | ... AM55: =TaxEquity!AM44+Assets!AM103+Receivables!AM16 -> 2.7953692
C56: Reverse investment income and FV; add finance interest | J56: =-Funding!J59-Funding!J56+Monthly_PL!J28 -> -33.835045 | K56: =-Funding!K59-Funding!K56+Monthly_PL!K28 -> -33.839313 | L56: =-Funding!L59-Funding!L56+Monthly_PL!L28 -> -32.751853 | M56: =-Funding!M59-Funding!M56+Monthly_PL!M28 -> -33.84785 | N56: =-Funding!N59-Funding!N56+Monthly_PL!N28 -> -32.760114 | O56: =-Funding!O59-Funding!O56+Monthly_PL!O28 -> -33.856386 | P56: =-Funding!P59-Funding!P56+Monthly_PL!P28 -> -33.860654 | Q56: =-Funding!Q59-Funding!Q56+Monthly_PL!Q28 -> -30.587671 | ... AM56: =-Funding!AM59-Funding!AM56+Monthly_PL!AM28 -> -35.421341
C57: Tax expense less cash tax paid | J57: =TaxEquity!J24-TaxEquity!J12 -> 44.113264 | K57: =TaxEquity!K24-TaxEquity!K12 -> 59.193146 | L57: =TaxEquity!L24-TaxEquity!L12 -> -365.03624 | M57: =TaxEquity!M24-TaxEquity!M12 -> 68.708671 | N57: =TaxEquity!N24-TaxEquity!N12 -> 69.695051 | O57: =TaxEquity!O24-TaxEquity!O12 -> -138.40372 | P57: =TaxEquity!P24-TaxEquity!P12 -> 75.074122 | Q57: =TaxEquity!Q24-TaxEquity!Q12 -> 74.283744 | ... AM57: =TaxEquity!AM24-TaxEquity!AM12 -> -142.91205
C58: Gross AR / inventory / goods AP / advances changes | J58: =-Receivables!J34-Inventory!J31+Receivables!J35+Receivables!J44 -> -147.81147 | K58: =-Receivables!K34-Inventory!K31+Receivables!K35+Receivables!K44 -> 62.914961 | L58: =-Receivables!L34-Inventory!L31+Receivables!L35+Receivables!L44 -> 171.75533 | M58: =-Receivables!M34-Inventory!M31+Receivables!M35+Receivables!M44 -> -216.04494 | N58: =-Receivables!N34-Inventory!N31+Receivables!N35+Receivables!N44 -> 245.11267 | O58: =-Receivables!O34-Inventory!O31+Receivables!O35+Receivables!O44 -> -236.13909 | P58: =-Receivables!P34-Inventory!P31+Receivables!P35+Receivables!P44 -> 420.74222 | Q58: =-Receivables!Q34-Inventory!Q31+Receivables!Q35+Receivables!Q44 -> 323.98876 | ... AM58: =-Receivables!AM34-Inventory!AM31+Receivables!AM35+Receivables!AM44 -> -268.30123
C59: Other balances and unreceived interest changes | J59: =-OtherBalances!J20+OtherBalances!J40-OtherBalances!J44 -> -7.9957033 | K59: =-OtherBalances!K20+OtherBalances!K40-OtherBalances!K44 -> -8.1387182 | L59: =-OtherBalances!L20+OtherBalances!L40-OtherBalances!L44 -> -8.5193875 | M59: =-OtherBalances!M20+OtherBalances!M40-OtherBalances!M44 -> -8.9670863 | N59: =-OtherBalances!N20+OtherBalances!N40-OtherBalances!N44 -> -8.9355626 | O59: =-OtherBalances!O20+OtherBalances!O40-OtherBalances!O44 -> -10.325693 | P59: =-OtherBalances!P20+OtherBalances!P40-OtherBalances!P44 -> -10.207041 | Q59: =-OtherBalances!Q20+OtherBalances!Q40-OtherBalances!Q44 -> -10.530705 | ... AM59: =-OtherBalances!AM20+OtherBalances!AM40-OtherBalances!AM44 -> -10.738921
C60: Indirect CFO | J60: =SUM(J53:J59) -> 92.221836 | K60: =SUM(K53:K59) -> 388.30705 | L60: =SUM(L53:L59) -> 105.05724 | M60: =SUM(M53:M59) -> 162.20412 | N60: =SUM(N53:N59) -> 632.11671 | O60: =SUM(O53:O59) -> -56.326546 | P60: =SUM(P53:P59) -> 837.36313 | Q60: =SUM(Q53:Q59) -> 740.5397 | ... AM60: =SUM(AM53:AM59) -> -85.997571
C61: Direct minus indirect CFO | J61: =J24-J60 -> 0 | K61: =K24-K60 -> 0 | L61: =L24-L60 -> 0 | M61: =M24-M60 -> 0 | N61: =N24-N60 -> 0 | O61: =O24-O60 -> -3.623768e-13 | P61: =P24-P60 -> 0 | Q61: =Q24-Q60 -> 0 | ... AM61: =AM24-AM60 -> 0
C62: Cash roll-forward difference | I62: =I50+I48-I51 -> 0 | J62: =J50+J24+J34+J45+J47-J51 -> 0 | K62: =K50+K24+K34+K45+K47-K51 -> 0 | L62: =L50+L24+L34+L45+L47-L51 -> 0 | M62: =M50+M24+M34+M45+M47-M51 -> 0 | N62: =N50+N24+N34+N45+N47-N51 -> 0 | O62: =O50+O24+O34+O45+O47-O51 -> 0 | P62: =P50+P24+P34+P45+P47-P51 -> 0 | Q62: =Q50+Q24+Q34+Q45+Q47-Q51 -> 0 | ... AM62: =AM50+AM24+AM34+AM45+AM47-AM51 -> 0

Sheet Revenue
C2: 公牛集团 Revenue
C3: RMB million except stated units. H1 2026 actual aggregate is separate; monthly forecast begins July 2026.
D6: Not disclosed | E6: Not disclosed | F6: Not disclosed | G6: Not disclosed | H6: Not disclosed | I6: H1: see H1Actual | J6: Forecast | K6: Forecast | L6: Forecast | M6: Forecast | N6: Forecast | O6: Forecast | P6: Forecast | Q6: Forecast | R6: Forecast | S6: Forecast | T6: Forecast | U6: Forecast | V6: Forecast | W6: Forecast | X6: Forecast | Y6: Forecast | Z6: Forecast | AA6: Forecast | AB6: Forecast | AC6: Forecast | AD6: Forecast | AE6: Forecast | AF6: Forecast | AG6: Forecast | AH6: Forecast | AI6: Forecast | AJ6: Forecast | AK6: Forecast | AL6: Forecast | AM6: Forecast
D7: 46053 | E7: 46081 | F7: 46112 | G7: 46142 | H7: 46173 | I7: 46203 | J7: 46234 | K7: 46265 | L7: 46295 | M7: 46326 | N7: 46356 | O7: 46387 | P7: 46418 | Q7: 46446 | R7: 46477 | S7: 46507 | T7: 46538 | U7: 46568 | V7: 46599 | W7: 46630 | X7: 46660 | Y7: 46691 | Z7: 46721 | AA7: 46752 | AB7: 46783 | AC7: 46812 | AD7: 46843 | AE7: 46873 | AF7: 46904 | AG7: 46934 | AH7: 46965 | AI7: 46996 | AJ7: 47026 | AK7: 47057 | AL7: 47087 | AM7: 47118
C9: 电连接产品
C10: Sales units | J10: =(SourceAnalysis!D9-(SourceHistory!F64-SourceHistory!F66)*SourceAnalysis!D9/SourceAnalysis!D24)*1000000/SourceAnalysis!D13/6*(1+Inputs!J9)*Inputs!J5 -> 48342423 | K10: =(SourceAnalysis!D9-(SourceHistory!F64-SourceHistory!F66)*SourceAnalysis!D9/SourceAnalysis!D24)*1000000/SourceAnalysis!D13/6*(1+Inputs!K9)*Inputs!K5 -> 48342423 | L10: =(SourceAnalysis!D9-(SourceHistory!F64-SourceHistory!F66)*SourceAnalysis!D9/SourceAnalysis!D24)*1000000/SourceAnalysis!D13/6*(1+Inputs!L9)*Inputs!L5 -> 48342423 | M10: =(SourceAnalysis!D9-(SourceHistory!F64-SourceHistory!F66)*SourceAnalysis!D9/SourceAnalysis!D24)*1000000/SourceAnalysis!D13/6*(1+Inputs!M9)*Inputs!M5 -> 48342423 | N10: =(SourceAnalysis!D9-(SourceHistory!F64-SourceHistory!F66)*SourceAnalysis!D9/SourceAnalysis!D24)*1000000/SourceAnalysis!D13/6*(1+Inputs!N9)*Inputs!N5 -> 48342423 | O10: =(SourceAnalysis!D9-(SourceHistory!F64-SourceHistory!F66)*SourceAnalysis!D9/SourceAnalysis!D24)*1000000/SourceAnalysis!D13/6*(1+Inputs!O9)*Inputs!O5 -> 48342423 | P10: =((SourceHistory!F65-SourceHistory!F67)*SourceAnalysis!D9/SourceAnalysis!D24*1000000/SourceAnalysis!D13/6)*(1+Inputs!P9)*Inputs!P5 -> 51490346 | Q10: =((SourceHistory!F65-SourceHistory!F67)*SourceAnalysis!D9/SourceAnalysis!D24*1000000/SourceAnalysis!D13/6)*(1+Inputs!Q9)*Inputs!Q5 -> 51490346 | R10: =((SourceHistory!F65-SourceHistory!F67)*SourceAnalysis!D9/SourceAnalysis!D24*1000000/SourceAnalysis!D13/6)*(1+Inputs!R9)*Inputs!R5 -> 51490346 | S10: =((SourceHistory!F65-SourceHistory!F67)*SourceAnalysis!D9/SourceAnalysis!D24*1000000/SourceAnalysis!D13/6)*(1+Inputs!S9)*Inputs!S5 -> 51490346 | T10: =((SourceHistory!F65-SourceHistory!F67)*SourceAnalysis!D9/SourceAnalysis!D24*1000000/SourceAnalysis!D13/6)*(1+Inputs!T9)*Inputs!T5 -> 51490346 | U10: =((SourceHistory!F65-SourceHistory!F67)*SourceAnalysis!D9/SourceAnalysis!D24*1000000/SourceAnalysis!D13/6)*(1+Inputs!U9)*Inputs!U5 -> 51490346 | V10: =Revenue!J10*(1+Inputs!V9)*Inputs!V5 -> 49309272 | W10: =Revenue!K10*(1+Inputs!W9)*Inputs!W5 -> 49309272 | X10: =Revenue!L10*(1+Inputs!X9)*Inputs!X5 -> 49309272 | Y10: =Revenue!M10*(1+Inputs!Y9)*Inputs!Y5 -> 49309272 | Z10: =Revenue!N10*(1+Inputs!Z9)*Inputs!Z5 -> 49309272 | AA10: =Revenue!O10*(1+Inputs!AA9)*Inputs!AA5 -> 49309272 | AB10: =Revenue!P10*(1+Inputs!AB9)*Inputs!AB5 -> 52520153 | AC10: =Revenue!Q10*(1+Inputs!AC9)*Inputs!AC5 -> 52520153 | ... AM10: =Revenue!AA10*(1+Inputs!AM9)*Inputs!AM5 -> 50295457
C11: Net ASP incl mix RMB | J11: =SourceAnalysis!D13*(1+Inputs!J10) -> 12.218193 | K11: =SourceAnalysis!D13*(1+Inputs!K10) -> 12.218193 | L11: =SourceAnalysis!D13*(1+Inputs!L10) -> 12.218193 | M11: =SourceAnalysis!D13*(1+Inputs!M10) -> 12.218193 | N11: =SourceAnalysis!D13*(1+Inputs!N10) -> 12.218193 | O11: =SourceAnalysis!D13*(1+Inputs!O10) -> 12.218193 | P11: =(SourceAnalysis!D13)*(1+Inputs!P10) -> 12.218193 | Q11: =(SourceAnalysis!D13)*(1+Inputs!Q10) -> 12.218193 | R11: =(SourceAnalysis!D13)*(1+Inputs!R10) -> 12.218193 | S11: =(SourceAnalysis!D13)*(1+Inputs!S10) -> 12.218193 | T11: =(SourceAnalysis!D13)*(1+Inputs!T10) -> 12.218193 | U11: =(SourceAnalysis!D13)*(1+Inputs!U10) -> 12.218193 | V11: =Revenue!J11*(1+Inputs!V10) -> 12.218193 | W11: =Revenue!K11*(1+Inputs!W10) -> 12.218193 | X11: =Revenue!L11*(1+Inputs!X10) -> 12.218193 | Y11: =Revenue!M11*(1+Inputs!Y10) -> 12.218193 | Z11: =Revenue!N11*(1+Inputs!Z10) -> 12.218193 | AA11: =Revenue!O11*(1+Inputs!AA10) -> 12.218193 | AB11: =Revenue!P11*(1+Inputs!AB10) -> 12.218193 | AC11: =Revenue!Q11*(1+Inputs!AC10) -> 12.218193 | ... AM11: =Revenue!AA11*(1+Inputs!AM10) -> 12.218193
C12: Product revenue | J12: =J10*J11/1000000 -> 590.65705 | K12: =K10*K11/1000000 -> 590.65705 | L12: =L10*L11/1000000 -> 590.65705 | M12: =M10*M11/1000000 -> 590.65705 | N12: =N10*N11/1000000 -> 590.65705 | O12: =O10*O11/1000000 -> 590.65705 | P12: =P10*P11/1000000 -> 629.11898 | Q12: =Q10*Q11/1000000 -> 629.11898 | ... AM12: =AM10*AM11/1000000 -> 614.5196
C13: Revenue unit/ASP check | J13: =J10*J11/1000000-J12 -> 0 | K13: =K10*K11/1000000-K12 -> 0 | L13: =L10*L11/1000000-L12 -> 0 | M13: =M10*M11/1000000-M12 -> 0 | N13: =N10*N11/1000000-N12 -> 0 | O13: =O10*O11/1000000-O12 -> 0 | P13: =P10*P11/1000000-P12 -> 0 | Q13: =Q10*Q11/1000000-Q12 -> 0 | ... AM13: =AM10*AM11/1000000-AM12 -> 0
C18: 智能电工照明
C19: Sales units | J19: =(SourceAnalysis!D14-(SourceHistory!F64-SourceHistory!F66)*SourceAnalysis!D14/SourceAnalysis!D24)*1000000/SourceAnalysis!D18/6*(1+Inputs!J13)*Inputs!J5 -> 88596987 | K19: =(SourceAnalysis!D14-(SourceHistory!F64-SourceHistory!F66)*SourceAnalysis!D14/SourceAnalysis!D24)*1000000/SourceAnalysis!D18/6*(1+Inputs!K13)*Inputs!K5 -> 88596987 | L19: =(SourceAnalysis!D14-(SourceHistory!F64-SourceHistory!F66)*SourceAnalysis!D14/SourceAnalysis!D24)*1000000/SourceAnalysis!D18/6*(1+Inputs!L13)*Inputs!L5 -> 88596987 | M19: =(SourceAnalysis!D14-(SourceHistory!F64-SourceHistory!F66)*SourceAnalysis!D14/SourceAnalysis!D24)*1000000/SourceAnalysis!D18/6*(1+Inputs!M13)*Inputs!M5 -> 88596987 | N19: =(SourceAnalysis!D14-(SourceHistory!F64-SourceHistory!F66)*SourceAnalysis!D14/SourceAnalysis!D24)*1000000/SourceAnalysis!D18/6*(1+Inputs!N13)*Inputs!N5 -> 88596987 | O19: =(SourceAnalysis!D14-(SourceHistory!F64-SourceHistory!F66)*SourceAnalysis!D14/SourceAnalysis!D24)*1000000/SourceAnalysis!D18/6*(1+Inputs!O13)*Inputs!O5 -> 88596987 | P19: =((SourceHistory!F65-SourceHistory!F67)*SourceAnalysis!D14/SourceAnalysis!D24*1000000/SourceAnalysis!D18/6)*(1+Inputs!P13)*Inputs!P5 -> 94366174 | Q19: =((SourceHistory!F65-SourceHistory!F67)*SourceAnalysis!D14/SourceAnalysis!D24*1000000/SourceAnalysis!D18/6)*(1+Inputs!Q13)*Inputs!Q5 -> 94366174 | R19: =((SourceHistory!F65-SourceHistory!F67)*SourceAnalysis!D14/SourceAnalysis!D24*1000000/SourceAnalysis!D18/6)*(1+Inputs!R13)*Inputs!R5 -> 94366174 | S19: =((SourceHistory!F65-SourceHistory!F67)*SourceAnalysis!D14/SourceAnalysis!D24*1000000/SourceAnalysis!D18/6)*(1+Inputs!S13)*Inputs!S5 -> 94366174 | T19: =((SourceHistory!F65-SourceHistory!F67)*SourceAnalysis!D14/SourceAnalysis!D24*1000000/SourceAnalysis!D18/6)*(1+Inputs!T13)*Inputs!T5 -> 94366174 | U19: =((SourceHistory!F65-SourceHistory!F67)*SourceAnalysis!D14/SourceAnalysis!D24*1000000/SourceAnalysis!D18/6)*(1+Inputs!U13)*Inputs!U5 -> 94366174 | V19: =Revenue!J19*(1+Inputs!V13)*Inputs!V5 -> 91254897 | W19: =Revenue!K19*(1+Inputs!W13)*Inputs!W5 -> 91254897 | X19: =Revenue!L19*(1+Inputs!X13)*Inputs!X5 -> 91254897 | Y19: =Revenue!M19*(1+Inputs!Y13)*Inputs!Y5 -> 91254897 | Z19: =Revenue!N19*(1+Inputs!Z13)*Inputs!Z5 -> 91254897 | AA19: =Revenue!O19*(1+Inputs!AA13)*Inputs!AA5 -> 91254897 | AB19: =Revenue!P19*(1+Inputs!AB13)*Inputs!AB5 -> 97197159 | AC19: =Revenue!Q19*(1+Inputs!AC13)*Inputs!AC5 -> 97197159 | ... AM19: =Revenue!AA19*(1+Inputs!AM13)*Inputs!AM5 -> 93992544
C20: Net ASP incl mix RMB | J20: =SourceAnalysis!D18*(1+Inputs!J14) -> 7.7807079 | K20: =SourceAnalysis!D18*(1+Inputs!K14) -> 7.7807079 | L20: =SourceAnalysis!D18*(1+Inputs!L14) -> 7.7807079 | M20: =SourceAnalysis!D18*(1+Inputs!M14) -> 7.7807079 | N20: =SourceAnalysis!D18*(1+Inputs!N14) -> 7.7807079 | O20: =SourceAnalysis!D18*(1+Inputs!O14) -> 7.7807079 | P20: =(SourceAnalysis!D18)*(1+Inputs!P14) -> 7.7807079 | Q20: =(SourceAnalysis!D18)*(1+Inputs!Q14) -> 7.7807079 | R20: =(SourceAnalysis!D18)*(1+Inputs!R14) -> 7.7807079 | S20: =(SourceAnalysis!D18)*(1+Inputs!S14) -> 7.7807079 | T20: =(SourceAnalysis!D18)*(1+Inputs!T14) -> 7.7807079 | U20: =(SourceAnalysis!D18)*(1+Inputs!U14) -> 7.7807079 | V20: =Revenue!J20*(1+Inputs!V14) -> 7.858515 | W20: =Revenue!K20*(1+Inputs!W14) -> 7.858515 | X20: =Revenue!L20*(1+Inputs!X14) -> 7.858515 | Y20: =Revenue!M20*(1+Inputs!Y14) -> 7.858515 | Z20: =Revenue!N20*(1+Inputs!Z14) -> 7.858515 | AA20: =Revenue!O20*(1+Inputs!AA14) -> 7.858515 | AB20: =Revenue!P20*(1+Inputs!AB14) -> 7.858515 | AC20: =Revenue!Q20*(1+Inputs!AC14) -> 7.858515 | ... AM20: =Revenue!AA20*(1+Inputs!AM14) -> 7.9371002
C21: Product revenue | J21: =J19*J20/1000000 -> 689.34728 | K21: =K19*K20/1000000 -> 689.34728 | L21: =L19*L20/1000000 -> 689.34728 | M21: =M19*M20/1000000 -> 689.34728 | N21: =N19*N20/1000000 -> 689.34728 | O21: =O19*O20/1000000 -> 689.34728 | P21: =P19*P20/1000000 -> 734.23564 | Q21: =Q19*Q20/1000000 -> 734.23564 | ... AM21: =AM19*AM20/1000000 -> 746.02823
C22: Revenue unit/ASP check | J22: =J19*J20/1000000-J21 -> 0 | K22: =K19*K20/1000000-K21 -> 0 | L22: =L19*L20/1000000-L21 -> 0 | M22: =M19*M20/1000000-M21 -> 0 | N22: =N19*N20/1000000-N21 -> 0 | O22: =O19*O20/1000000-O21 -> 0 | P22: =P19*P20/1000000-P21 -> 0 | Q22: =Q19*Q20/1000000-Q21 -> 0 | ... AM22: =AM19*AM20/1000000-AM21 -> 0
C27: 新能源产品
C28: Sales units | J28: =(SourceAnalysis!D19-(SourceHistory!F64-SourceHistory!F66)*SourceAnalysis!D19/SourceAnalysis!D24)*1000000/SourceAnalysis!D23/6*(1+Inputs!J17)*Inputs!J5 -> 122044.41 | K28: =(SourceAnalysis!D19-(SourceHistory!F64-SourceHistory!F66)*SourceAnalysis!D19/SourceAnalysis!D24)*1000000/SourceAnalysis!D23/6*(1+Inputs!K17)*Inputs!K5 -> 122044.41 | L28: =(SourceAnalysis!D19-(SourceHistory!F64-SourceHistory!F66)*SourceAnalysis!D19/SourceAnalysis!D24)*1000000/SourceAnalysis!D23/6*(1+Inputs!L17)*Inputs!L5 -> 122044.41 | M28: =(SourceAnalysis!D19-(SourceHistory!F64-SourceHistory!F66)*SourceAnalysis!D19/SourceAnalysis!D24)*1000000/SourceAnalysis!D23/6*(1+Inputs!M17)*Inputs!M5 -> 122044.41 | N28: =(SourceAnalysis!D19-(SourceHistory!F64-SourceHistory!F66)*SourceAnalysis!D19/SourceAnalysis!D24)*1000000/SourceAnalysis!D23/6*(1+Inputs!N17)*Inputs!N5 -> 122044.41 | O28: =(SourceAnalysis!D19-(SourceHistory!F64-SourceHistory!F66)*SourceAnalysis!D19/SourceAnalysis!D24)*1000000/SourceAnalysis!D23/6*(1+Inputs!O17)*Inputs!O5 -> 122044.41 | P28: =((SourceHistory!F65-SourceHistory!F67)*SourceAnalysis!D19/SourceAnalysis!D24*1000000/SourceAnalysis!D23/6)*(1+Inputs!P17)*Inputs!P5 -> 129991.6 | Q28: =((SourceHistory!F65-SourceHistory!F67)*SourceAnalysis!D19/SourceAnalysis!D24*1000000/SourceAnalysis!D23/6)*(1+Inputs!Q17)*Inputs!Q5 -> 129991.6 | R28: =((SourceHistory!F65-SourceHistory!F67)*SourceAnalysis!D19/SourceAnalysis!D24*1000000/SourceAnalysis!D23/6)*(1+Inputs!R17)*Inputs!R5 -> 129991.6 | S28: =((SourceHistory!F65-SourceHistory!F67)*SourceAnalysis!D19/SourceAnalysis!D24*1000000/SourceAnalysis!D23/6)*(1+Inputs!S17)*Inputs!S5 -> 129991.6 | T28: =((SourceHistory!F65-SourceHistory!F67)*SourceAnalysis!D19/SourceAnalysis!D24*1000000/SourceAnalysis!D23/6)*(1+Inputs!T17)*Inputs!T5 -> 129991.6 | U28: =((SourceHistory!F65-SourceHistory!F67)*SourceAnalysis!D19/SourceAnalysis!D24*1000000/SourceAnalysis!D23/6)*(1+Inputs!U17)*Inputs!U5 -> 129991.6 | V28: =Revenue!J28*(1+Inputs!V17)*Inputs!V5 -> 140351.07 | W28: =Revenue!K28*(1+Inputs!W17)*Inputs!W5 -> 140351.07 | X28: =Revenue!L28*(1+Inputs!X17)*Inputs!X5 -> 140351.07 | Y28: =Revenue!M28*(1+Inputs!Y17)*Inputs!Y5 -> 140351.07 | Z28: =Revenue!N28*(1+Inputs!Z17)*Inputs!Z5 -> 140351.07 | AA28: =Revenue!O28*(1+Inputs!AA17)*Inputs!AA5 -> 140351.07 | AB28: =Revenue!P28*(1+Inputs!AB17)*Inputs!AB5 -> 149490.34 | AC28: =Revenue!Q28*(1+Inputs!AC17)*Inputs!AC5 -> 149490.34 | ... AM28: =Revenue!AA28*(1+Inputs!AM17)*Inputs!AM5 -> 161403.73
C29: Net ASP incl mix RMB | J29: =SourceAnalysis!D23*(1+Inputs!J18) -> 621.01045 | K29: =SourceAnalysis!D23*(1+Inputs!K18) -> 621.01045 | L29: =SourceAnalysis!D23*(1+Inputs!L18) -> 621.01045 | M29: =SourceAnalysis!D23*(1+Inputs!M18) -> 621.01045 | N29: =SourceAnalysis!D23*(1+Inputs!N18) -> 621.01045 | O29: =SourceAnalysis!D23*(1+Inputs!O18) -> 621.01045 | P29: =(SourceAnalysis!D23)*(1+Inputs!P18) -> 621.01045 | Q29: =(SourceAnalysis!D23)*(1+Inputs!Q18) -> 621.01045 | R29: =(SourceAnalysis!D23)*(1+Inputs!R18) -> 621.01045 | S29: =(SourceAnalysis!D23)*(1+Inputs!S18) -> 621.01045 | T29: =(SourceAnalysis!D23)*(1+Inputs!T18) -> 621.01045 | U29: =(SourceAnalysis!D23)*(1+Inputs!U18) -> 621.01045 | V29: =Revenue!J29*(1+Inputs!V18) -> 608.59024 | W29: =Revenue!K29*(1+Inputs!W18) -> 608.59024 | X29: =Revenue!L29*(1+Inputs!X18) -> 608.59024 | Y29: =Revenue!M29*(1+Inputs!Y18) -> 608.59024 | Z29: =Revenue!N29*(1+Inputs!Z18) -> 608.59024 | AA29: =Revenue!O29*(1+Inputs!AA18) -> 608.59024 | AB29: =Revenue!P29*(1+Inputs!AB18) -> 608.59024 | AC29: =Revenue!Q29*(1+Inputs!AC18) -> 608.59024 | ... AM29: =Revenue!AA29*(1+Inputs!AM18) -> 596.41844
C30: Product revenue | J30: =J28*J29/1000000 -> 75.790855 | K30: =K28*K29/1000000 -> 75.790855 | L30: =L28*L29/1000000 -> 75.790855 | M30: =M28*M29/1000000 -> 75.790855 | N30: =N28*N29/1000000 -> 75.790855 | O30: =O28*O29/1000000 -> 75.790855 | P30: =P28*P29/1000000 -> 80.726142 | Q30: =Q28*Q29/1000000 -> 80.726142 | ... AM30: =AM28*AM29/1000000 -> 96.264162
C31: Revenue unit/ASP check | J31: =J28*J29/1000000-J30 -> 0 | K31: =K28*K29/1000000-K30 -> 0 | L31: =L28*L29/1000000-L30 -> 0 | M31: =M28*M29/1000000-M30 -> 0 | N31: =N28*N29/1000000-N30 -> 0 | O31: =O28*O29/1000000-O30 -> 0 | P31: =P28*P29/1000000-P30 -> 0 | Q31: =Q28*Q29/1000000-Q30 -> 0 | ... AM31: =AM28*AM29/1000000-AM30 -> 0
C39: Other business revenue (separate leaf) | J39: =(SourceHistory!F9-SourceAnalysis!D24-SourceHistory!F66)/6 -> 0.76245724 | K39: =(SourceHistory!F9-SourceAnalysis!D24-SourceHistory!F66)/6 -> 0.76245724 | L39: =(SourceHistory!F9-SourceAnalysis!D24-SourceHistory!F66)/6 -> 0.76245724 | M39: =(SourceHistory!F9-SourceAnalysis!D24-SourceHistory!F66)/6 -> 0.76245724 | N39: =(SourceHistory!F9-SourceAnalysis!D24-SourceHistory!F66)/6 -> 0.76245724 | O39: =(SourceHistory!F9-SourceAnalysis!D24-SourceHistory!F66)/6 -> 0.76245724 | P39: =(SourceHistory!F67/6) -> 4.7604359 | Q39: =(SourceHistory!F67/6) -> 4.7604359 | R39: =(SourceHistory!F67/6) -> 4.7604359 | S39: =(SourceHistory!F67/6) -> 4.7604359 | T39: =(SourceHistory!F67/6) -> 4.7604359 | U39: =(SourceHistory!F67/6) -> 4.7604359 | V39: =Revenue!J39 -> 0.76245724 | W39: =Revenue!K39 -> 0.76245724 | X39: =Revenue!L39 -> 0.76245724 | Y39: =Revenue!M39 -> 0.76245724 | Z39: =Revenue!N39 -> 0.76245724 | AA39: =Revenue!O39 -> 0.76245724 | AB39: =Revenue!P39 -> 4.7604359 | AC39: =Revenue!Q39 -> 4.7604359 | ... AM39: =Revenue!AA39 -> 0.76245724
C40: Total revenue | I40: =H1Data!D83 -> 8393.7911 | J40: =J12+J21+J30+J39 -> 1356.5576 | K40: =K12+K21+K30+K39 -> 1356.5576 | L40: =L12+L21+L30+L39 -> 1356.5576 | M40: =M12+M21+M30+M39 -> 1356.5576 | N40: =N12+N21+N30+N39 -> 1356.5576 | O40: =O12+O21+O30+O39 -> 1356.5576 | P40: =P12+P21+P30+P39 -> 1448.8412 | Q40: =Q12+Q21+Q30+Q39 -> 1448.8412 | ... AM40: =AM12+AM21+AM30+AM39 -> 1457.5744
C44: Jan–Jun2026 revenues allocate the reported H1 total using FY2025 main-product mix and equal monthly weights. These are modeled product/month quantities, not monthly or product actuals. H2 and later periods respond to bottom-level inputs.

Sheet Production
C2: 公牛集团 Production
C3: RMB million except stated units. H1 2026 actual aggregate is separate; monthly forecast begins July 2026.
D6: Not disclosed | E6: Not disclosed | F6: Not disclosed | G6: Not disclosed | H6: Not disclosed | I6: H1: see H1Actual | J6: Forecast | K6: Forecast | L6: Forecast | M6: Forecast | N6: Forecast | O6: Forecast | P6: Forecast | Q6: Forecast | R6: Forecast | S6: Forecast | T6: Forecast | U6: Forecast | V6: Forecast | W6: Forecast | X6: Forecast | Y6: Forecast | Z6: Forecast | AA6: Forecast | AB6: Forecast | AC6: Forecast | AD6: Forecast | AE6: Forecast | AF6: Forecast | AG6: Forecast | AH6: Forecast | AI6: Forecast | AJ6: Forecast | AK6: Forecast | AL6: Forecast | AM6: Forecast
D7: 46053 | E7: 46081 | F7: 46112 | G7: 46142 | H7: 46173 | I7: 46203 | J7: 46234 | K7: 46265 | L7: 46295 | M7: 46326 | N7: 46356 | O7: 46387 | P7: 46418 | Q7: 46446 | R7: 46477 | S7: 46507 | T7: 46538 | U7: 46568 | V7: 46599 | W7: 46630 | X7: 46660 | Y7: 46691 | Z7: 46721 | AA7: 46752 | AB7: 46783 | AC7: 46812 | AD7: 46843 | AE7: 46873 | AF7: 46904 | AG7: 46934 | AH7: 46965 | AI7: 46996 | AJ7: 47026 | AK7: 47057 | AL7: 47087 | AM7: 47118
C9: 电连接产品
C10: Opening FG physical units | J10: =SourceAnalysis!D12 -> 34262900 | K10: =Production!J15 -> 33672009 | L10: =Production!K15 -> 33672009 | M10: =Production!L15 -> 34794409 | N10: =Production!M15 -> 33672009 | O10: =Production!N15 -> 34794409 | P10: =Production!O15 -> 33672009 | Q10: =Production!P15 -> 35864635 | R10: =Production!Q15 -> 39707275 | ... AM10: =Production!AL15 -> 36200103
C11: Target ending FG units | J11: =Revenue!J10/DAY(J$7)*MAX(0,Inputs!J25) -> 33672009 | K11: =Revenue!K10/DAY(K$7)*MAX(0,Inputs!K25) -> 33672009 | L11: =Revenue!L10/DAY(L$7)*MAX(0,Inputs!L25) -> 34794409 | M11: =Revenue!M10/DAY(M$7)*MAX(0,Inputs!M25) -> 33672009 | N11: =Revenue!N10/DAY(N$7)*MAX(0,Inputs!N25) -> 34794409 | O11: =Revenue!O10/DAY(O$7)*MAX(0,Inputs!O25) -> 33672009 | P11: =Revenue!P10/DAY(P$7)*MAX(0,Inputs!P25) -> 35864635 | Q11: =Revenue!Q10/DAY(Q$7)*MAX(0,Inputs!Q25) -> 39707275 | ... AM11: =Revenue!AM10/DAY(AM$7)*MAX(0,Inputs!AM25) -> 35032358
C12: Sales units requested | J12: =Revenue!J10 -> 48342423 | K12: =Revenue!K10 -> 48342423 | L12: =Revenue!L10 -> 48342423 | M12: =Revenue!M10 -> 48342423 | N12: =Revenue!N10 -> 48342423 | O12: =Revenue!O10 -> 48342423 | P12: =Revenue!P10 -> 51490346 | Q12: =Revenue!Q10 -> 51490346 | ... AM12: =Revenue!AM10 -> 50295457
C13: Production units required | J13: =MAX(0,J12+J11-J10) -> 47751532 | K13: =MAX(0,K12+K11-K10) -> 48342423 | L13: =MAX(0,L12+L11-L10) -> 49464824 | M13: =MAX(0,M12+M11-M10) -> 47220023 | N13: =MAX(0,N12+N11-N10) -> 49464824 | O13: =MAX(0,O12+O11-O10) -> 47220023 | P13: =MAX(0,P12+P11-P10) -> 53682972 | Q13: =MAX(0,Q12+Q11-Q10) -> 55332985 | ... AM13: =MAX(0,AM12+AM11-AM10) -> 49127712
C14: Available FG units | J14: =J10+J13 -> 82014432 | K14: =K10+K13 -> 82014432 | L14: =L10+L13 -> 83136832 | M14: =M10+M13 -> 82014432 | N14: =N10+N13 -> 83136832 | O14: =O10+O13 -> 82014432 | P14: =P10+P13 -> 87354981 | Q14: =Q10+Q13 -> 91197620 | ... AM14: =AM10+AM13 -> 85327815
C15: Closing FG units | J15: =J14-J12 -> 33672009 | K15: =K14-K12 -> 33672009 | L15: =L14-L12 -> 34794409 | M15: =M14-M12 -> 33672009 | N15: =N14-N12 -> 34794409 | O15: =O14-O12 -> 33672009 | P15: =P14-P12 -> 35864635 | Q15: =Q14-Q12 -> 39707275 | ... AM15: =AM14-AM12 -> 35032358
C16: Physical roll-forward | J16: =J10+J13-J12-J15 -> 0 | K16: =K10+K13-K12-K15 -> 0 | L16: =L10+L13-L12-L15 -> 0 | M16: =M10+M13-M12-M15 -> 0 | N16: =N10+N13-N12-N15 -> 0 | O16: =O10+O13-O12-O15 -> 0 | P16: =P10+P13-P12-P15 -> 0 | Q16: =Q10+Q13-Q12-Q15 -> 0 | ... AM16: =AM10+AM13-AM12-AM15 -> 0
C17: Material cost / production unit RMB | J17: =(SourceAnalysis!D10*SourceAnalysis!D25*1000000/SourceAnalysis!D11)*(1+Inputs!J21) -> 6.0794253 | K17: =(Production!J17)*(1+Inputs!K21) -> 6.0794253 | L17: =(Production!K17)*(1+Inputs!L21) -> 6.0794253 | M17: =(Production!L17)*(1+Inputs!M21) -> 6.0794253 | N17: =(Production!M17)*(1+Inputs!N21) -> 6.0794253 | O17: =(Production!N17)*(1+Inputs!O21) -> 6.0794253 | P17: =(Production!O17)*(1+Inputs!P21) -> 6.2010138 | Q17: =(Production!P17)*(1+Inputs!Q21) -> 6.2010138 | R17: =(Production!Q17)*(1+Inputs!R21) -> 6.2010138 | ... AM17: =(Production!AL17)*(1+Inputs!AM21) -> 6.3250341
C18: Cash overhead / production unit RMB | J18: =(SourceAnalysis!D29*SourceAnalysis!D10/(SourceDetail!E80/1000000)*1000000/SourceAnalysis!D11)*(1+Inputs!J22) -> 0.64975585 | K18: =(Production!J18)*(1+Inputs!K22) -> 0.64975585 | L18: =(Production!K18)*(1+Inputs!L22) -> 0.64975585 | M18: =(Production!L18)*(1+Inputs!M22) -> 0.64975585 | N18: =(Production!M18)*(1+Inputs!N22) -> 0.64975585 | O18: =(Production!N18)*(1+Inputs!O22) -> 0.64975585 | P18: =(Production!O18)*(1+Inputs!P22) -> 0.66275097 | Q18: =(Production!P18)*(1+Inputs!Q22) -> 0.66275097 | R18: =(Production!Q18)*(1+Inputs!R22) -> 0.66275097 | ... AM18: =(Production!AL18)*(1+Inputs!AM22) -> 0.67600599
C19: Material consumption cost | J19: =J13*J17/1000000 -> 290.30187 | K19: =K13*K17/1000000 -> 293.89415 | L19: =L13*L17/1000000 -> 300.7177 | M19: =M13*M17/1000000 -> 287.0706 | N19: =N13*N17/1000000 -> 300.7177 | O19: =O13*O17/1000000 -> 287.0706 | P19: =P13*P17/1000000 -> 332.88885 | Q19: =Q13*Q17/1000000 -> 343.12061 | ... AM19: =AM13*AM17/1000000 -> 310.73445
C20: Allocated production payroll | J20: =Payroll!J16*IF(Production!J84>0,J13*SourceAnalysis!D10/SourceAnalysis!D11/Production!J84,0) -> 20.971388 | K20: =Payroll!K16*IF(Production!K84>0,K13*SourceAnalysis!D10/SourceAnalysis!D11/Production!K84,0) -> 21.265774 | L20: =Payroll!L16*IF(Production!L84>0,L13*SourceAnalysis!D10/SourceAnalysis!D11/Production!L84,0) -> 21.20032 | M20: =Payroll!M16*IF(Production!M84>0,M13*SourceAnalysis!D10/SourceAnalysis!D11/Production!M84,0) -> 21.334775 | N20: =Payroll!N16*IF(Production!N84>0,N13*SourceAnalysis!D10/SourceAnalysis!D11/Production!N84,0) -> 21.20032 | O20: =Payroll!O16*IF(Production!O84>0,O13*SourceAnalysis!D10/SourceAnalysis!D11/Production!O84,0) -> 21.334775 | P20: =Payroll!P16*IF(Production!P84>0,P13*SourceAnalysis!D10/SourceAnalysis!D11/Production!P84,0) -> 21.782692 | Q20: =Payroll!Q16*IF(Production!Q84>0,Q13*SourceAnalysis!D10/SourceAnalysis!D11/Production!Q84,0) -> 21.698714 | R20: =Payroll!R16*IF(Production!R84>0,R13*SourceAnalysis!D10/SourceAnalysis!D11/Production!R84,0) -> 22.146768 | S20: =Payroll!S16*IF(Production!S84>0,S13*SourceAnalysis!D10/SourceAnalysis!D11/Production!S84,0) -> 21.83633 | T20: =Payroll!T16*IF(Production!T84>0,T13*SourceAnalysis!D10/SourceAnalysis!D11/Production!T84,0) -> 21.974819 | U20: =Payroll!U16*IF(Production!U84>0,U13*SourceAnalysis!D10/SourceAnalysis!D11/Production!U84,0) -> 21.83633 | V20: =Payroll!V16*IF(Production!V84>0,V13*SourceAnalysis!D10/SourceAnalysis!D11/Production!V84,0) -> 21.383372 | W20: =Payroll!W16*IF(Production!W84>0,W13*SourceAnalysis!D10/SourceAnalysis!D11/Production!W84,0) -> 21.607579 | X20: =Payroll!X16*IF(Production!X84>0,X13*SourceAnalysis!D10/SourceAnalysis!D11/Production!X84,0) -> 21.536978 | Y20: =Payroll!Y16*IF(Production!Y84>0,Y13*SourceAnalysis!D10/SourceAnalysis!D11/Production!Y84,0) -> 21.682034 | Z20: =Payroll!Z16*IF(Production!Z84>0,Z13*SourceAnalysis!D10/SourceAnalysis!D11/Production!Z84,0) -> 21.536978 | AA20: =Payroll!AA16*IF(Production!AA84>0,AA13*SourceAnalysis!D10/SourceAnalysis!D11/Production!AA84,0) -> 21.682034 | AB20: =Payroll!AB16*IF(Production!AB84>0,AB13*SourceAnalysis!D10/SourceAnalysis!D11/Production!AB84,0) -> 22.125253 | AC20: =Payroll!AC16*IF(Production!AC84>0,AC13*SourceAnalysis!D10/SourceAnalysis!D11/Production!AC84,0) -> 22.109405 | AD20: =Payroll!AD16*IF(Production!AD84>0,AD13*SourceAnalysis!D10/SourceAnalysis!D11/Production!AD84,0) -> 22.419242 | AE20: =Payroll!AE16*IF(Production!AE84>0,AE13*SourceAnalysis!D10/SourceAnalysis!D11/Production!AE84,0) -> 22.183088 | AF20: =Payroll!AF16*IF(Production!AF84>0,AF13*SourceAnalysis!D10/SourceAnalysis!D11/Production!AF84,0) -> 22.332495 | AG20: =Payroll!AG16*IF(Production!AG84>0,AG13*SourceAnalysis!D10/SourceAnalysis!D11/Production!AG84,0) -> 22.183088 | AH20: =Payroll!AH16*IF(Production!AH84>0,AH13*SourceAnalysis!D10/SourceAnalysis!D11/Production!AH84,0) -> 21.682469 | AI20: =Payroll!AI16*IF(Production!AI84>0,AI13*SourceAnalysis!D10/SourceAnalysis!D11/Production!AI84,0) -> 21.933338 | AJ20: =Payroll!AJ16*IF(Production!AJ84>0,AJ13*SourceAnalysis!D10/SourceAnalysis!D11/Production!AJ84,0) -> 21.857114 | AK20: =Payroll!AK16*IF(Production!AK84>0,AK13*SourceAnalysis!D10/SourceAnalysis!D11/Production!AK84,0) -> 22.013758 | AL20: =Payroll!AL16*IF(Production!AL84>0,AL13*SourceAnalysis!D10/SourceAnalysis!D11/Production!AL84,0) -> 21.857114 | AM20: =Payroll!AM16*IF(Production!AM84>0,AM13*SourceAnalysis!D10/SourceAnalysis!D11/Production!AM84,0) -> 22.013758
C21: Cash factory overhead | J21: =J13*J18/1000000 -> 31.026837 | K21: =K13*K18/1000000 -> 31.410772 | L21: =L13*L18/1000000 -> 32.140059 | M21: =M13*M18/1000000 -> 30.681486 | N21: =N13*N18/1000000 -> 32.140059 | O21: =O13*O18/1000000 -> 30.681486 | P21: =P13*P18/1000000 -> 35.578442 | Q21: =Q13*Q18/1000000 -> 36.67199 | ... AM21: =AM13*AM18/1000000 -> 33.210628
C22: Allocated manufacturing depreciation | J22: =Assets!J100*SourceAnalysis!D28*IF(Production!J84>0,J13*SourceAnalysis!D10/SourceAnalysis!D11/Production!J84,0) -> 7.3475143 | K22: =Assets!K100*SourceAnalysis!D28*IF(Production!K84>0,K13*SourceAnalysis!D10/SourceAnalysis!D11/Production!K84,0) -> 7.5102949 | L22: =Assets!L100*SourceAnalysis!D28*IF(Production!L84>0,L13*SourceAnalysis!D10/SourceAnalysis!D11/Production!L84,0) -> 7.5466347 | M22: =Assets!M100*SourceAnalysis!D28*IF(Production!M84>0,M13*SourceAnalysis!D10/SourceAnalysis!D11/Production!M84,0) -> 7.6543295 | N22: =Assets!N100*SourceAnalysis!D28*IF(Production!N84>0,N13*SourceAnalysis!D10/SourceAnalysis!D11/Production!N84,0) -> 7.6655466 | O22: =Assets!O100*SourceAnalysis!D28*IF(Production!O84>0,O13*SourceAnalysis!D10/SourceAnalysis!D11/Production!O84,0) -> 7.7739956 | P22: =Assets!P100*SourceAnalysis!D28*IF(Production!P84>0,P13*SourceAnalysis!D10/SourceAnalysis!D11/Production!P84,0) -> 7.7653372 | Q22: =Assets!Q100*SourceAnalysis!D28*IF(Production!Q84>0,Q13*SourceAnalysis!D10/SourceAnalysis!D11/Production!Q84,0) -> 7.7974352 | R22: =Assets!R100*SourceAnalysis!D28*IF(Production!R84>0,R13*SourceAnalysis!D10/SourceAnalysis!D11/Production!R84,0) -> 8.0217597 | S22: =Assets!S100*SourceAnalysis!D28*IF(Production!S84>0,S13*SourceAnalysis!D10/SourceAnalysis!D11/Production!S84,0) -> 7.9717448 | T22: =Assets!T100*SourceAnalysis!D28*IF(Production!T84>0,T13*SourceAnalysis!D10/SourceAnalysis!D11/Production!T84,0) -> 8.0851273 | U22: =Assets!U100*SourceAnalysis!D28*IF(Production!U84>0,U13*SourceAnalysis!D10/SourceAnalysis!D11/Production!U84,0) -> 8.0966023 | V22: =Assets!V100*SourceAnalysis!D28*IF(Production!V84>0,V13*SourceAnalysis!D10/SourceAnalysis!D11/Production!V84,0) -> 7.9897857 | W22: =Assets!W100*SourceAnalysis!D28*IF(Production!W84>0,W13*SourceAnalysis!D10/SourceAnalysis!D11/Production!W84,0) -> 8.1353343 | X22: =Assets!X100*SourceAnalysis!D28*IF(Production!X84>0,X13*SourceAnalysis!D10/SourceAnalysis!D11/Production!X84,0) -> 7.8249611 | Y22: =Assets!Y100*SourceAnalysis!D28*IF(Production!Y84>0,Y13*SourceAnalysis!D10/SourceAnalysis!D11/Production!Y84,0) -> 7.9350967 | Z22: =Assets!Z100*SourceAnalysis!D28*IF(Production!Z84>0,Z13*SourceAnalysis!D10/SourceAnalysis!D11/Production!Z84,0) -> 7.9435827 | AA22: =Assets!AA100*SourceAnalysis!D28*IF(Production!AA84>0,AA13*SourceAnalysis!D10/SourceAnalysis!D11/Production!AA84,0) -> 8.0590719 | AB22: =Assets!AB100*SourceAnalysis!D28*IF(Production!AB84>0,AB13*SourceAnalysis!D10/SourceAnalysis!D11/Production!AB84,0) -> 8.0456973 | AC22: =Assets!AC100*SourceAnalysis!D28*IF(Production!AC84>0,AC13*SourceAnalysis!D10/SourceAnalysis!D11/Production!AC84,0) -> 8.1043711 | AD22: =Assets!AD100*SourceAnalysis!D28*IF(Production!AD84>0,AD13*SourceAnalysis!D10/SourceAnalysis!D11/Production!AD84,0) -> 8.283284 | AE22: =Assets!AE100*SourceAnalysis!D28*IF(Production!AE84>0,AE13*SourceAnalysis!D10/SourceAnalysis!D11/Production!AE84,0) -> 8.2606833 | AF22: =Assets!AF100*SourceAnalysis!D28*IF(Production!AF84>0,AF13*SourceAnalysis!D10/SourceAnalysis!D11/Production!AF84,0) -> 8.3814076 | AG22: =Assets!AG100*SourceAnalysis!D28*IF(Production!AG84>0,AG13*SourceAnalysis!D10/SourceAnalysis!D11/Production!AG84,0) -> 8.3899864 | AH22: =Assets!AH100*SourceAnalysis!D28*IF(Production!AH84>0,AH13*SourceAnalysis!D10/SourceAnalysis!D11/Production!AH84,0) -> 8.2638374 | AI22: =Assets!AI100*SourceAnalysis!D28*IF(Production!AI84>0,AI13*SourceAnalysis!D10/SourceAnalysis!D11/Production!AI84,0) -> 8.4233748 | AJ22: =Assets!AJ100*SourceAnalysis!D28*IF(Production!AJ84>0,AJ13*SourceAnalysis!D10/SourceAnalysis!D11/Production!AJ84,0) -> 8.4578029 | AK22: =Assets!AK100*SourceAnalysis!D28*IF(Production!AK84>0,AK13*SourceAnalysis!D10/SourceAnalysis!D11/Production!AK84,0) -> 8.5825757 | AL22: =Assets!AL100*SourceAnalysis!D28*IF(Production!AL84>0,AL13*SourceAnalysis!D10/SourceAnalysis!D11/Production!AL84,0) -> 8.585206 | AM22: =Assets!AM100*SourceAnalysis!D28*IF(Production!AM84>0,AM13*SourceAnalysis!D10/SourceAnalysis!D11/Production!AM84,0) -> 8.7108918
C23: Production cost transferred into FG | J23: =SUM(J19:J22) -> 349.64761 | K23: =SUM(K19:K22) -> 354.08099 | L23: =SUM(L19:L22) -> 361.60471 | M23: =SUM(M19:M22) -> 346.74119 | N23: =SUM(N19:N22) -> 361.72362 | O23: =SUM(O19:O22) -> 346.86086 | P23: =SUM(P19:P22) -> 398.01532 | Q23: =SUM(Q19:Q22) -> 409.28874 | ... AM23: =SUM(AM19:AM22) -> 374.66973
C24: Opening FG carrying value | J24: =H1Data!D63*(SourceAnalysis!D12*SourceAnalysis!D10/SourceAnalysis!D11)/(SourceAnalysis!D12*SourceAnalysis!D10/SourceAnalysis!D11+SourceAnalysis!D17*SourceAnalysis!D15/SourceAnalysis!D16+SourceAnalysis!D22*SourceAnalysis!D20/SourceAnalysis!D21) -> 362.48954 | K24: =Production!J28 -> 292.37645 | L24: =Production!K28 -> 265.41086 | M24: =Production!L28 -> 262.41842 | N24: =Production!M28 -> 250.09778 | O24: =Production!N28 -> 256.05936 | P24: =Production!O28 -> 247.53613 | Q24: =Production!P28 -> 265.03889 | R24: =Production!Q28 -> 293.601 | ... AM24: =Production!AL28 -> 275.13986
C25: WIP value released into FG | J25: =Inventory!J18*IF(Production!J84>0,J13*SourceAnalysis!D10/SourceAnalysis!D11/Production!J84,0) -> 0 | K25: =Inventory!K18*IF(Production!K84>0,K13*SourceAnalysis!D10/SourceAnalysis!D11/Production!K84,0) -> 0 | L25: =Inventory!L18*IF(Production!L84>0,L13*SourceAnalysis!D10/SourceAnalysis!D11/Production!L84,0) -> 0 | M25: =Inventory!M18*IF(Production!M84>0,M13*SourceAnalysis!D10/SourceAnalysis!D11/Production!M84,0) -> 0 | N25: =Inventory!N18*IF(Production!N84>0,N13*SourceAnalysis!D10/SourceAnalysis!D11/Production!N84,0) -> 0 | O25: =Inventory!O18*IF(Production!O84>0,O13*SourceAnalysis!D10/SourceAnalysis!D11/Production!O84,0) -> 0 | P25: =Inventory!P18*IF(Production!P84>0,P13*SourceAnalysis!D10/SourceAnalysis!D11/Production!P84,0) -> 0 | Q25: =Inventory!Q18*IF(Production!Q84>0,Q13*SourceAnalysis!D10/SourceAnalysis!D11/Production!Q84,0) -> 0 | R25: =Inventory!R18*IF(Production!R84>0,R13*SourceAnalysis!D10/SourceAnalysis!D11/Production!R84,0) -> 0 | S25: =Inventory!S18*IF(Production!S84>0,S13*SourceAnalysis!D10/SourceAnalysis!D11/Production!S84,0) -> 0 | T25: =Inventory!T18*IF(Production!T84>0,T13*SourceAnalysis!D10/SourceAnalysis!D11/Production!T84,0) -> 0 | U25: =Inventory!U18*IF(Production!U84>0,U13*SourceAnalysis!D10/SourceAnalysis!D11/Production!U84,0) -> 0 | V25: =Inventory!V18*IF(Production!V84>0,V13*SourceAnalysis!D10/SourceAnalysis!D11/Production!V84,0) -> 0 | W25: =Inventory!W18*IF(Production!W84>0,W13*SourceAnalysis!D10/SourceAnalysis!D11/Production!W84,0) -> 0 | X25: =Inventory!X18*IF(Production!X84>0,X13*SourceAnalysis!D10/SourceAnalysis!D11/Production!X84,0) -> 0 | Y25: =Inventory!Y18*IF(Production!Y84>0,Y13*SourceAnalysis!D10/SourceAnalysis!D11/Production!Y84,0) -> 0 | Z25: =Inventory!Z18*IF(Production!Z84>0,Z13*SourceAnalysis!D10/SourceAnalysis!D11/Production!Z84,0) -> 0 | AA25: =Inventory!AA18*IF(Production!AA84>0,AA13*SourceAnalysis!D10/SourceAnalysis!D11/Production!AA84,0) -> 0 | AB25: =Inventory!AB18*IF(Production!AB84>0,AB13*SourceAnalysis!D10/SourceAnalysis!D11/Production!AB84,0) -> 0 | AC25: =Inventory!AC18*IF(Production!AC84>0,AC13*SourceAnalysis!D10/SourceAnalysis!D11/Production!AC84,0) -> 0 | AD25: =Inventory!AD18*IF(Production!AD84>0,AD13*SourceAnalysis!D10/SourceAnalysis!D11/Production!AD84,0) -> 0 | AE25: =Inventory!AE18*IF(Production!AE84>0,AE13*SourceAnalysis!D10/SourceAnalysis!D11/Production!AE84,0) -> 0 | AF25: =Inventory!AF18*IF(Production!AF84>0,AF13*SourceAnalysis!D10/SourceAnalysis!D11/Production!AF84,0) -> 0 | AG25: =Inventory!AG18*IF(Production!AG84>0,AG13*SourceAnalysis!D10/SourceAnalysis!D11/Production!AG84,0) -> 0 | AH25: =Inventory!AH18*IF(Production!AH84>0,AH13*SourceAnalysis!D10/SourceAnalysis!D11/Production!AH84,0) -> 0 | AI25: =Inventory!AI18*IF(Production!AI84>0,AI13*SourceAnalysis!D10/SourceAnalysis!D11/Production!AI84,0) -> 0 | AJ25: =Inventory!AJ18*IF(Production!AJ84>0,AJ13*SourceAnalysis!D10/SourceAnalysis!D11/Production!AJ84,0) -> 0 | AK25: =Inventory!AK18*IF(Production!AK84>0,AK13*SourceAnalysis!D10/SourceAnalysis!D11/Production!AK84,0) -> 0 | AL25: =Inventory!AL18*IF(Production!AL84>0,AL13*SourceAnalysis!D10/SourceAnalysis!D11/Production!AL84,0) -> 0 | AM25: =Inventory!AM18*IF(Production!AM84>0,AM13*SourceAnalysis!D10/SourceAnalysis!D11/Production!AM84,0) -> 0
C26: Weighted average FG cost/unit RMB | J26: =IF(J14>0,(J24+J23+J25)*1000000/J14,0) -> 8.6830712 | K26: =IF(K14>0,(K24+K23+K25)*1000000/K14,0) -> 7.8822401 | L26: =IF(L14>0,(L24+L23+L25)*1000000/L14,0) -> 7.5419709 | M26: =IF(M14>0,(M24+M23+M25)*1000000/M14,0) -> 7.4274685 | N26: =IF(N14>0,(N24+N23+N25)*1000000/N14,0) -> 7.35921 | O26: =IF(O14>0,(O24+O23+O25)*1000000/O14,0) -> 7.3513918 | P26: =IF(P14>0,(P24+P23+P25)*1000000/P14,0) -> 7.3899787 | Q26: =IF(Q14>0,(Q24+Q23+Q25)*1000000/Q14,0) -> 7.3941363 | ... AM26: =IF(AM14>0,(AM24+AM23+AM25)*1000000/AM14,0) -> 7.6154486
C27: COGS released on sales | J27: =J12*J26/1000000 -> 419.7607 | K27: =K12*K26/1000000 -> 381.04659 | L27: =L12*L26/1000000 -> 364.59715 | M27: =M12*M26/1000000 -> 359.06183 | N27: =N12*N26/1000000 -> 355.76205 | O27: =O12*O26/1000000 -> 355.38409 | P27: =P12*P26/1000000 -> 380.51256 | Q27: =Q12*Q26/1000000 -> 380.72664 | ... AM27: =AM12*AM26/1000000 -> 383.02247
C28: Closing FG carrying value | J28: =J24+J23+J25-J27 -> 292.37645 | K28: =K24+K23+K25-K27 -> 265.41086 | L28: =L24+L23+L25-L27 -> 262.41842 | M28: =M24+M23+M25-M27 -> 250.09778 | N28: =N24+N23+N25-N27 -> 256.05936 | O28: =O24+O23+O25-O27 -> 247.53613 | P28: =P24+P23+P25-P27 -> 265.03889 | Q28: =Q24+Q23+Q25-Q27 -> 293.601 | ... AM28: =AM24+AM23+AM25-AM27 -> 266.78712
C29: FG carrying-value roll-forward | J29: =J24+J23+J25-J27-J28 -> 0 | K29: =K24+K23+K25-K27-K28 -> 0 | L29: =L24+L23+L25-L27-L28 -> 0 | M29: =M24+M23+M25-M27-M28 -> 0 | N29: =N24+N23+N25-N27-N28 -> 0 | O29: =O24+O23+O25-O27-O28 -> 0 | P29: =P24+P23+P25-P27-P28 -> 0 | Q29: =Q24+Q23+Q25-Q27-Q28 -> 0 | ... AM29: =AM24+AM23+AM25-AM27-AM28 -> 0
C33: 智能电工照明
C34: Opening FG physical units | J34: =SourceAnalysis!D17 -> 69896800 | K34: =Production!J39 -> 69364818 | L34: =Production!K39 -> 69364818 | M34: =Production!L39 -> 71676979 | N34: =Production!M39 -> 69364818 | O34: =Production!N39 -> 71676979 | P34: =Production!O39 -> 69364818 | Q34: =Production!P39 -> 73881660 | R34: =Production!Q39 -> 81797552 | ... AM34: =Production!AL39 -> 76042107
C35: Target ending FG units | J35: =Revenue!J19/DAY(J$7)*MAX(0,Inputs!J26) -> 69364818 | K35: =Revenue!K19/DAY(K$7)*MAX(0,Inputs!K26) -> 69364818 | L35: =Revenue!L19/DAY(L$7)*MAX(0,Inputs!L26) -> 71676979 | M35: =Revenue!M19/DAY(M$7)*MAX(0,Inputs!M26) -> 69364818 | N35: =Revenue!N19/DAY(N$7)*MAX(0,Inputs!N26) -> 71676979 | O35: =Revenue!O19/DAY(O$7)*MAX(0,Inputs!O26) -> 69364818 | P35: =Revenue!P19/DAY(P$7)*MAX(0,Inputs!P26) -> 73881660 | Q35: =Revenue!Q19/DAY(Q$7)*MAX(0,Inputs!Q26) -> 81797552 | ... AM35: =Revenue!AM19/DAY(AM$7)*MAX(0,Inputs!AM26) -> 73589136
C36: Sales units requested | J36: =Revenue!J19 -> 88596987 | K36: =Revenue!K19 -> 88596987 | L36: =Revenue!L19 -> 88596987 | M36: =Revenue!M19 -> 88596987 | N36: =Revenue!N19 -> 88596987 | O36: =Revenue!O19 -> 88596987 | P36: =Revenue!P19 -> 94366174 | Q36: =Revenue!Q19 -> 94366174 | ... AM36: =Revenue!AM19 -> 93992544
C37: Production units required | J37: =MAX(0,J36+J35-J34) -> 88065005 | K37: =MAX(0,K36+K35-K34) -> 88596987 | L37: =MAX(0,L36+L35-L34) -> 90909148 | M37: =MAX(0,M36+M35-M34) -> 86284827 | N37: =MAX(0,N36+N35-N34) -> 90909148 | O37: =MAX(0,O36+O35-O34) -> 86284827 | P37: =MAX(0,P36+P35-P34) -> 98883015 | Q37: =MAX(0,Q36+Q35-Q34) -> 1.0228207e+08 | ... AM37: =MAX(0,AM36+AM35-AM34) -> 91539573
C38: Available FG units | J38: =J34+J37 -> 1.5796181e+08 | K38: =K34+K37 -> 1.5796181e+08 | L38: =L34+L37 -> 1.6027397e+08 | M38: =M34+M37 -> 1.5796181e+08 | N38: =N34+N37 -> 1.6027397e+08 | O38: =O34+O37 -> 1.5796181e+08 | P38: =P34+P37 -> 1.6824783e+08 | Q38: =Q34+Q37 -> 1.7616373e+08 | ... AM38: =AM34+AM37 -> 1.6758168e+08
C39: Closing FG units | J39: =J38-J36 -> 69364818 | K39: =K38-K36 -> 69364818 | L39: =L38-L36 -> 71676979 | M39: =M38-M36 -> 69364818 | N39: =N38-N36 -> 71676979 | O39: =O38-O36 -> 69364818 | P39: =P38-P36 -> 73881660 | Q39: =Q38-Q36 -> 81797552 | ... AM39: =AM38-AM36 -> 73589136
C40: Physical roll-forward | J40: =J34+J37-J36-J39 -> 0 | K40: =K34+K37-K36-K39 -> 0 | L40: =L34+L37-L36-L39 -> 0 | M40: =M34+M37-M36-M39 -> 0 | N40: =N34+N37-N36-N39 -> 0 | O40: =O34+O37-O36-O39 -> 0 | P40: =P34+P37-P36-P39 -> 0 | Q40: =Q34+Q37-Q36-Q39 -> 0 | ... AM40: =AM34+AM37-AM36-AM39 -> 0
C41: Material cost / production unit RMB | J41: =(SourceAnalysis!D15*SourceAnalysis!D25*1000000/SourceAnalysis!D16)*(1+Inputs!J21) -> 3.4965413 | K41: =(Production!J41)*(1+Inputs!K21) -> 3.4965413 | L41: =(Production!K41)*(1+Inputs!L21) -> 3.4965413 | M41: =(Production!L41)*(1+Inputs!M21) -> 3.4965413 | N41: =(Production!M41)*(1+Inputs!N21) -> 3.4965413 | O41: =(Production!N41)*(1+Inputs!O21) -> 3.4965413 | P41: =(Production!O41)*(1+Inputs!P21) -> 3.5664721 | Q41: =(Production!P41)*(1+Inputs!Q21) -> 3.5664721 | R41: =(Production!Q41)*(1+Inputs!R21) -> 3.5664721 | ... AM41: =(Production!AL41)*(1+Inputs!AM21) -> 3.6378016
C42: Cash overhead / production unit RMB | J42: =(SourceAnalysis!D29*SourceAnalysis!D15/(SourceDetail!E80/1000000)*1000000/SourceAnalysis!D16)*(1+Inputs!J22) -> 0.37370279 | K42: =(Production!J42)*(1+Inputs!K22) -> 0.37370279 | L42: =(Production!K42)*(1+Inputs!L22) -> 0.37370279 | M42: =(Production!L42)*(1+Inputs!M22) -> 0.37370279 | N42: =(Production!M42)*(1+Inputs!N22) -> 0.37370279 | O42: =(Production!N42)*(1+Inputs!O22) -> 0.37370279 | P42: =(Production!O42)*(1+Inputs!P22) -> 0.38117684 | Q42: =(Production!P42)*(1+Inputs!Q22) -> 0.38117684 | R42: =(Production!Q42)*(1+Inputs!R22) -> 0.38117684 | ... AM42: =(Production!AL42)*(1+Inputs!AM22) -> 0.38880038
C43: Material consumption cost | J43: =J37*J41/1000000 -> 307.92293 | K43: =K37*K41/1000000 -> 309.78303 | L43: =L37*L41/1000000 -> 317.86759 | M43: =M37*M41/1000000 -> 301.69846 | N43: =N37*N41/1000000 -> 317.86759 | O43: =O37*O41/1000000 -> 301.69846 | P43: =P37*P41/1000000 -> 352.66352 | Q43: =Q37*Q41/1000000 -> 364.78614 | ... AM43: =AM37*AM41/1000000 -> 333.0028
C44: Allocated production payroll | J44: =Payroll!J16*IF(Production!J84>0,J37*SourceAnalysis!D15/SourceAnalysis!D16/Production!J84,0) -> 22.244332 | K44: =Payroll!K16*IF(Production!K84>0,K37*SourceAnalysis!D15/SourceAnalysis!D16/Production!K84,0) -> 22.415471 | L44: =Payroll!L16*IF(Production!L84>0,L37*SourceAnalysis!D15/SourceAnalysis!D16/Production!L84,0) -> 22.409372 | M44: =Payroll!M16*IF(Production!M84>0,M37*SourceAnalysis!D15/SourceAnalysis!D16/Production!M84,0) -> 22.421902 | N44: =Payroll!N16*IF(Production!N84>0,N37*SourceAnalysis!D15/SourceAnalysis!D16/Production!N84,0) -> 22.409372 | O44: =Payroll!O16*IF(Production!O84>0,O37*SourceAnalysis!D15/SourceAnalysis!D16/Production!O84,0) -> 22.421902 | P44: =Payroll!P16*IF(Production!P84>0,P37*SourceAnalysis!D15/SourceAnalysis!D16/Production!P84,0) -> 23.076654 | Q44: =Payroll!Q16*IF(Production!Q84>0,Q37*SourceAnalysis!D15/SourceAnalysis!D16/Production!Q84,0) -> 23.068828 | R44: =Payroll!R16*IF(Production!R84>0,R37*SourceAnalysis!D15/SourceAnalysis!D16/Production!R84,0) -> 23.110583 | S44: =Payroll!S16*IF(Production!S84>0,S37*SourceAnalysis!D15/SourceAnalysis!D16/Production!S84,0) -> 23.081653 | T44: =Payroll!T16*IF(Production!T84>0,T37*SourceAnalysis!D15/SourceAnalysis!D16/Production!T84,0) -> 23.094559 | U44: =Payroll!U16*IF(Production!U84>0,U37*SourceAnalysis!D15/SourceAnalysis!D16/Production!U84,0) -> 23.081653 | V44: =Payroll!V16*IF(Production!V84>0,V37*SourceAnalysis!D15/SourceAnalysis!D16/Production!V84,0) -> 22.793482 | W44: =Payroll!W16*IF(Production!W84>0,W37*SourceAnalysis!D15/SourceAnalysis!D16/Production!W84,0) -> 22.999047 | X44: =Payroll!X16*IF(Production!X84>0,X37*SourceAnalysis!D15/SourceAnalysis!D16/Production!X84,0) -> 22.988418 | Y44: =Payroll!Y16*IF(Production!Y84>0,Y37*SourceAnalysis!D15/SourceAnalysis!D16/Production!Y84,0) -> 23.010256 | Z44: =Payroll!Z16*IF(Production!Z84>0,Z37*SourceAnalysis!D15/SourceAnalysis!D16/Production!Z84,0) -> 22.988418 | AA44: =Payroll!AA16*IF(Production!AA84>0,AA37*SourceAnalysis!D15/SourceAnalysis!D16/Production!AA84,0) -> 23.010256 | AB44: =Payroll!AB16*IF(Production!AB84>0,AB37*SourceAnalysis!D15/SourceAnalysis!D16/Production!AB84,0) -> 23.669363 | AC44: =Payroll!AC16*IF(Production!AC84>0,AC37*SourceAnalysis!D15/SourceAnalysis!D16/Production!AC84,0) -> 23.666977 | AD44: =Payroll!AD16*IF(Production!AD84>0,AD37*SourceAnalysis!D15/SourceAnalysis!D16/Production!AD84,0) -> 23.713623 | AE44: =Payroll!AE16*IF(Production!AE84>0,AE37*SourceAnalysis!D15/SourceAnalysis!D16/Production!AE84,0) -> 23.67807 | AF44: =Payroll!AF16*IF(Production!AF84>0,AF37*SourceAnalysis!D15/SourceAnalysis!D16/Production!AF84,0) -> 23.700564 | AG44: =Payroll!AG16*IF(Production!AG84>0,AG37*SourceAnalysis!D15/SourceAnalysis!D16/Production!AG84,0) -> 23.67807 | AH44: =Payroll!AH16*IF(Production!AH84>0,AH37*SourceAnalysis!D15/SourceAnalysis!D16/Production!AH84,0) -> 23.338895 | AI44: =Payroll!AI16*IF(Production!AI84>0,AI37*SourceAnalysis!D15/SourceAnalysis!D16/Production!AI84,0) -> 23.574664 | AJ44: =Payroll!AJ16*IF(Production!AJ84>0,AJ37*SourceAnalysis!D15/SourceAnalysis!D16/Production!AJ84,0) -> 23.558856 | AK44: =Payroll!AK16*IF(Production!AK84>0,AK37*SourceAnalysis!D15/SourceAnalysis!D16/Production!AK84,0) -> 23.591343 | AL44: =Payroll!AL16*IF(Production!AL84>0,AL37*SourceAnalysis!D15/SourceAnalysis!D16/Production!AL84,0) -> 23.558856 | AM44: =Payroll!AM16*IF(Production!AM84>0,AM37*SourceAnalysis!D15/SourceAnalysis!D16/Production!AM84,0) -> 23.591343
C45: Cash factory overhead | J45: =J37*J42/1000000 -> 32.910138 | K45: =K37*K42/1000000 -> 33.108941 | L45: =L37*L42/1000000 -> 33.973002 | M45: =M37*M42/1000000 -> 32.24488 | N45: =N37*N42/1000000 -> 33.973002 | O45: =O37*O42/1000000 -> 32.24488 | P45: =P37*P42/1000000 -> 37.691916 | Q45: =Q37*Q42/1000000 -> 38.987555 | ... AM45: =AM37*AM42/1000000 -> 35.590621
C46: Allocated manufacturing depreciation | J46: =Assets!J100*SourceAnalysis!D28*IF(Production!J84>0,J37*SourceAnalysis!D15/SourceAnalysis!D16/Production!J84,0) -> 7.7935017 | K46: =Assets!K100*SourceAnalysis!D28*IF(Production!K84>0,K37*SourceAnalysis!D15/SourceAnalysis!D16/Production!K84,0) -> 7.9163258 | L46: =Assets!L100*SourceAnalysis!D28*IF(Production!L84>0,L37*SourceAnalysis!D15/SourceAnalysis!D16/Production!L84,0) -> 7.9770183 | M46: =Assets!M100*SourceAnalysis!D28*IF(Production!M84>0,M37*SourceAnalysis!D15/SourceAnalysis!D16/Production!M84,0) -> 8.0443605 | N46: =Assets!N100*SourceAnalysis!D28*IF(Production!N84>0,N37*SourceAnalysis!D15/SourceAnalysis!D16/Production!N84,0) -> 8.1027117 | O46: =Assets!O100*SourceAnalysis!D28*IF(Production!O84>0,O37*SourceAnalysis!D15/SourceAnalysis!D16/Production!O84,0) -> 8.1701243 | P46: =Assets!P100*SourceAnalysis!D28*IF(Production!P84>0,P37*SourceAnalysis!D15/SourceAnalysis!D16/Production!P84,0) -> 8.2266232 | Q46: =Assets!Q100*SourceAnalysis!D28*IF(Production!Q84>0,Q37*SourceAnalysis!D15/SourceAnalysis!D16/Production!Q84,0) -> 8.2897856 | R46: =Assets!R100*SourceAnalysis!D28*IF(Production!R84>0,R37*SourceAnalysis!D15/SourceAnalysis!D16/Production!R84,0) -> 8.3708623 | S46: =Assets!S100*SourceAnalysis!D28*IF(Production!S84>0,S37*SourceAnalysis!D15/SourceAnalysis!D16/Production!S84,0) -> 8.4263723 | T46: =Assets!T100*SourceAnalysis!D28*IF(Production!T84>0,T37*SourceAnalysis!D15/SourceAnalysis!D16/Production!T84,0) -> 8.4971099 | U46: =Assets!U100*SourceAnalysis!D28*IF(Production!U84>0,U37*SourceAnalysis!D15/SourceAnalysis!D16/Production!U84,0) -> 8.5583504 | V46: =Assets!V100*SourceAnalysis!D28*IF(Production!V84>0,V37*SourceAnalysis!D15/SourceAnalysis!D16/Production!V84,0) -> 8.5166661 | W46: =Assets!W100*SourceAnalysis!D28*IF(Production!W84>0,W37*SourceAnalysis!D15/SourceAnalysis!D16/Production!W84,0) -> 8.6592271 | X46: =Assets!X100*SourceAnalysis!D28*IF(Production!X84>0,X37*SourceAnalysis!D15/SourceAnalysis!D16/Production!X84,0) -> 8.352308 | Y46: =Assets!Y100*SourceAnalysis!D28*IF(Production!Y84>0,Y37*SourceAnalysis!D15/SourceAnalysis!D16/Production!Y84,0) -> 8.4211935 | Z46: =Assets!Z100*SourceAnalysis!D28*IF(Production!Z84>0,Z37*SourceAnalysis!D15/SourceAnalysis!D16/Production!Z84,0) -> 8.4789238 | AA46: =Assets!AA100*SourceAnalysis!D28*IF(Production!AA84>0,AA37*SourceAnalysis!D15/SourceAnalysis!D16/Production!AA84,0) -> 8.5527634 | AB46: =Assets!AB100*SourceAnalysis!D28*IF(Production!AB84>0,AB37*SourceAnalysis!D15/SourceAnalysis!D16/Production!AB84,0) -> 8.6072026 | AC46: =Assets!AC100*SourceAnalysis!D28*IF(Production!AC84>0,AC37*SourceAnalysis!D15/SourceAnalysis!D16/Production!AC84,0) -> 8.6753113 | AD46: =Assets!AD100*SourceAnalysis!D28*IF(Production!AD84>0,AD37*SourceAnalysis!D15/SourceAnalysis!D16/Production!AD84,0) -> 8.7615219 | AE46: =Assets!AE100*SourceAnalysis!D28*IF(Production!AE84>0,AE37*SourceAnalysis!D15/SourceAnalysis!D16/Production!AE84,0) -> 8.8173947 | AF46: =Assets!AF100*SourceAnalysis!D28*IF(Production!AF84>0,AF37*SourceAnalysis!D15/SourceAnalysis!D16/Production!AF84,0) -> 8.8948451 | AG46: =Assets!AG100*SourceAnalysis!D28*IF(Production!AG84>0,AG37*SourceAnalysis!D15/SourceAnalysis!D16/Production!AG84,0) -> 8.955412 | AH46: =Assets!AH100*SourceAnalysis!D28*IF(Production!AH84>0,AH37*SourceAnalysis!D15/SourceAnalysis!D16/Production!AH84,0) -> 8.8951505 | AI46: =Assets!AI100*SourceAnalysis!D28*IF(Production!AI84>0,AI37*SourceAnalysis!D15/SourceAnalysis!D16/Production!AI84,0) -> 9.0537167 | AJ46: =Assets!AJ100*SourceAnalysis!D28*IF(Production!AJ84>0,AJ37*SourceAnalysis!D15/SourceAnalysis!D16/Production!AJ84,0) -> 9.1163066 | AK46: =Assets!AK100*SourceAnalysis!D28*IF(Production!AK84>0,AK37*SourceAnalysis!D15/SourceAnalysis!D16/Production!AK84,0) -> 9.197634 | AL46: =Assets!AL100*SourceAnalysis!D28*IF(Production!AL84>0,AL37*SourceAnalysis!D15/SourceAnalysis!D16/Production!AL84,0) -> 9.253629 | AM46: =Assets!AM100*SourceAnalysis!D28*IF(Production!AM84>0,AM37*SourceAnalysis!D15/SourceAnalysis!D16/Production!AM84,0) -> 9.3351457
C47: Production cost transferred into FG | J47: =SUM(J43:J46) -> 370.8709 | K47: =SUM(K43:K46) -> 373.22376 | L47: =SUM(L43:L46) -> 382.22698 | M47: =SUM(M43:M46) -> 364.4096 | N47: =SUM(N43:N46) -> 382.35268 | O47: =SUM(O43:O46) -> 364.53537 | P47: =SUM(P43:P46) -> 421.65871 | Q47: =SUM(Q43:Q46) -> 435.13231 | ... AM47: =SUM(AM43:AM46) -> 401.51991
C48: Opening FG carrying value | J48: =H1Data!D63*(SourceAnalysis!D17*SourceAnalysis!D15/SourceAnalysis!D16)/(SourceAnalysis!D12*SourceAnalysis!D10/SourceAnalysis!D11+SourceAnalysis!D17*SourceAnalysis!D15/SourceAnalysis!D16+SourceAnalysis!D22*SourceAnalysis!D20/SourceAnalysis!D21) -> 425.30921 | K48: =Production!J52 -> 349.62179 | L48: =Production!K52 -> 317.41882 | M48: =Production!L52 -> 312.89235 | N48: =Production!M52 -> 297.41954 | O48: =Production!N52 -> 304.00457 | P48: =Production!O52 -> 293.57192 | Q48: =Production!P52 -> 314.07493 | R48: =Production!Q52 -> 347.87705 | ... AM48: =Production!AL52 -> 332.42017
C49: WIP value released into FG | J49: =Inventory!J18*IF(Production!J84>0,J37*SourceAnalysis!D15/SourceAnalysis!D16/Production!J84,0) -> 0 | K49: =Inventory!K18*IF(Production!K84>0,K37*SourceAnalysis!D15/SourceAnalysis!D16/Production!K84,0) -> 0 | L49: =Inventory!L18*IF(Production!L84>0,L37*SourceAnalysis!D15/SourceAnalysis!D16/Production!L84,0) -> 0 | M49: =Inventory!M18*IF(Production!M84>0,M37*SourceAnalysis!D15/SourceAnalysis!D16/Production!M84,0) -> 0 | N49: =Inventory!N18*IF(Production!N84>0,N37*SourceAnalysis!D15/SourceAnalysis!D16/Production!N84,0) -> 0 | O49: =Inventory!O18*IF(Production!O84>0,O37*SourceAnalysis!D15/SourceAnalysis!D16/Production!O84,0) -> 0 | P49: =Inventory!P18*IF(Production!P84>0,P37*SourceAnalysis!D15/SourceAnalysis!D16/Production!P84,0) -> 0 | Q49: =Inventory!Q18*IF(Production!Q84>0,Q37*SourceAnalysis!D15/SourceAnalysis!D16/Production!Q84,0) -> 0 | R49: =Inventory!R18*IF(Production!R84>0,R37*SourceAnalysis!D15/SourceAnalysis!D16/Production!R84,0) -> 0 | S49: =Inventory!S18*IF(Production!S84>0,S37*SourceAnalysis!D15/SourceAnalysis!D16/Production!S84,0) -> 0 | T49: =Inventory!T18*IF(Production!T84>0,T37*SourceAnalysis!D15/SourceAnalysis!D16/Production!T84,0) -> 0 | U49: =Inventory!U18*IF(Production!U84>0,U37*SourceAnalysis!D15/SourceAnalysis!D16/Production!U84,0) -> 0 | V49: =Inventory!V18*IF(Production!V84>0,V37*SourceAnalysis!D15/SourceAnalysis!D16/Production!V84,0) -> 0 | W49: =Inventory!W18*IF(Production!W84>0,W37*SourceAnalysis!D15/SourceAnalysis!D16/Production!W84,0) -> 0 | X49: =Inventory!X18*IF(Production!X84>0,X37*SourceAnalysis!D15/SourceAnalysis!D16/Production!X84,0) -> 0 | Y49: =Inventory!Y18*IF(Production!Y84>0,Y37*SourceAnalysis!D15/SourceAnalysis!D16/Production!Y84,0) -> 0 | Z49: =Inventory!Z18*IF(Production!Z84>0,Z37*SourceAnalysis!D15/SourceAnalysis!D16/Production!Z84,0) -> 0 | AA49: =Inventory!AA18*IF(Production!AA84>0,AA37*SourceAnalysis!D15/SourceAnalysis!D16/Production!AA84,0) -> 0 | AB49: =Inventory!AB18*IF(Production!AB84>0,AB37*SourceAnalysis!D15/SourceAnalysis!D16/Production!AB84,0) -> 0 | AC49: =Inventory!AC18*IF(Production!AC84>0,AC37*SourceAnalysis!D15/SourceAnalysis!D16/Production!AC84,0) -> 0 | AD49: =Inventory!AD18*IF(Production!AD84>0,AD37*SourceAnalysis!D15/SourceAnalysis!D16/Production!AD84,0) -> 0 | AE49: =Inventory!AE18*IF(Production!AE84>0,AE37*SourceAnalysis!D15/SourceAnalysis!D16/Production!AE84,0) -> 0 | AF49: =Inventory!AF18*IF(Production!AF84>0,AF37*SourceAnalysis!D15/SourceAnalysis!D16/Production!AF84,0) -> 0 | AG49: =Inventory!AG18*IF(Production!AG84>0,AG37*SourceAnalysis!D15/SourceAnalysis!D16/Production!AG84,0) -> 0 | AH49: =Inventory!AH18*IF(Production!AH84>0,AH37*SourceAnalysis!D15/SourceAnalysis!D16/Production!AH84,0) -> 0 | AI49: =Inventory!AI18*IF(Production!AI84>0,AI37*SourceAnalysis!D15/SourceAnalysis!D16/Production!AI84,0) -> 0 | AJ49: =Inventory!AJ18*IF(Production!AJ84>0,AJ37*SourceAnalysis!D15/SourceAnalysis!D16/Production!AJ84,0) -> 0 | AK49: =Inventory!AK18*IF(Production!AK84>0,AK37*SourceAnalysis!D15/SourceAnalysis!D16/Production!AK84,0) -> 0 | AL49: =Inventory!AL18*IF(Production!AL84>0,AL37*SourceAnalysis!D15/SourceAnalysis!D16/Production!AL84,0) -> 0 | AM49: =Inventory!AM18*IF(Production!AM84>0,AM37*SourceAnalysis!D15/SourceAnalysis!D16/Production!AM84,0) -> 0
C50: Weighted average FG cost/unit RMB | J50: =IF(J38>0,(J48+J47+J49)*1000000/J38,0) -> 5.0403331 | K50: =IF(K38>0,(K48+K47+K49)*1000000/K38,0) -> 4.5760781 | L50: =IF(L38>0,(L48+L47+L49)*1000000/L38,0) -> 4.3653116 | M50: =IF(M38>0,(M48+M47+M49)*1000000/M38,0) -> 4.2877577 | N50: =IF(N38>0,(N48+N47+N49)*1000000/N38,0) -> 4.241314 | O50: =IF(O38>0,(O48+O47+O49)*1000000/O38,0) -> 4.2322885 | P50: =IF(P38>0,(P48+P47+P49)*1000000/P38,0) -> 4.2510541 | Q50: =IF(Q38>0,(Q48+Q47+Q49)*1000000/Q38,0) -> 4.252903 | ... AM50: =IF(AM38>0,(AM48+AM47+AM49)*1000000/AM38,0) -> 4.3795962
C51: COGS released on sales | J51: =J36*J50/1000000 -> 446.55833 | K51: =K36*K50/1000000 -> 405.42673 | L51: =L36*L50/1000000 -> 386.75346 | M51: =M36*M50/1000000 -> 379.88242 | N51: =N36*N50/1000000 -> 375.76764 | O51: =O36*O50/1000000 -> 374.96801 | P51: =P36*P50/1000000 -> 401.15571 | Q51: =Q36*Q50/1000000 -> 401.33018 | ... AM51: =AM36*AM50/1000000 -> 411.64939
C52: Closing FG carrying value | J52: =J48+J47+J49-J51 -> 349.62179 | K52: =K48+K47+K49-K51 -> 317.41882 | L52: =L48+L47+L49-L51 -> 312.89235 | M52: =M48+M47+M49-M51 -> 297.41954 | N52: =N48+N47+N49-N51 -> 304.00457 | O52: =O48+O47+O49-O51 -> 293.57192 | P52: =P48+P47+P49-P51 -> 314.07493 | Q52: =Q48+Q47+Q49-Q51 -> 347.87705 | ... AM52: =AM48+AM47+AM49-AM51 -> 322.2907
C53: FG carrying-value roll-forward | J53: =J48+J47+J49-J51-J52 -> 0 | K53: =K48+K47+K49-K51-K52 -> 0 | L53: =L48+L47+L49-L51-L52 -> 0 | M53: =M48+M47+M49-M51-M52 -> 0 | N53: =N48+N47+N49-N51-N52 -> 0 | O53: =O48+O47+O49-O51-O52 -> 0 | P53: =P48+P47+P49-P51-P52 -> 0 | Q53: =Q48+Q47+Q49-Q51-Q52 -> 0 | ... AM53: =AM48+AM47+AM49-AM51-AM52 -> 0
C57: 新能源产品
C58: Opening FG physical units | J58: =SourceAnalysis!D22 -> 160000 | K58: =Production!J63 -> 177281.15 | L58: =Production!K63 -> 177281.15 | M58: =Production!L63 -> 183190.52 | N58: =Production!M63 -> 177281.15 | O58: =Production!N63 -> 183190.52 | P58: =Production!O63 -> 177281.15 | Q58: =Production!P63 -> 188825.2 | R58: =Production!Q63 -> 209056.47 | ... AM58: =Production!AL63 -> 242269.46
C59: Target ending FG units | J59: =Revenue!J28/DAY(J$7)*MAX(0,Inputs!J27) -> 177281.15 | K59: =Revenue!K28/DAY(K$7)*MAX(0,Inputs!K27) -> 177281.15 | L59: =Revenue!L28/DAY(L$7)*MAX(0,Inputs!L27) -> 183190.52 | M59: =Revenue!M28/DAY(M$7)*MAX(0,Inputs!M27) -> 177281.15 | N59: =Revenue!N28/DAY(N$7)*MAX(0,Inputs!N27) -> 183190.52 | O59: =Revenue!O28/DAY(O$7)*MAX(0,Inputs!O27) -> 177281.15 | P59: =Revenue!P28/DAY(P$7)*MAX(0,Inputs!P27) -> 188825.2 | Q59: =Revenue!Q28/DAY(Q$7)*MAX(0,Inputs!Q27) -> 209056.47 | ... AM59: =Revenue!AM28/DAY(AM$7)*MAX(0,Inputs!AM27) -> 234454.32
C60: Sales units requested | J60: =Revenue!J28 -> 122044.41 | K60: =Revenue!K28 -> 122044.41 | L60: =Revenue!L28 -> 122044.41 | M60: =Revenue!M28 -> 122044.41 | N60: =Revenue!N28 -> 122044.41 | O60: =Revenue!O28 -> 122044.41 | P60: =Revenue!P28 -> 129991.6 | Q60: =Revenue!Q28 -> 129991.6 | ... AM60: =Revenue!AM28 -> 161403.73
C61: Production units required | J61: =MAX(0,J60+J59-J58) -> 139325.56 | K61: =MAX(0,K60+K59-K58) -> 122044.41 | L61: =MAX(0,L60+L59-L58) -> 127953.78 | M61: =MAX(0,M60+M59-M58) -> 116135.04 | N61: =MAX(0,N60+N59-N58) -> 127953.78 | O61: =MAX(0,O60+O59-O58) -> 116135.04 | P61: =MAX(0,P60+P59-P58) -> 141535.65 | Q61: =MAX(0,Q60+Q59-Q58) -> 150222.87 | ... AM61: =MAX(0,AM60+AM59-AM58) -> 153588.59
C62: Available FG units | J62: =J58+J61 -> 299325.56 | K62: =K58+K61 -> 299325.56 | L62: =L58+L61 -> 305234.93 | M62: =M58+M61 -> 299325.56 | N62: =N58+N61 -> 305234.93 | O62: =O58+O61 -> 299325.56 | P62: =P58+P61 -> 318816.8 | Q62: =Q58+Q61 -> 339048.07 | ... AM62: =AM58+AM61 -> 395858.05
C63: Closing FG units | J63: =J62-J60 -> 177281.15 | K63: =K62-K60 -> 177281.15 | L63: =L62-L60 -> 183190.52 | M63: =M62-M60 -> 177281.15 | N63: =N62-N60 -> 183190.52 | O63: =O62-O60 -> 177281.15 | P63: =P62-P60 -> 188825.2 | Q63: =Q62-Q60 -> 209056.47 | ... AM63: =AM62-AM60 -> 234454.32
C64: Physical roll-forward | J64: =J58+J61-J60-J63 -> 0 | K64: =K58+K61-K60-K63 -> 0 | L64: =L58+L61-L60-L63 -> 0 | M64: =M58+M61-M60-M63 -> 0 | N64: =N58+N61-N60-N63 -> 0 | O64: =O58+O61-O60-O63 -> 0 | P64: =P58+P61-P60-P63 -> 0 | Q64: =Q58+Q61-Q60-Q63 -> 0 | ... AM64: =AM58+AM61-AM60-AM63 -> 0
C65: Material cost / production unit RMB | J65: =(SourceAnalysis!D20*SourceAnalysis!D25*1000000/SourceAnalysis!D21)*(1+Inputs!J21) -> 377.27925 | K65: =(Production!J65)*(1+Inputs!K21) -> 377.27925 | L65: =(Production!K65)*(1+Inputs!L21) -> 377.27925 | M65: =(Production!L65)*(1+Inputs!M21) -> 377.27925 | N65: =(Production!M65)*(1+Inputs!N21) -> 377.27925 | O65: =(Production!N65)*(1+Inputs!O21) -> 377.27925 | P65: =(Production!O65)*(1+Inputs!P21) -> 384.82483 | Q65: =(Production!P65)*(1+Inputs!Q21) -> 384.82483 | R65: =(Production!Q65)*(1+Inputs!R21) -> 384.82483 | ... AM65: =(Production!AL65)*(1+Inputs!AM21) -> 392.52133
C66: Cash overhead / production unit RMB | J66: =(SourceAnalysis!D29*SourceAnalysis!D20/(SourceDetail!E80/1000000)*1000000/SourceAnalysis!D21)*(1+Inputs!J22) -> 40.322792 | K66: =(Production!J66)*(1+Inputs!K22) -> 40.322792 | L66: =(Production!K66)*(1+Inputs!L22) -> 40.322792 | M66: =(Production!L66)*(1+Inputs!M22) -> 40.322792 | N66: =(Production!M66)*(1+Inputs!N22) -> 40.322792 | O66: =(Production!N66)*(1+Inputs!O22) -> 40.322792 | P66: =(Production!O66)*(1+Inputs!P22) -> 41.129247 | Q66: =(Production!P66)*(1+Inputs!Q22) -> 41.129247 | R66: =(Production!Q66)*(1+Inputs!R22) -> 41.129247 | ... AM66: =(Production!AL66)*(1+Inputs!AM22) -> 41.951832
C67: Material consumption cost | J67: =J61*J65/1000000 -> 52.564642 | K67: =K61*K65/1000000 -> 46.044823 | L67: =L61*L65/1000000 -> 48.274307 | M67: =M61*M65/1000000 -> 43.81534 | N67: =N61*N65/1000000 -> 48.274307 | O67: =O61*O65/1000000 -> 43.81534 | P67: =P61*P65/1000000 -> 54.466432 | Q67: =Q61*Q65/1000000 -> 57.809491 | ... AM67: =AM61*AM65/1000000 -> 60.286797
C68: Allocated production payroll | J68: =Payroll!J16*IF(Production!J84>0,J61*SourceAnalysis!D20/SourceAnalysis!D21/Production!J84,0) -> 3.7972662 | K68: =Payroll!K16*IF(Production!K84>0,K61*SourceAnalysis!D20/SourceAnalysis!D21/Production!K84,0) -> 3.3317398 | L68: =Payroll!L16*IF(Production!L84>0,L61*SourceAnalysis!D20/SourceAnalysis!D21/Production!L84,0) -> 3.403294 | M68: =Payroll!M16*IF(Production!M84>0,M61*SourceAnalysis!D20/SourceAnalysis!D21/Production!M84,0) -> 3.2563085 | N68: =Payroll!N16*IF(Production!N84>0,N61*SourceAnalysis!D20/SourceAnalysis!D21/Production!N84,0) -> 3.403294 | O68: =Payroll!O16*IF(Production!O84>0,O61*SourceAnalysis!D20/SourceAnalysis!D21/Production!O84,0) -> 3.2563085 | P68: =Payroll!P16*IF(Production!P84>0,P61*SourceAnalysis!D20/SourceAnalysis!D21/Production!P84,0) -> 3.564029 | Q68: =Payroll!Q16*IF(Production!Q84>0,Q61*SourceAnalysis!D20/SourceAnalysis!D21/Production!Q84,0) -> 3.655833 | R68: =Payroll!R16*IF(Production!R84>0,R61*SourceAnalysis!D20/SourceAnalysis!D21/Production!R84,0) -> 3.1660236 | S68: =Payroll!S16*IF(Production!S84>0,S61*SourceAnalysis!D20/SourceAnalysis!D21/Production!S84,0) -> 3.5053928 | T68: =Payroll!T16*IF(Production!T84>0,T61*SourceAnalysis!D20/SourceAnalysis!D21/Production!T84,0) -> 3.3539977 | U68: =Payroll!U16*IF(Production!U84>0,U61*SourceAnalysis!D20/SourceAnalysis!D21/Production!U84,0) -> 3.5053928 | V68: =Payroll!V16*IF(Production!V84>0,V61*SourceAnalysis!D20/SourceAnalysis!D21/Production!V84,0) -> 4.2465211 | W68: =Payroll!W16*IF(Production!W84>0,W61*SourceAnalysis!D20/SourceAnalysis!D21/Production!W84,0) -> 3.8167494 | X68: =Payroll!X16*IF(Production!X84>0,X61*SourceAnalysis!D20/SourceAnalysis!D21/Production!X84,0) -> 3.897979 | Y68: =Payroll!Y16*IF(Production!Y84>0,Y61*SourceAnalysis!D20/SourceAnalysis!D21/Production!Y84,0) -> 3.7310851 | Z68: =Payroll!Z16*IF(Production!Z84>0,Z61*SourceAnalysis!D20/SourceAnalysis!D21/Production!Z84,0) -> 3.897979 | AA68: =Payroll!AA16*IF(Production!AA84>0,AA61*SourceAnalysis!D20/SourceAnalysis!D21/Production!AA84,0) -> 3.7310851 | AB68: =Payroll!AB16*IF(Production!AB84>0,AB61*SourceAnalysis!D20/SourceAnalysis!D21/Production!AB84,0) -> 4.0814604 | AC68: =Payroll!AC16*IF(Production!AC84>0,AC61*SourceAnalysis!D20/SourceAnalysis!D21/Production!AC84,0) -> 4.0996942 | AD68: =Payroll!AD16*IF(Production!AD84>0,AD61*SourceAnalysis!D20/SourceAnalysis!D21/Production!AD84,0) -> 3.7432114 | AE68: =Payroll!AE16*IF(Production!AE84>0,AE61*SourceAnalysis!D20/SourceAnalysis!D21/Production!AE84,0) -> 4.0149184 | AF68: =Payroll!AF16*IF(Production!AF84>0,AF61*SourceAnalysis!D20/SourceAnalysis!D21/Production!AF84,0) -> 3.8430177 | AG68: =Payroll!AG16*IF(Production!AG84>0,AG61*SourceAnalysis!D20/SourceAnalysis!D21/Production!AG84,0) -> 4.0149184 | AH68: =Payroll!AH16*IF(Production!AH84>0,AH61*SourceAnalysis!D20/SourceAnalysis!D21/Production!AH84,0) -> 4.8547124 | AI68: =Payroll!AI16*IF(Production!AI84>0,AI61*SourceAnalysis!D20/SourceAnalysis!D21/Production!AI84,0) -> 4.3680736 | AJ68: =Payroll!AJ16*IF(Production!AJ84>0,AJ61*SourceAnalysis!D20/SourceAnalysis!D21/Production!AJ84,0) -> 4.4601064 | AK68: =Payroll!AK16*IF(Production!AK84>0,AK61*SourceAnalysis!D20/SourceAnalysis!D21/Production!AK84,0) -> 4.2709747 | AL68: =Payroll!AL16*IF(Production!AL84>0,AL61*SourceAnalysis!D20/SourceAnalysis!D21/Production!AL84,0) -> 4.4601064 | AM68: =Payroll!AM16*IF(Production!AM84>0,AM61*SourceAnalysis!D20/SourceAnalysis!D21/Production!AM84,0) -> 4.2709747
C69: Cash factory overhead | J69: =J61*J66/1000000 -> 5.6179955 | K69: =K61*K66/1000000 -> 4.9211713 | L69: =L61*L66/1000000 -> 5.1594537 | M69: =M61*M66/1000000 -> 4.682889 | N69: =N61*N66/1000000 -> 5.1594537 | O69: =O61*O66/1000000 -> 4.682889 | P69: =P61*P66/1000000 -> 5.8212547 | Q69: =Q61*Q66/1000000 -> 6.1785536 | ... AM69: =AM61*AM66/1000000 -> 6.4433227
C70: Allocated manufacturing depreciation | J70: =Assets!J100*SourceAnalysis!D28*IF(Production!J84>0,J61*SourceAnalysis!D20/SourceAnalysis!D21/Production!J84,0) -> 1.3304064 | K70: =Assets!K100*SourceAnalysis!D28*IF(Production!K84>0,K61*SourceAnalysis!D20/SourceAnalysis!D21/Production!K84,0) -> 1.1766488 | L70: =Assets!L100*SourceAnalysis!D28*IF(Production!L84>0,L61*SourceAnalysis!D20/SourceAnalysis!D21/Production!L84,0) -> 1.2114636 | M70: =Assets!M100*SourceAnalysis!D28*IF(Production!M84>0,M61*SourceAnalysis!D20/SourceAnalysis!D21/Production!M84,0) -> 1.1682738 | N70: =Assets!N100*SourceAnalysis!D28*IF(Production!N84>0,N61*SourceAnalysis!D20/SourceAnalysis!D21/Production!N84,0) -> 1.2305526 | O70: =Assets!O100*SourceAnalysis!D28*IF(Production!O84>0,O61*SourceAnalysis!D20/SourceAnalysis!D21/Production!O84,0) -> 1.1865383 | P70: =Assets!P100*SourceAnalysis!D28*IF(Production!P84>0,P61*SourceAnalysis!D20/SourceAnalysis!D21/Production!P84,0) -> 1.2705448 | Q70: =Assets!Q100*SourceAnalysis!D28*IF(Production!Q84>0,Q61*SourceAnalysis!D20/SourceAnalysis!D21/Production!Q84,0) -> 1.313724 | R70: =Assets!R100*SourceAnalysis!D28*IF(Production!R84>0,R61*SourceAnalysis!D20/SourceAnalysis!D21/Production!R84,0) -> 1.1467624 | S70: =Assets!S100*SourceAnalysis!D28*IF(Production!S84>0,S61*SourceAnalysis!D20/SourceAnalysis!D21/Production!S84,0) -> 1.2797067 | T70: =Assets!T100*SourceAnalysis!D28*IF(Production!T84>0,T61*SourceAnalysis!D20/SourceAnalysis!D21/Production!T84,0) -> 1.2340261 | U70: =Assets!U100*SourceAnalysis!D28*IF(Production!U84>0,U61*SourceAnalysis!D20/SourceAnalysis!D21/Production!U84,0) -> 1.2997501 | V70: =Assets!V100*SourceAnalysis!D28*IF(Production!V84>0,V61*SourceAnalysis!D20/SourceAnalysis!D21/Production!V84,0) -> 1.5866905 | W70: =Assets!W100*SourceAnalysis!D28*IF(Production!W84>0,W61*SourceAnalysis!D20/SourceAnalysis!D21/Production!W84,0) -> 1.4370204 | X70: =Assets!X100*SourceAnalysis!D28*IF(Production!X84>0,X61*SourceAnalysis!D20/SourceAnalysis!D21/Production!X84,0) -> 1.4162402 | Y70: =Assets!Y100*SourceAnalysis!D28*IF(Production!Y84>0,Y61*SourceAnalysis!D20/SourceAnalysis!D21/Production!Y84,0) -> 1.3654863 | Z70: =Assets!Z100*SourceAnalysis!D28*IF(Production!Z84>0,Z61*SourceAnalysis!D20/SourceAnalysis!D21/Production!Z84,0) -> 1.4377095 | AA70: =Assets!AA100*SourceAnalysis!D28*IF(Production!AA84>0,AA61*SourceAnalysis!D20/SourceAnalysis!D21/Production!AA84,0) -> 1.3868202 | AB70: =Assets!AB100*SourceAnalysis!D28*IF(Production!AB84>0,AB61*SourceAnalysis!D20/SourceAnalysis!D21/Production!AB84,0) -> 1.4841952 | AC70: =Assets!AC100*SourceAnalysis!D28*IF(Production!AC84>0,AC61*SourceAnalysis!D20/SourceAnalysis!D21/Production!AC84,0) -> 1.5027742 | AD70: =Assets!AD100*SourceAnalysis!D28*IF(Production!AD84>0,AD61*SourceAnalysis!D20/SourceAnalysis!D21/Production!AD84,0) -> 1.3830121 | AE70: =Assets!AE100*SourceAnalysis!D28*IF(Production!AE84>0,AE61*SourceAnalysis!D20/SourceAnalysis!D21/Production!AE84,0) -> 1.4951016 | AF70: =Assets!AF100*SourceAnalysis!D28*IF(Production!AF84>0,AF61*SourceAnalysis!D20/SourceAnalysis!D21/Production!AF84,0) -> 1.4422884 | AG70: =Assets!AG100*SourceAnalysis!D28*IF(Production!AG84>0,AG61*SourceAnalysis!D20/SourceAnalysis!D21/Production!AG84,0) -> 1.5185041 | AH70: =Assets!AH100*SourceAnalysis!D28*IF(Production!AH84>0,AH61*SourceAnalysis!D20/SourceAnalysis!D21/Production!AH84,0) -> 1.8502761 | AI70: =Assets!AI100*SourceAnalysis!D28*IF(Production!AI84>0,AI61*SourceAnalysis!D20/SourceAnalysis!D21/Production!AI84,0) -> 1.677534 | AJ70: =Assets!AJ100*SourceAnalysis!D28*IF(Production!AJ84>0,AJ61*SourceAnalysis!D20/SourceAnalysis!D21/Production!AJ84,0) -> 1.7258774 | AK70: =Assets!AK100*SourceAnalysis!D28*IF(Production!AK84>0,AK61*SourceAnalysis!D20/SourceAnalysis!D21/Production!AK84,0) -> 1.6651388 | AL70: =Assets!AL100*SourceAnalysis!D28*IF(Production!AL84>0,AL61*SourceAnalysis!D20/SourceAnalysis!D21/Production!AL84,0) -> 1.751875 | AM70: =Assets!AM100*SourceAnalysis!D28*IF(Production!AM84>0,AM61*SourceAnalysis!D20/SourceAnalysis!D21/Production!AM84,0) -> 1.6900339
C71: Production cost transferred into FG | J71: =SUM(J67:J70) -> 63.31031 | K71: =SUM(K67:K70) -> 55.474383 | L71: =SUM(L67:L70) -> 58.048518 | M71: =SUM(M67:M70) -> 52.922811 | N71: =SUM(N67:N70) -> 58.067607 | O71: =SUM(O67:O70) -> 52.941076 | P71: =SUM(P67:P70) -> 65.122261 | Q71: =SUM(Q67:Q70) -> 68.957601 | ... AM71: =SUM(AM67:AM70) -> 72.691128
C72: Opening FG carrying value | J72: =H1Data!D63*(SourceAnalysis!D22*SourceAnalysis!D20/SourceAnalysis!D21)/(SourceAnalysis!D12*SourceAnalysis!D10/SourceAnalysis!D11+SourceAnalysis!D17*SourceAnalysis!D15/SourceAnalysis!D16+SourceAnalysis!D22*SourceAnalysis!D20/SourceAnalysis!D21) -> 105.04895 | K72: =Production!J76 -> 99.713917 | L72: =Production!K76 -> 91.913167 | M72: =Production!L76 -> 90.001361 | N72: =Production!M76 -> 84.649508 | O72: =Production!N76 -> 85.653442 | P72: =Production!O76 -> 82.08519 | Q72: =Production!P76 -> 87.18636 | R72: =Production!Q76 -> 96.278104 | ... AM72: =Production!AL76 -> 114.2799
C73: WIP value released into FG | J73: =Inventory!J18*IF(Production!J84>0,J61*SourceAnalysis!D20/SourceAnalysis!D21/Production!J84,0) -> 0 | K73: =Inventory!K18*IF(Production!K84>0,K61*SourceAnalysis!D20/SourceAnalysis!D21/Production!K84,0) -> 0 | L73: =Inventory!L18*IF(Production!L84>0,L61*SourceAnalysis!D20/SourceAnalysis!D21/Production!L84,0) -> 0 | M73: =Inventory!M18*IF(Production!M84>0,M61*SourceAnalysis!D20/SourceAnalysis!D21/Production!M84,0) -> 0 | N73: =Inventory!N18*IF(Production!N84>0,N61*SourceAnalysis!D20/SourceAnalysis!D21/Production!N84,0) -> 0 | O73: =Inventory!O18*IF(Production!O84>0,O61*SourceAnalysis!D20/SourceAnalysis!D21/Production!O84,0) -> 0 | P73: =Inventory!P18*IF(Production!P84>0,P61*SourceAnalysis!D20/SourceAnalysis!D21/Production!P84,0) -> 0 | Q73: =Inventory!Q18*IF(Production!Q84>0,Q61*SourceAnalysis!D20/SourceAnalysis!D21/Production!Q84,0) -> 0 | R73: =Inventory!R18*IF(Production!R84>0,R61*SourceAnalysis!D20/SourceAnalysis!D21/Production!R84,0) -> 0 | S73: =Inventory!S18*IF(Production!S84>0,S61*SourceAnalysis!D20/SourceAnalysis!D21/Production!S84,0) -> 0 | T73: =Inventory!T18*IF(Production!T84>0,T61*SourceAnalysis!D20/SourceAnalysis!D21/Production!T84,0) -> 0 | U73: =Inventory!U18*IF(Production!U84>0,U61*SourceAnalysis!D20/SourceAnalysis!D21/Production!U84,0) -> 0 | V73: =Inventory!V18*IF(Production!V84>0,V61*SourceAnalysis!D20/SourceAnalysis!D21/Production!V84,0) -> 0 | W73: =Inventory!W18*IF(Production!W84>0,W61*SourceAnalysis!D20/SourceAnalysis!D21/Production!W84,0) -> 0 | X73: =Inventory!X18*IF(Production!X84>0,X61*SourceAnalysis!D20/SourceAnalysis!D21/Production!X84,0) -> 0 | Y73: =Inventory!Y18*IF(Production!Y84>0,Y61*SourceAnalysis!D20/SourceAnalysis!D21/Production!Y84,0) -> 0 | Z73: =Inventory!Z18*IF(Production!Z84>0,Z61*SourceAnalysis!D20/SourceAnalysis!D21/Production!Z84,0) -> 0 | AA73: =Inventory!AA18*IF(Production!AA84>0,AA61*SourceAnalysis!D20/SourceAnalysis!D21/Production!AA84,0) -> 0 | AB73: =Inventory!AB18*IF(Production!AB84>0,AB61*SourceAnalysis!D20/SourceAnalysis!D21/Production!AB84,0) -> 0 | AC73: =Inventory!AC18*IF(Production!AC84>0,AC61*SourceAnalysis!D20/SourceAnalysis!D21/Production!AC84,0) -> 0 | AD73: =Inventory!AD18*IF(Production!AD84>0,AD61*SourceAnalysis!D20/SourceAnalysis!D21/Production!AD84,0) -> 0 | AE73: =Inventory!AE18*IF(Production!AE84>0,AE61*SourceAnalysis!D20/SourceAnalysis!D21/Production!AE84,0) -> 0 | AF73: =Inventory!AF18*IF(Production!AF84>0,AF61*SourceAnalysis!D20/SourceAnalysis!D21/Production!AF84,0) -> 0 | AG73: =Inventory!AG18*IF(Production!AG84>0,AG61*SourceAnalysis!D20/SourceAnalysis!D21/Production!AG84,0) -> 0 | AH73: =Inventory!AH18*IF(Production!AH84>0,AH61*SourceAnalysis!D20/SourceAnalysis!D21/Production!AH84,0) -> 0 | AI73: =Inventory!AI18*IF(Production!AI84>0,AI61*SourceAnalysis!D20/SourceAnalysis!D21/Production!AI84,0) -> 0 | AJ73: =Inventory!AJ18*IF(Production!AJ84>0,AJ61*SourceAnalysis!D20/SourceAnalysis!D21/Production!AJ84,0) -> 0 | AK73: =Inventory!AK18*IF(Production!AK84>0,AK61*SourceAnalysis!D20/SourceAnalysis!D21/Production!AK84,0) -> 0 | AL73: =Inventory!AL18*IF(Production!AL84>0,AL61*SourceAnalysis!D20/SourceAnalysis!D21/Production!AL84,0) -> 0 | AM73: =Inventory!AM18*IF(Production!AM84>0,AM61*SourceAnalysis!D20/SourceAnalysis!D21/Production!AM84,0) -> 0
C74: Weighted average FG cost/unit RMB | J74: =IF(J62>0,(J72+J71+J73)*1000000/J62,0) -> 562.46204 | K74: =IF(K62>0,(K72+K71+K73)*1000000/K62,0) -> 518.4599 | L74: =IF(L62>0,(L72+L71+L73)*1000000/L62,0) -> 491.29922 | M74: =IF(M62>0,(M72+M71+M73)*1000000/M62,0) -> 477.48736 | N74: =IF(N62>0,(N72+N71+N73)*1000000/N62,0) -> 467.56482 | O74: =IF(O62>0,(O72+O71+O73)*1000000/O62,0) -> 463.02267 | P74: =IF(P62>0,(P72+P71+P73)*1000000/P62,0) -> 461.73054 | Q74: =IF(Q62>0,(Q72+Q71+Q73)*1000000/Q62,0) -> 460.53635 | ... AM74: =IF(AM62>0,(AM72+AM71+AM73)*1000000/AM62,0) -> 472.31838
C75: COGS released on sales | J75: =J60*J74/1000000 -> 68.645348 | K75: =K60*K74/1000000 -> 63.275133 | L75: =L60*L74/1000000 -> 59.960324 | M75: =M60*M74/1000000 -> 58.274664 | N75: =N60*N74/1000000 -> 57.063673 | O75: =O60*O74/1000000 -> 56.509328 | P75: =P60*P74/1000000 -> 60.021091 | Q75: =Q60*Q74/1000000 -> 59.865857 | ... AM75: =AM60*AM74/1000000 -> 76.233949
C76: Closing FG carrying value | J76: =J72+J71+J73-J75 -> 99.713917 | K76: =K72+K71+K73-K75 -> 91.913167 | L76: =L72+L71+L73-L75 -> 90.001361 | M76: =M72+M71+M73-M75 -> 84.649508 | N76: =N72+N71+N73-N75 -> 85.653442 | O76: =O72+O71+O73-O75 -> 82.08519 | P76: =P72+P71+P73-P75 -> 87.18636 | Q76: =Q72+Q71+Q73-Q75 -> 96.278104 | ... AM76: =AM72+AM71+AM73-AM75 -> 110.73708
C77: FG carrying-value roll-forward | J77: =J72+J71+J73-J75-J76 -> 0 | K77: =K72+K71+K73-K75-K76 -> 0 | L77: =L72+L71+L73-L75-L76 -> 0 | M77: =M72+M71+M73-M75-M76 -> 0 | N77: =N72+N71+N73-N75-N76 -> 0 | O77: =O72+O71+O73-O75-O76 -> 0 | P77: =P72+P71+P73-P75-P76 -> 0 | Q77: =Q72+Q71+Q73-Q75-Q76 -> 0 | ... AM77: =AM72+AM71+AM73-AM75-AM76 -> 0
C84: Production allocation denominator | J84: =J13*SourceAnalysis!D10/SourceAnalysis!D11+J37*SourceAnalysis!D15/SourceAnalysis!D16+J61*SourceAnalysis!D20/SourceAnalysis!D21 -> 770.11564 | K84: =K13*SourceAnalysis!D10/SourceAnalysis!D11+K37*SourceAnalysis!D15/SourceAnalysis!D16+K61*SourceAnalysis!D20/SourceAnalysis!D21 -> 768.85247 | L84: =L13*SourceAnalysis!D10/SourceAnalysis!D11+L37*SourceAnalysis!D15/SourceAnalysis!D16+L61*SourceAnalysis!D20/SourceAnalysis!D21 -> 789.13235 | M84: =M13*SourceAnalysis!D10/SourceAnalysis!D11+M37*SourceAnalysis!D15/SourceAnalysis!D16+M61*SourceAnalysis!D20/SourceAnalysis!D21 -> 748.57259 | N84: =N13*SourceAnalysis!D10/SourceAnalysis!D11+N37*SourceAnalysis!D15/SourceAnalysis!D16+N61*SourceAnalysis!D20/SourceAnalysis!D21 -> 789.13235 | O84: =O13*SourceAnalysis!D10/SourceAnalysis!D11+O37*SourceAnalysis!D15/SourceAnalysis!D16+O61*SourceAnalysis!D20/SourceAnalysis!D21 -> 748.57259 | P84: =P13*SourceAnalysis!D10/SourceAnalysis!D11+P37*SourceAnalysis!D15/SourceAnalysis!D16+P61*SourceAnalysis!D20/SourceAnalysis!D21 -> 858.53504 | Q84: =Q13*SourceAnalysis!D10/SourceAnalysis!D11+Q37*SourceAnalysis!D15/SourceAnalysis!D16+Q61*SourceAnalysis!D20/SourceAnalysis!D21 -> 888.34799 | R84: =R13*SourceAnalysis!D10/SourceAnalysis!D11+R37*SourceAnalysis!D15/SourceAnalysis!D16+R61*SourceAnalysis!D20/SourceAnalysis!D21 -> 749.48797 | S84: =S13*SourceAnalysis!D10/SourceAnalysis!D11+S37*SourceAnalysis!D15/SourceAnalysis!D16+S61*SourceAnalysis!D20/SourceAnalysis!D21 -> 840.51843 | T84: =T13*SourceAnalysis!D10/SourceAnalysis!D11+T37*SourceAnalysis!D15/SourceAnalysis!D16+T61*SourceAnalysis!D20/SourceAnalysis!D21 -> 797.31753 | U84: =U13*SourceAnalysis!D10/SourceAnalysis!D11+U37*SourceAnalysis!D15/SourceAnalysis!D16+U61*SourceAnalysis!D20/SourceAnalysis!D21 -> 840.51843 | V84: =V13*SourceAnalysis!D10/SourceAnalysis!D11+V37*SourceAnalysis!D15/SourceAnalysis!D16+V61*SourceAnalysis!D20/SourceAnalysis!D21 -> 759.08848 | W84: =W13*SourceAnalysis!D10/SourceAnalysis!D11+W37*SourceAnalysis!D15/SourceAnalysis!D16+W61*SourceAnalysis!D20/SourceAnalysis!D21 -> 794.97872 | X84: =X13*SourceAnalysis!D10/SourceAnalysis!D11+X37*SourceAnalysis!D15/SourceAnalysis!D16+X61*SourceAnalysis!D20/SourceAnalysis!D21 -> 816.10284 | Y84: =Y13*SourceAnalysis!D10/SourceAnalysis!D11+Y37*SourceAnalysis!D15/SourceAnalysis!D16+Y61*SourceAnalysis!D20/SourceAnalysis!D21 -> 773.8546 | Z84: =Z13*SourceAnalysis!D10/SourceAnalysis!D11+Z37*SourceAnalysis!D15/SourceAnalysis!D16+Z61*SourceAnalysis!D20/SourceAnalysis!D21 -> 816.10284 | AA84: =AA13*SourceAnalysis!D10/SourceAnalysis!D11+AA37*SourceAnalysis!D15/SourceAnalysis!D16+AA61*SourceAnalysis!D20/SourceAnalysis!D21 -> 773.8546 | AB84: =AB13*SourceAnalysis!D10/SourceAnalysis!D11+AB37*SourceAnalysis!D15/SourceAnalysis!D16+AB61*SourceAnalysis!D20/SourceAnalysis!D21 -> 888.0118 | AC84: =AC13*SourceAnalysis!D10/SourceAnalysis!D11+AC37*SourceAnalysis!D15/SourceAnalysis!D16+AC61*SourceAnalysis!D20/SourceAnalysis!D21 -> 893.29653 | AD84: =AD13*SourceAnalysis!D10/SourceAnalysis!D11+AD37*SourceAnalysis!D15/SourceAnalysis!D16+AD61*SourceAnalysis!D20/SourceAnalysis!D21 -> 800.19447 | AE84: =AE13*SourceAnalysis!D10/SourceAnalysis!D11+AE37*SourceAnalysis!D15/SourceAnalysis!D16+AE61*SourceAnalysis!D20/SourceAnalysis!D21 -> 869.24516 | AF84: =AF13*SourceAnalysis!D10/SourceAnalysis!D11+AF37*SourceAnalysis!D15/SourceAnalysis!D16+AF61*SourceAnalysis!D20/SourceAnalysis!D21 -> 824.24583 | AG84: =AG13*SourceAnalysis!D10/SourceAnalysis!D11+AG37*SourceAnalysis!D15/SourceAnalysis!D16+AG61*SourceAnalysis!D20/SourceAnalysis!D21 -> 869.24516 | AH84: =AH13*SourceAnalysis!D10/SourceAnalysis!D11+AH37*SourceAnalysis!D15/SourceAnalysis!D16+AH61*SourceAnalysis!D20/SourceAnalysis!D21 -> 786.49732 | AI84: =AI13*SourceAnalysis!D10/SourceAnalysis!D11+AI37*SourceAnalysis!D15/SourceAnalysis!D16+AI61*SourceAnalysis!D20/SourceAnalysis!D21 -> 822.79998 | AJ84: =AJ13*SourceAnalysis!D10/SourceAnalysis!D11+AJ37*SourceAnalysis!D15/SourceAnalysis!D16+AJ61*SourceAnalysis!D20/SourceAnalysis!D21 -> 844.83954 | AK84: =AK13*SourceAnalysis!D10/SourceAnalysis!D11+AK37*SourceAnalysis!D15/SourceAnalysis!D16+AK61*SourceAnalysis!D20/SourceAnalysis!D21 -> 800.76041 | AL84: =AL13*SourceAnalysis!D10/SourceAnalysis!D11+AL37*SourceAnalysis!D15/SourceAnalysis!D16+AL61*SourceAnalysis!D20/SourceAnalysis!D21 -> 844.83954 | AM84: =AM13*SourceAnalysis!D10/SourceAnalysis!D11+AM37*SourceAnalysis!D15/SourceAnalysis!D16+AM61*SourceAnalysis!D20/SourceAnalysis!D21 -> 800.76041
C85: Material consumed | J85: =J19+J43+J67 -> 650.78944 | K85: =K19+K43+K67 -> 649.722 | L85: =L19+L43+L67 -> 666.8596 | M85: =M19+M43+M67 -> 632.5844 | N85: =N19+N43+N67 -> 666.8596 | O85: =O19+O43+O67 -> 632.5844 | P85: =P19+P43+P67 -> 740.0188 | Q85: =Q19+Q43+Q67 -> 765.71623 | ... AM85: =AM19+AM43+AM67 -> 704.02405
C86: Cash factory overhead | J86: =J21+J45+J69 -> 69.554971 | K86: =K21+K45+K69 -> 69.440885 | L86: =L21+L45+L69 -> 71.272514 | M86: =M21+M45+M69 -> 67.609256 | N86: =N21+N45+N69 -> 71.272514 | O86: =O21+O45+O69 -> 67.609256 | P86: =P21+P45+P69 -> 79.091612 | Q86: =Q21+Q45+Q69 -> 81.838098 | ... AM86: =AM21+AM45+AM69 -> 75.244571
C87: Manufacturing payroll cash | J87: =Payroll!J16 -> 47.012986 | K87: =Payroll!K16 -> 47.012986 | L87: =Payroll!L16 -> 47.012986 | M87: =Payroll!M16 -> 47.012986 | N87: =Payroll!N16 -> 47.012986 | O87: =Payroll!O16 -> 47.012986 | P87: =Payroll!P16 -> 48.423375 | Q87: =Payroll!Q16 -> 48.423375 | ... AM87: =Payroll!AM16 -> 49.876076
C88: COGS released from finished goods | J88: =J27+J51+J75 -> 934.96438 | K88: =K27+K51+K75 -> 849.74845 | L88: =L27+L51+L75 -> 811.31093 | M88: =M27+M51+M75 -> 797.21891 | N88: =N27+N51+N75 -> 788.59336 | O88: =O27+O51+O75 -> 786.86144 | P88: =P27+P51+P75 -> 841.68936 | Q88: =Q27+Q51+Q75 -> 841.92267 | ... AM88: =AM27+AM51+AM75 -> 870.90581
C89: FG carrying value total | J89: =J28+J52+J76 -> 741.71215 | K89: =K28+K52+K76 -> 674.74285 | L89: =L28+L52+L76 -> 665.31213 | M89: =M28+M52+M76 -> 632.16683 | N89: =N28+N52+N76 -> 645.71738 | O89: =O28+O52+O76 -> 623.19324 | P89: =P28+P52+P76 -> 666.30018 | Q89: =Q28+Q52+Q76 -> 737.75616 | ... AM89: =AM28+AM52+AM76 -> 699.8149
C90: Unabsorbed payroll and D&A when no production | J90: =IF(J84=0,Payroll!J16+Assets!J100*SourceAnalysis!D28,0) -> 0 | K90: =IF(K84=0,Payroll!K16+Assets!K100*SourceAnalysis!D28,0) -> 0 | L90: =IF(L84=0,Payroll!L16+Assets!L100*SourceAnalysis!D28,0) -> 0 | M90: =IF(M84=0,Payroll!M16+Assets!M100*SourceAnalysis!D28,0) -> 0 | N90: =IF(N84=0,Payroll!N16+Assets!N100*SourceAnalysis!D28,0) -> 0 | O90: =IF(O84=0,Payroll!O16+Assets!O100*SourceAnalysis!D28,0) -> 0 | P90: =IF(P84=0,Payroll!P16+Assets!P100*SourceAnalysis!D28,0) -> 0 | Q90: =IF(Q84=0,Payroll!Q16+Assets!Q100*SourceAnalysis!D28,0) -> 0 | R90: =IF(R84=0,Payroll!R16+Assets!R100*SourceAnalysis!D28,0) -> 0 | S90: =IF(S84=0,Payroll!S16+Assets!S100*SourceAnalysis!D28,0) -> 0 | T90: =IF(T84=0,Payroll!T16+Assets!T100*SourceAnalysis!D28,0) -> 0 | U90: =IF(U84=0,Payroll!U16+Assets!U100*SourceAnalysis!D28,0) -> 0 | V90: =IF(V84=0,Payroll!V16+Assets!V100*SourceAnalysis!D28,0) -> 0 | W90: =IF(W84=0,Payroll!W16+Assets!W100*SourceAnalysis!D28,0) -> 0 | X90: =IF(X84=0,Payroll!X16+Assets!X100*SourceAnalysis!D28,0) -> 0 | Y90: =IF(Y84=0,Payroll!Y16+Assets!Y100*SourceAnalysis!D28,0) -> 0 | Z90: =IF(Z84=0,Payroll!Z16+Assets!Z100*SourceAnalysis!D28,0) -> 0 | AA90: =IF(AA84=0,Payroll!AA16+Assets!AA100*SourceAnalysis!D28,0) -> 0 | AB90: =IF(AB84=0,Payroll!AB16+Assets!AB100*SourceAnalysis!D28,0) -> 0 | AC90: =IF(AC84=0,Payroll!AC16+Assets!AC100*SourceAnalysis!D28,0) -> 0 | AD90: =IF(AD84=0,Payroll!AD16+Assets!AD100*SourceAnalysis!D28,0) -> 0 | AE90: =IF(AE84=0,Payroll!AE16+Assets!AE100*SourceAnalysis!D28,0) -> 0 | AF90: =IF(AF84=0,Payroll!AF16+Assets!AF100*SourceAnalysis!D28,0) -> 0 | AG90: =IF(AG84=0,Payroll!AG16+Assets!AG100*SourceAnalysis!D28,0) -> 0 | AH90: =IF(AH84=0,Payroll!AH16+Assets!AH100*SourceAnalysis!D28,0) -> 0 | AI90: =IF(AI84=0,Payroll!AI16+Assets!AI100*SourceAnalysis!D28,0) -> 0 | AJ90: =IF(AJ84=0,Payroll!AJ16+Assets!AJ100*SourceAnalysis!D28,0) -> 0 | AK90: =IF(AK84=0,Payroll!AK16+Assets!AK100*SourceAnalysis!D28,0) -> 0 | AL90: =IF(AL84=0,Payroll!AL16+Assets!AL100*SourceAnalysis!D28,0) -> 0 | AM90: =IF(AM84=0,Payroll!AM16+Assets!AM100*SourceAnalysis!D28,0) -> 0
C95: L13/L14: book FG allocated by disclosed physical stock × calculated unit COGS; this is not a disclosed product inventory valuation. Material and factory-overhead nature shares are allocated using product COGS. Production requirement is uncapped because actual usable capacity is not evidenced; do not interpret it as a capacity plan.

Sheet Payroll
C2: 公牛集团 Payroll
C3: RMB million except stated units. H1 2026 actual aggregate is separate; monthly forecast begins July 2026.
D6: Not disclosed | E6: Not disclosed | F6: Not disclosed | G6: Not disclosed | H6: Not disclosed | I6: H1: see H1Actual | J6: Forecast | K6: Forecast | L6: Forecast | M6: Forecast | N6: Forecast | O6: Forecast | P6: Forecast | Q6: Forecast | R6: Forecast | S6: Forecast | T6: Forecast | U6: Forecast | V6: Forecast | W6: Forecast | X6: Forecast | Y6: Forecast | Z6: Forecast | AA6: Forecast | AB6: Forecast | AC6: Forecast | AD6: Forecast | AE6: Forecast | AF6: Forecast | AG6: Forecast | AH6: Forecast | AI6: Forecast | AJ6: Forecast | AK6: Forecast | AL6: Forecast | AM6: Forecast
D7: 46053 | E7: 46081 | F7: 46112 | G7: 46142 | H7: 46173 | I7: 46203 | J7: 46234 | K7: 46265 | L7: 46295 | M7: 46326 | N7: 46356 | O7: 46387 | P7: 46418 | Q7: 46446 | R7: 46477 | S7: 46507 | T7: 46538 | U7: 46568 | V7: 46599 | W7: 46630 | X7: 46660 | Y7: 46691 | Z7: 46721 | AA7: 46752 | AB7: 46783 | AC7: 46812 | AD7: 46843 | AE7: 46873 | AF7: 46904 | AG7: 46934 | AH7: 46965 | AI7: 46996 | AJ7: 47026 | AK7: 47057 | AL7: 47087 | AM7: 47118
C9: Production 制造
C10: Opening employees | J10: =(SourceDetail!E200/1) -> 7734 | K10: =Payroll!J13 -> 7734 | L10: =Payroll!K13 -> 7734 | M10: =Payroll!L13 -> 7734 | N10: =Payroll!M13 -> 7734 | O10: =Payroll!N13 -> 7734 | P10: =Payroll!O13 -> 7734 | Q10: =Payroll!P13 -> 7734 | R10: =Payroll!Q13 -> 7734 | ... AM10: =Payroll!AL13 -> 7734
C11: Hires requested | J11: =MAX(0,Inputs!J70) -> 0 | K11: =MAX(0,Inputs!K70) -> 0 | L11: =MAX(0,Inputs!L70) -> 0 | M11: =MAX(0,Inputs!M70) -> 0 | N11: =MAX(0,Inputs!N70) -> 0 | O11: =MAX(0,Inputs!O70) -> 0 | P11: =MAX(0,Inputs!P70) -> 0 | Q11: =MAX(0,Inputs!Q70) -> 0 | ... AM11: =MAX(0,Inputs!AM70) -> 0
C12: Exits effective | J12: =MIN(MAX(0,Inputs!J71),J10+J11) -> 0 | K12: =MIN(MAX(0,Inputs!K71),K10+K11) -> 0 | L12: =MIN(MAX(0,Inputs!L71),L10+L11) -> 0 | M12: =MIN(MAX(0,Inputs!M71),M10+M11) -> 0 | N12: =MIN(MAX(0,Inputs!N71),N10+N11) -> 0 | O12: =MIN(MAX(0,Inputs!O71),O10+O11) -> 0 | P12: =MIN(MAX(0,Inputs!P71),P10+P11) -> 0 | Q12: =MIN(MAX(0,Inputs!Q71),Q10+Q11) -> 0 | ... AM12: =MIN(MAX(0,Inputs!AM71),AM10+AM11) -> 0
C13: Closing employees | J13: =J10+J11-J12 -> 7734 | K13: =K10+K11-K12 -> 7734 | L13: =L10+L11-L12 -> 7734 | M13: =M10+M11-M12 -> 7734 | N13: =N10+N11-N12 -> 7734 | O13: =O10+O11-O12 -> 7734 | P13: =P10+P11-P12 -> 7734 | Q13: =Q10+Q11-Q12 -> 7734 | ... AM13: =AM10+AM11-AM12 -> 7734
C14: Average modeled employees | J14: =(J10+J13)/2 -> 7734 | K14: =(K10+K13)/2 -> 7734 | L14: =(L10+L13)/2 -> 7734 | M14: =(M10+M13)/2 -> 7734 | N14: =(N10+N13)/2 -> 7734 | O14: =(O10+O13)/2 -> 7734 | P14: =(P10+P13)/2 -> 7734 | Q14: =(Q10+Q13)/2 -> 7734 | ... AM14: =(AM10+AM13)/2 -> 7734
C15: Monthly remuneration/person RMB | J15: =((SourceDetail!E76/1000000)*1000000/(SourceDetail!E200/1)/12)*(1+Inputs!J23) -> 6078.7413 | K15: =(Payroll!J15)*(1+Inputs!K23) -> 6078.7413 | L15: =(Payroll!K15)*(1+Inputs!L23) -> 6078.7413 | M15: =(Payroll!L15)*(1+Inputs!M23) -> 6078.7413 | N15: =(Payroll!M15)*(1+Inputs!N23) -> 6078.7413 | O15: =(Payroll!N15)*(1+Inputs!O23) -> 6078.7413 | P15: =(Payroll!O15)*(1+Inputs!P23) -> 6261.1036 | Q15: =(Payroll!P15)*(1+Inputs!Q23) -> 6261.1036 | R15: =(Payroll!Q15)*(1+Inputs!R23) -> 6261.1036 | ... AM15: =(Payroll!AL15)*(1+Inputs!AM23) -> 6448.9367
C16: Payroll cost RMB million | J16: =J14*J15/1000000 -> 47.012986 | K16: =K14*K15/1000000 -> 47.012986 | L16: =L14*L15/1000000 -> 47.012986 | M16: =M14*M15/1000000 -> 47.012986 | N16: =N14*N15/1000000 -> 47.012986 | O16: =O14*O15/1000000 -> 47.012986 | P16: =P14*P15/1000000 -> 48.423375 | Q16: =Q14*Q15/1000000 -> 48.423375 | ... AM16: =AM14*AM15/1000000 -> 49.876076
C17: Headcount roll-forward | J17: =J10+J11-J12-J13 -> 0 | K17: =K10+K11-K12-K13 -> 0 | L17: =L10+L11-L12-L13 -> 0 | M17: =M10+M11-M12-M13 -> 0 | N17: =N10+N11-N12-N13 -> 0 | O17: =O10+O11-O12-O13 -> 0 | P17: =P10+P11-P12-P13 -> 0 | Q17: =Q10+Q11-Q12-Q13 -> 0 | ... AM17: =AM10+AM11-AM12-AM13 -> 0
C21: Sales 销售
C22: Opening employees | J22: =(SourceDetail!E201/1) -> 1066 | K22: =Payroll!J25 -> 1066 | L22: =Payroll!K25 -> 1066 | M22: =Payroll!L25 -> 1066 | N22: =Payroll!M25 -> 1066 | O22: =Payroll!N25 -> 1066 | P22: =Payroll!O25 -> 1066 | Q22: =Payroll!P25 -> 1066 | R22: =Payroll!Q25 -> 1066 | ... AM22: =Payroll!AL25 -> 1066
C23: Hires requested | J23: =MAX(0,Inputs!J72) -> 0 | K23: =MAX(0,Inputs!K72) -> 0 | L23: =MAX(0,Inputs!L72) -> 0 | M23: =MAX(0,Inputs!M72) -> 0 | N23: =MAX(0,Inputs!N72) -> 0 | O23: =MAX(0,Inputs!O72) -> 0 | P23: =MAX(0,Inputs!P72) -> 0 | Q23: =MAX(0,Inputs!Q72) -> 0 | ... AM23: =MAX(0,Inputs!AM72) -> 0
C24: Exits effective | J24: =MIN(MAX(0,Inputs!J73),J22+J23) -> 0 | K24: =MIN(MAX(0,Inputs!K73),K22+K23) -> 0 | L24: =MIN(MAX(0,Inputs!L73),L22+L23) -> 0 | M24: =MIN(MAX(0,Inputs!M73),M22+M23) -> 0 | N24: =MIN(MAX(0,Inputs!N73),N22+N23) -> 0 | O24: =MIN(MAX(0,Inputs!O73),O22+O23) -> 0 | P24: =MIN(MAX(0,Inputs!P73),P22+P23) -> 0 | Q24: =MIN(MAX(0,Inputs!Q73),Q22+Q23) -> 0 | ... AM24: =MIN(MAX(0,Inputs!AM73),AM22+AM23) -> 0
C25: Closing employees | J25: =J22+J23-J24 -> 1066 | K25: =K22+K23-K24 -> 1066 | L25: =L22+L23-L24 -> 1066 | M25: =M22+M23-M24 -> 1066 | N25: =N22+N23-N24 -> 1066 | O25: =O22+O23-O24 -> 1066 | P25: =P22+P23-P24 -> 1066 | Q25: =Q22+Q23-Q24 -> 1066 | ... AM25: =AM22+AM23-AM24 -> 1066
C26: Average modeled employees | J26: =(J22+J25)/2 -> 1066 | K26: =(K22+K25)/2 -> 1066 | L26: =(L22+L25)/2 -> 1066 | M26: =(M22+M25)/2 -> 1066 | N26: =(N22+N25)/2 -> 1066 | O26: =(O22+O25)/2 -> 1066 | P26: =(P22+P25)/2 -> 1066 | Q26: =(Q22+Q25)/2 -> 1066 | ... AM26: =(AM22+AM25)/2 -> 1066
C27: Monthly remuneration/person RMB | J27: =((SourceDetail!E10/1000000)*1000000/(SourceDetail!E201/1)/12)*(1+Inputs!J23) -> 34991.638 | K27: =(Payroll!J27)*(1+Inputs!K23) -> 34991.638 | L27: =(Payroll!K27)*(1+Inputs!L23) -> 34991.638 | M27: =(Payroll!L27)*(1+Inputs!M23) -> 34991.638 | N27: =(Payroll!M27)*(1+Inputs!N23) -> 34991.638 | O27: =(Payroll!N27)*(1+Inputs!O23) -> 34991.638 | P27: =(Payroll!O27)*(1+Inputs!P23) -> 36041.387 | Q27: =(Payroll!P27)*(1+Inputs!Q23) -> 36041.387 | R27: =(Payroll!Q27)*(1+Inputs!R23) -> 36041.387 | ... AM27: =(Payroll!AL27)*(1+Inputs!AM23) -> 37122.629
C28: Payroll cost RMB million | J28: =J26*J27/1000000 -> 37.301086 | K28: =K26*K27/1000000 -> 37.301086 | L28: =L26*L27/1000000 -> 37.301086 | M28: =M26*M27/1000000 -> 37.301086 | N28: =N26*N27/1000000 -> 37.301086 | O28: =O26*O27/1000000 -> 37.301086 | P28: =P26*P27/1000000 -> 38.420119 | Q28: =Q26*Q27/1000000 -> 38.420119 | ... AM28: =AM26*AM27/1000000 -> 39.572722
C29: Headcount roll-forward | J29: =J22+J23-J24-J25 -> 0 | K29: =K22+K23-K24-K25 -> 0 | L29: =L22+L23-L24-L25 -> 0 | M29: =M22+M23-M24-M25 -> 0 | N29: =N22+N23-N24-N25 -> 0 | O29: =O22+O23-O24-O25 -> 0 | P29: =P22+P23-P24-P25 -> 0 | Q29: =Q22+Q23-Q24-Q25 -> 0 | ... AM29: =AM22+AM23-AM24-AM25 -> 0
C33: R&D 研发
C34: Opening employees | J34: =(SourceDetail!E202/1) -> 2010 | K34: =Payroll!J37 -> 2010 | L34: =Payroll!K37 -> 2010 | M34: =Payroll!L37 -> 2010 | N34: =Payroll!M37 -> 2010 | O34: =Payroll!N37 -> 2010 | P34: =Payroll!O37 -> 2010 | Q34: =Payroll!P37 -> 2010 | R34: =Payroll!Q37 -> 2010 | ... AM34: =Payroll!AL37 -> 2010
C35: Hires requested | J35: =MAX(0,Inputs!J74) -> 0 | K35: =MAX(0,Inputs!K74) -> 0 | L35: =MAX(0,Inputs!L74) -> 0 | M35: =MAX(0,Inputs!M74) -> 0 | N35: =MAX(0,Inputs!N74) -> 0 | O35: =MAX(0,Inputs!O74) -> 0 | P35: =MAX(0,Inputs!P74) -> 0 | Q35: =MAX(0,Inputs!Q74) -> 0 | ... AM35: =MAX(0,Inputs!AM74) -> 0
C36: Exits effective | J36: =MIN(MAX(0,Inputs!J75),J34+J35) -> 0 | K36: =MIN(MAX(0,Inputs!K75),K34+K35) -> 0 | L36: =MIN(MAX(0,Inputs!L75),L34+L35) -> 0 | M36: =MIN(MAX(0,Inputs!M75),M34+M35) -> 0 | N36: =MIN(MAX(0,Inputs!N75),N34+N35) -> 0 | O36: =MIN(MAX(0,Inputs!O75),O34+O35) -> 0 | P36: =MIN(MAX(0,Inputs!P75),P34+P35) -> 0 | Q36: =MIN(MAX(0,Inputs!Q75),Q34+Q35) -> 0 | ... AM36: =MIN(MAX(0,Inputs!AM75),AM34+AM35) -> 0
C37: Closing employees | J37: =J34+J35-J36 -> 2010 | K37: =K34+K35-K36 -> 2010 | L37: =L34+L35-L36 -> 2010 | M37: =M34+M35-M36 -> 2010 | N37: =N34+N35-N36 -> 2010 | O37: =O34+O35-O36 -> 2010 | P37: =P34+P35-P36 -> 2010 | Q37: =Q34+Q35-Q36 -> 2010 | ... AM37: =AM34+AM35-AM36 -> 2010
C38: Average modeled employees | J38: =(J34+J37)/2 -> 2010 | K38: =(K34+K37)/2 -> 2010 | L38: =(L34+L37)/2 -> 2010 | M38: =(M34+M37)/2 -> 2010 | N38: =(N34+N37)/2 -> 2010 | O38: =(O34+O37)/2 -> 2010 | P38: =(P34+P37)/2 -> 2010 | Q38: =(Q34+Q37)/2 -> 2010 | ... AM38: =(AM34+AM37)/2 -> 2010
C39: Monthly remuneration/person RMB | J39: =((SourceDetail!E46/1000000)*1000000/(SourceDetail!E202/1)/12)*(1+Inputs!J23) -> 16467.645 | K39: =(Payroll!J39)*(1+Inputs!K23) -> 16467.645 | L39: =(Payroll!K39)*(1+Inputs!L23) -> 16467.645 | M39: =(Payroll!L39)*(1+Inputs!M23) -> 16467.645 | N39: =(Payroll!M39)*(1+Inputs!N23) -> 16467.645 | O39: =(Payroll!N39)*(1+Inputs!O23) -> 16467.645 | P39: =(Payroll!O39)*(1+Inputs!P23) -> 16961.674 | Q39: =(Payroll!P39)*(1+Inputs!Q23) -> 16961.674 | R39: =(Payroll!Q39)*(1+Inputs!R23) -> 16961.674 | ... AM39: =(Payroll!AL39)*(1+Inputs!AM23) -> 17470.524
C40: Payroll cost RMB million | J40: =J38*J39/1000000 -> 33.099966 | K40: =K38*K39/1000000 -> 33.099966 | L40: =L38*L39/1000000 -> 33.099966 | M40: =M38*M39/1000000 -> 33.099966 | N40: =N38*N39/1000000 -> 33.099966 | O40: =O38*O39/1000000 -> 33.099966 | P40: =P38*P39/1000000 -> 34.092965 | Q40: =Q38*Q39/1000000 -> 34.092965 | ... AM40: =AM38*AM39/1000000 -> 35.115754
C41: Headcount roll-forward | J41: =J34+J35-J36-J37 -> 0 | K41: =K34+K35-K36-K37 -> 0 | L41: =L34+L35-L36-L37 -> 0 | M41: =M34+M35-M36-M37 -> 0 | N41: =N34+N35-N36-N37 -> 0 | O41: =O34+O35-O36-O37 -> 0 | P41: =P34+P35-P36-P37 -> 0 | Q41: =Q34+Q35-Q36-Q37 -> 0 | ... AM41: =AM34+AM35-AM36-AM37 -> 0
C45: Finance/admin 财务行政
C46: Opening employees | J46: =((SourceDetail!E203/1)+(SourceDetail!E204/1)) -> 1702 | K46: =Payroll!J49 -> 1702 | L46: =Payroll!K49 -> 1702 | M46: =Payroll!L49 -> 1702 | N46: =Payroll!M49 -> 1702 | O46: =Payroll!N49 -> 1702 | P46: =Payroll!O49 -> 1702 | Q46: =Payroll!P49 -> 1702 | R46: =Payroll!Q49 -> 1702 | ... AM46: =Payroll!AL49 -> 1702
C47: Hires requested | J47: =MAX(0,Inputs!J76) -> 0 | K47: =MAX(0,Inputs!K76) -> 0 | L47: =MAX(0,Inputs!L76) -> 0 | M47: =MAX(0,Inputs!M76) -> 0 | N47: =MAX(0,Inputs!N76) -> 0 | O47: =MAX(0,Inputs!O76) -> 0 | P47: =MAX(0,Inputs!P76) -> 0 | Q47: =MAX(0,Inputs!Q76) -> 0 | ... AM47: =MAX(0,Inputs!AM76) -> 0
C48: Exits effective | J48: =MIN(MAX(0,Inputs!J77),J46+J47) -> 0 | K48: =MIN(MAX(0,Inputs!K77),K46+K47) -> 0 | L48: =MIN(MAX(0,Inputs!L77),L46+L47) -> 0 | M48: =MIN(MAX(0,Inputs!M77),M46+M47) -> 0 | N48: =MIN(MAX(0,Inputs!N77),N46+N47) -> 0 | O48: =MIN(MAX(0,Inputs!O77),O46+O47) -> 0 | P48: =MIN(MAX(0,Inputs!P77),P46+P47) -> 0 | Q48: =MIN(MAX(0,Inputs!Q77),Q46+Q47) -> 0 | ... AM48: =MIN(MAX(0,Inputs!AM77),AM46+AM47) -> 0
C49: Closing employees | J49: =J46+J47-J48 -> 1702 | K49: =K46+K47-K48 -> 1702 | L49: =L46+L47-L48 -> 1702 | M49: =M46+M47-M48 -> 1702 | N49: =N46+N47-N48 -> 1702 | O49: =O46+O47-O48 -> 1702 | P49: =P46+P47-P48 -> 1702 | Q49: =Q46+Q47-Q48 -> 1702 | ... AM49: =AM46+AM47-AM48 -> 1702
C50: Average modeled employees | J50: =(J46+J49)/2 -> 1702 | K50: =(K46+K49)/2 -> 1702 | L50: =(L46+L49)/2 -> 1702 | M50: =(M46+M49)/2 -> 1702 | N50: =(N46+N49)/2 -> 1702 | O50: =(O46+O49)/2 -> 1702 | P50: =(P46+P49)/2 -> 1702 | Q50: =(Q46+Q49)/2 -> 1702 | ... AM50: =(AM46+AM49)/2 -> 1702
C51: Monthly remuneration/person RMB | J51: =((SourceDetail!E24/1000000)*1000000/((SourceDetail!E203/1)+(SourceDetail!E204/1))/12)*(1+Inputs!J23) -> 21627.095 | K51: =(Payroll!J51)*(1+Inputs!K23) -> 21627.095 | L51: =(Payroll!K51)*(1+Inputs!L23) -> 21627.095 | M51: =(Payroll!L51)*(1+Inputs!M23) -> 21627.095 | N51: =(Payroll!M51)*(1+Inputs!N23) -> 21627.095 | O51: =(Payroll!N51)*(1+Inputs!O23) -> 21627.095 | P51: =(Payroll!O51)*(1+Inputs!P23) -> 22275.908 | Q51: =(Payroll!P51)*(1+Inputs!Q23) -> 22275.908 | R51: =(Payroll!Q51)*(1+Inputs!R23) -> 22275.908 | ... AM51: =(Payroll!AL51)*(1+Inputs!AM23) -> 22944.185
C52: Payroll cost RMB million | J52: =J50*J51/1000000 -> 36.809315 | K52: =K50*K51/1000000 -> 36.809315 | L52: =L50*L51/1000000 -> 36.809315 | M52: =M50*M51/1000000 -> 36.809315 | N52: =N50*N51/1000000 -> 36.809315 | O52: =O50*O51/1000000 -> 36.809315 | P52: =P50*P51/1000000 -> 37.913595 | Q52: =Q50*Q51/1000000 -> 37.913595 | ... AM52: =AM50*AM51/1000000 -> 39.051003
C53: Headcount roll-forward | J53: =J46+J47-J48-J49 -> 0 | K53: =K46+K47-K48-K49 -> 0 | L53: =L46+L47-L48-L49 -> 0 | M53: =M46+M47-M48-M49 -> 0 | N53: =N46+N47-N48-N49 -> 0 | O53: =O46+O47-O48-O49 -> 0 | P53: =P46+P47-P48-P49 -> 0 | Q53: =Q46+Q47-Q48-Q49 -> 0 | ... AM53: =AM46+AM47-AM48-AM49 -> 0
C61: L15: payroll / year-end functional HC is a modeled remuneration proxy. Technical staff are allocated to R&D; finance/admin to administration. Neither mapping is an issuer-approved payroll budget.

Sheet ExpenseDetail
C2: 公牛集团 ExpenseDetail
C3: RMB million except stated units. H1 2026 actual aggregate is separate; monthly forecast begins July 2026.
D6: Not disclosed | E6: Not disclosed | F6: Not disclosed | G6: Not disclosed | H6: Not disclosed | I6: H1: see H1Actual | J6: Forecast | K6: Forecast | L6: Forecast | M6: Forecast | N6: Forecast | O6: Forecast | P6: Forecast | Q6: Forecast | R6: Forecast | S6: Forecast | T6: Forecast | U6: Forecast | V6: Forecast | W6: Forecast | X6: Forecast | Y6: Forecast | Z6: Forecast | AA6: Forecast | AB6: Forecast | AC6: Forecast | AD6: Forecast | AE6: Forecast | AF6: Forecast | AG6: Forecast | AH6: Forecast | AI6: Forecast | AJ6: Forecast | AK6: Forecast | AL6: Forecast | AM6: Forecast
D7: 46053 | E7: 46081 | F7: 46112 | G7: 46142 | H7: 46173 | I7: 46203 | J7: 46234 | K7: 46265 | L7: 46295 | M7: 46326 | N7: 46356 | O7: 46387 | P7: 46418 | Q7: 46446 | R7: 46477 | S7: 46507 | T7: 46538 | U7: 46568 | V7: 46599 | W7: 46630 | X7: 46660 | Y7: 46691 | Z7: 46721 | AA7: 46752 | AB7: 46783 | AC7: 46812 | AD7: 46843 | AE7: 46873 | AF7: 46904 | AG7: 46934 | AH7: 46965 | AI7: 46996 | AJ7: 47026 | AK7: 47057 | AL7: 47087 | AM7: 47118
C9: selling
C10: selling.market_promotion | J10: =(Revenue!J40*(SourceDetail!E8/1000000)/SourceHistory!F9)*Inputs!J130 -> 46.320565 | K10: =(Revenue!K40*(SourceDetail!E8/1000000)/SourceHistory!F9)*Inputs!K130 -> 46.320565 | L10: =(Revenue!L40*(SourceDetail!E8/1000000)/SourceHistory!F9)*Inputs!L130 -> 46.320565 | M10: =(Revenue!M40*(SourceDetail!E8/1000000)/SourceHistory!F9)*Inputs!M130 -> 46.320565 | N10: =(Revenue!N40*(SourceDetail!E8/1000000)/SourceHistory!F9)*Inputs!N130 -> 46.320565 | O10: =(Revenue!O40*(SourceDetail!E8/1000000)/SourceHistory!F9)*Inputs!O130 -> 46.320565 | P10: =(Revenue!P40*(SourceDetail!E8/1000000)/SourceHistory!F9)*Inputs!P130 -> 49.471649 | Q10: =(Revenue!Q40*(SourceDetail!E8/1000000)/SourceHistory!F9)*Inputs!Q130 -> 49.471649 | R10: =(Revenue!R40*(SourceDetail!E8/1000000)/SourceHistory!F9)*Inputs!R130 -> 49.471649 | S10: =(Revenue!S40*(SourceDetail!E8/1000000)/SourceHistory!F9)*Inputs!S130 -> 49.471649 | T10: =(Revenue!T40*(SourceDetail!E8/1000000)/SourceHistory!F9)*Inputs!T130 -> 49.471649 | U10: =(Revenue!U40*(SourceDetail!E8/1000000)/SourceHistory!F9)*Inputs!U130 -> 49.471649 | V10: =(Revenue!V40*(SourceDetail!E8/1000000)/SourceHistory!F9)*Inputs!V130 -> 48.00119 | W10: =(Revenue!W40*(SourceDetail!E8/1000000)/SourceHistory!F9)*Inputs!W130 -> 48.00119 | X10: =(Revenue!X40*(SourceDetail!E8/1000000)/SourceHistory!F9)*Inputs!X130 -> 48.00119 | Y10: =(Revenue!Y40*(SourceDetail!E8/1000000)/SourceHistory!F9)*Inputs!Y130 -> 48.00119 | Z10: =(Revenue!Z40*(SourceDetail!E8/1000000)/SourceHistory!F9)*Inputs!Z130 -> 48.00119 | AA10: =(Revenue!AA40*(SourceDetail!E8/1000000)/SourceHistory!F9)*Inputs!AA130 -> 48.00119 | AB10: =(Revenue!AB40*(SourceDetail!E8/1000000)/SourceHistory!F9)*Inputs!AB130 -> 51.261711 | AC10: =(Revenue!AC40*(SourceDetail!E8/1000000)/SourceHistory!F9)*Inputs!AC130 -> 51.261711 | AD10: =(Revenue!AD40*(SourceDetail!E8/1000000)/SourceHistory!F9)*Inputs!AD130 -> 51.261711 | AE10: =(Revenue!AE40*(SourceDetail!E8/1000000)/SourceHistory!F9)*Inputs!AE130 -> 51.261711 | AF10: =(Revenue!AF40*(SourceDetail!E8/1000000)/SourceHistory!F9)*Inputs!AF130 -> 51.261711 | AG10: =(Revenue!AG40*(SourceDetail!E8/1000000)/SourceHistory!F9)*Inputs!AG130 -> 51.261711 | AH10: =(Revenue!AH40*(SourceDetail!E8/1000000)/SourceHistory!F9)*Inputs!AH130 -> 49.769852 | AI10: =(Revenue!AI40*(SourceDetail!E8/1000000)/SourceHistory!F9)*Inputs!AI130 -> 49.769852 | AJ10: =(Revenue!AJ40*(SourceDetail!E8/1000000)/SourceHistory!F9)*Inputs!AJ130 -> 49.769852 | AK10: =(Revenue!AK40*(SourceDetail!E8/1000000)/SourceHistory!F9)*Inputs!AK130 -> 49.769852 | AL10: =(Revenue!AL40*(SourceDetail!E8/1000000)/SourceHistory!F9)*Inputs!AL130 -> 49.769852 | AM10: =(Revenue!AM40*(SourceDetail!E8/1000000)/SourceHistory!F9)*Inputs!AM130 -> 49.769852
C11: selling.payroll | J11: =Payroll!J28 -> 37.301086 | K11: =Payroll!K28 -> 37.301086 | L11: =Payroll!L28 -> 37.301086 | M11: =Payroll!M28 -> 37.301086 | N11: =Payroll!N28 -> 37.301086 | O11: =Payroll!O28 -> 37.301086 | P11: =Payroll!P28 -> 38.420119 | Q11: =Payroll!Q28 -> 38.420119 | ... AM11: =Payroll!AM28 -> 39.572722
C12: selling.advertising | J12: =((SourceDetail!E12/1000000)/12*(1.02^1))*Inputs!J132 -> 6.5550325 | K12: =((SourceDetail!E12/1000000)/12*(1.02^1))*Inputs!K132 -> 6.5550325 | L12: =((SourceDetail!E12/1000000)/12*(1.02^1))*Inputs!L132 -> 6.5550325 | M12: =((SourceDetail!E12/1000000)/12*(1.02^1))*Inputs!M132 -> 6.5550325 | N12: =((SourceDetail!E12/1000000)/12*(1.02^1))*Inputs!N132 -> 6.5550325 | O12: =((SourceDetail!E12/1000000)/12*(1.02^1))*Inputs!O132 -> 6.5550325 | P12: =((SourceDetail!E12/1000000)/12*(1.02^2))*Inputs!P132 -> 6.6861331 | Q12: =((SourceDetail!E12/1000000)/12*(1.02^2))*Inputs!Q132 -> 6.6861331 | R12: =((SourceDetail!E12/1000000)/12*(1.02^2))*Inputs!R132 -> 6.6861331 | S12: =((SourceDetail!E12/1000000)/12*(1.02^2))*Inputs!S132 -> 6.6861331 | T12: =((SourceDetail!E12/1000000)/12*(1.02^2))*Inputs!T132 -> 6.6861331 | U12: =((SourceDetail!E12/1000000)/12*(1.02^2))*Inputs!U132 -> 6.6861331 | V12: =((SourceDetail!E12/1000000)/12*(1.02^2))*Inputs!V132 -> 6.6861331 | W12: =((SourceDetail!E12/1000000)/12*(1.02^2))*Inputs!W132 -> 6.6861331 | X12: =((SourceDetail!E12/1000000)/12*(1.02^2))*Inputs!X132 -> 6.6861331 | Y12: =((SourceDetail!E12/1000000)/12*(1.02^2))*Inputs!Y132 -> 6.6861331 | Z12: =((SourceDetail!E12/1000000)/12*(1.02^2))*Inputs!Z132 -> 6.6861331 | AA12: =((SourceDetail!E12/1000000)/12*(1.02^2))*Inputs!AA132 -> 6.6861331 | AB12: =((SourceDetail!E12/1000000)/12*(1.02^3))*Inputs!AB132 -> 6.8198558 | AC12: =((SourceDetail!E12/1000000)/12*(1.02^3))*Inputs!AC132 -> 6.8198558 | AD12: =((SourceDetail!E12/1000000)/12*(1.02^3))*Inputs!AD132 -> 6.8198558 | AE12: =((SourceDetail!E12/1000000)/12*(1.02^3))*Inputs!AE132 -> 6.8198558 | AF12: =((SourceDetail!E12/1000000)/12*(1.02^3))*Inputs!AF132 -> 6.8198558 | AG12: =((SourceDetail!E12/1000000)/12*(1.02^3))*Inputs!AG132 -> 6.8198558 | AH12: =((SourceDetail!E12/1000000)/12*(1.02^3))*Inputs!AH132 -> 6.8198558 | AI12: =((SourceDetail!E12/1000000)/12*(1.02^3))*Inputs!AI132 -> 6.8198558 | AJ12: =((SourceDetail!E12/1000000)/12*(1.02^3))*Inputs!AJ132 -> 6.8198558 | AK12: =((SourceDetail!E12/1000000)/12*(1.02^3))*Inputs!AK132 -> 6.8198558 | AL12: =((SourceDetail!E12/1000000)/12*(1.02^3))*Inputs!AL132 -> 6.8198558 | AM12: =((SourceDetail!E12/1000000)/12*(1.02^3))*Inputs!AM132 -> 6.8198558
C13: selling.travel | J13: =((SourceDetail!E14/1000000)/12/(SourceDetail!E201/1)*Payroll!J26)*Inputs!J133 -> 4.7331054 | K13: =((SourceDetail!E14/1000000)/12/(SourceDetail!E201/1)*Payroll!K26)*Inputs!K133 -> 4.7331054 | L13: =((SourceDetail!E14/1000000)/12/(SourceDetail!E201/1)*Payroll!L26)*Inputs!L133 -> 4.7331054 | M13: =((SourceDetail!E14/1000000)/12/(SourceDetail!E201/1)*Payroll!M26)*Inputs!M133 -> 4.7331054 | N13: =((SourceDetail!E14/1000000)/12/(SourceDetail!E201/1)*Payroll!N26)*Inputs!N133 -> 4.7331054 | O13: =((SourceDetail!E14/1000000)/12/(SourceDetail!E201/1)*Payroll!O26)*Inputs!O133 -> 4.7331054 | P13: =((SourceDetail!E14/1000000)/12/(SourceDetail!E201/1)*Payroll!P26)*Inputs!P133 -> 4.7331054 | Q13: =((SourceDetail!E14/1000000)/12/(SourceDetail!E201/1)*Payroll!Q26)*Inputs!Q133 -> 4.7331054 | R13: =((SourceDetail!E14/1000000)/12/(SourceDetail!E201/1)*Payroll!R26)*Inputs!R133 -> 4.7331054 | S13: =((SourceDetail!E14/1000000)/12/(SourceDetail!E201/1)*Payroll!S26)*Inputs!S133 -> 4.7331054 | T13: =((SourceDetail!E14/1000000)/12/(SourceDetail!E201/1)*Payroll!T26)*Inputs!T133 -> 4.7331054 | U13: =((SourceDetail!E14/1000000)/12/(SourceDetail!E201/1)*Payroll!U26)*Inputs!U133 -> 4.7331054 | V13: =((SourceDetail!E14/1000000)/12/(SourceDetail!E201/1)*Payroll!V26)*Inputs!V133 -> 4.7331054 | W13: =((SourceDetail!E14/1000000)/12/(SourceDetail!E201/1)*Payroll!W26)*Inputs!W133 -> 4.7331054 | X13: =((SourceDetail!E14/1000000)/12/(SourceDetail!E201/1)*Payroll!X26)*Inputs!X133 -> 4.7331054 | Y13: =((SourceDetail!E14/1000000)/12/(SourceDetail!E201/1)*Payroll!Y26)*Inputs!Y133 -> 4.7331054 | Z13: =((SourceDetail!E14/1000000)/12/(SourceDetail!E201/1)*Payroll!Z26)*Inputs!Z133 -> 4.7331054 | AA13: =((SourceDetail!E14/1000000)/12/(SourceDetail!E201/1)*Payroll!AA26)*Inputs!AA133 -> 4.7331054 | AB13: =((SourceDetail!E14/1000000)/12/(SourceDetail!E201/1)*Payroll!AB26)*Inputs!AB133 -> 4.7331054 | AC13: =((SourceDetail!E14/1000000)/12/(SourceDetail!E201/1)*Payroll!AC26)*Inputs!AC133 -> 4.7331054 | AD13: =((SourceDetail!E14/1000000)/12/(SourceDetail!E201/1)*Payroll!AD26)*Inputs!AD133 -> 4.7331054 | AE13: =((SourceDetail!E14/1000000)/12/(SourceDetail!E201/1)*Payroll!AE26)*Inputs!AE133 -> 4.7331054 | AF13: =((SourceDetail!E14/1000000)/12/(SourceDetail!E201/1)*Payroll!AF26)*Inputs!AF133 -> 4.7331054 | AG13: =((SourceDetail!E14/1000000)/12/(SourceDetail!E201/1)*Payroll!AG26)*Inputs!AG133 -> 4.7331054 | AH13: =((SourceDetail!E14/1000000)/12/(SourceDetail!E201/1)*Payroll!AH26)*Inputs!AH133 -> 4.7331054 | AI13: =((SourceDetail!E14/1000000)/12/(SourceDetail!E201/1)*Payroll!AI26)*Inputs!AI133 -> 4.7331054 | AJ13: =((SourceDetail!E14/1000000)/12/(SourceDetail!E201/1)*Payroll!AJ26)*Inputs!AJ133 -> 4.7331054 | AK13: =((SourceDetail!E14/1000000)/12/(SourceDetail!E201/1)*Payroll!AK26)*Inputs!AK133 -> 4.7331054 | AL13: =((SourceDetail!E14/1000000)/12/(SourceDetail!E201/1)*Payroll!AL26)*Inputs!AL133 -> 4.7331054 | AM13: =((SourceDetail!E14/1000000)/12/(SourceDetail!E201/1)*Payroll!AM26)*Inputs!AM133 -> 4.7331054
C14: selling.office | J14: =((SourceDetail!E16/1000000)/12/(SourceDetail!E201/1)*Payroll!J26)*Inputs!J134 -> 5.0575338 | K14: =((SourceDetail!E16/1000000)/12/(SourceDetail!E201/1)*Payroll!K26)*Inputs!K134 -> 5.0575338 | L14: =((SourceDetail!E16/1000000)/12/(SourceDetail!E201/1)*Payroll!L26)*Inputs!L134 -> 5.0575338 | M14: =((SourceDetail!E16/1000000)/12/(SourceDetail!E201/1)*Payroll!M26)*Inputs!M134 -> 5.0575338 | N14: =((SourceDetail!E16/1000000)/12/(SourceDetail!E201/1)*Payroll!N26)*Inputs!N134 -> 5.0575338 | O14: =((SourceDetail!E16/1000000)/12/(SourceDetail!E201/1)*Payroll!O26)*Inputs!O134 -> 5.0575338 | P14: =((SourceDetail!E16/1000000)/12/(SourceDetail!E201/1)*Payroll!P26)*Inputs!P134 -> 5.0575338 | Q14: =((SourceDetail!E16/1000000)/12/(SourceDetail!E201/1)*Payroll!Q26)*Inputs!Q134 -> 5.0575338 | R14: =((SourceDetail!E16/1000000)/12/(SourceDetail!E201/1)*Payroll!R26)*Inputs!R134 -> 5.0575338 | S14: =((SourceDetail!E16/1000000)/12/(SourceDetail!E201/1)*Payroll!S26)*Inputs!S134 -> 5.0575338 | T14: =((SourceDetail!E16/1000000)/12/(SourceDetail!E201/1)*Payroll!T26)*Inputs!T134 -> 5.0575338 | U14: =((SourceDetail!E16/1000000)/12/(SourceDetail!E201/1)*Payroll!U26)*Inputs!U134 -> 5.0575338 | V14: =((SourceDetail!E16/1000000)/12/(SourceDetail!E201/1)*Payroll!V26)*Inputs!V134 -> 5.0575338 | W14: =((SourceDetail!E16/1000000)/12/(SourceDetail!E201/1)*Payroll!W26)*Inputs!W134 -> 5.0575338 | X14: =((SourceDetail!E16/1000000)/12/(SourceDetail!E201/1)*Payroll!X26)*Inputs!X134 -> 5.0575338 | Y14: =((SourceDetail!E16/1000000)/12/(SourceDetail!E201/1)*Payroll!Y26)*Inputs!Y134 -> 5.0575338 | Z14: =((SourceDetail!E16/1000000)/12/(SourceDetail!E201/1)*Payroll!Z26)*Inputs!Z134 -> 5.0575338 | AA14: =((SourceDetail!E16/1000000)/12/(SourceDetail!E201/1)*Payroll!AA26)*Inputs!AA134 -> 5.0575338 | AB14: =((SourceDetail!E16/1000000)/12/(SourceDetail!E201/1)*Payroll!AB26)*Inputs!AB134 -> 5.0575338 | AC14: =((SourceDetail!E16/1000000)/12/(SourceDetail!E201/1)*Payroll!AC26)*Inputs!AC134 -> 5.0575338 | AD14: =((SourceDetail!E16/1000000)/12/(SourceDetail!E201/1)*Payroll!AD26)*Inputs!AD134 -> 5.0575338 | AE14: =((SourceDetail!E16/1000000)/12/(SourceDetail!E201/1)*Payroll!AE26)*Inputs!AE134 -> 5.0575338 | AF14: =((SourceDetail!E16/1000000)/12/(SourceDetail!E201/1)*Payroll!AF26)*Inputs!AF134 -> 5.0575338 | AG14: =((SourceDetail!E16/1000000)/12/(SourceDetail!E201/1)*Payroll!AG26)*Inputs!AG134 -> 5.0575338 | AH14: =((SourceDetail!E16/1000000)/12/(SourceDetail!E201/1)*Payroll!AH26)*Inputs!AH134 -> 5.0575338 | AI14: =((SourceDetail!E16/1000000)/12/(SourceDetail!E201/1)*Payroll!AI26)*Inputs!AI134 -> 5.0575338 | AJ14: =((SourceDetail!E16/1000000)/12/(SourceDetail!E201/1)*Payroll!AJ26)*Inputs!AJ134 -> 5.0575338 | AK14: =((SourceDetail!E16/1000000)/12/(SourceDetail!E201/1)*Payroll!AK26)*Inputs!AK134 -> 5.0575338 | AL14: =((SourceDetail!E16/1000000)/12/(SourceDetail!E201/1)*Payroll!AL26)*Inputs!AL134 -> 5.0575338 | AM14: =((SourceDetail!E16/1000000)/12/(SourceDetail!E201/1)*Payroll!AM26)*Inputs!AM134 -> 5.0575338
C15: selling.rent | J15: =((SourceDetail!E18/1000000)/12*(1.02^1))*Inputs!J135 -> 0.16431249 | K15: =((SourceDetail!E18/1000000)/12*(1.02^1))*Inputs!K135 -> 0.16431249 | L15: =((SourceDetail!E18/1000000)/12*(1.02^1))*Inputs!L135 -> 0.16431249 | M15: =((SourceDetail!E18/1000000)/12*(1.02^1))*Inputs!M135 -> 0.16431249 | N15: =((SourceDetail!E18/1000000)/12*(1.02^1))*Inputs!N135 -> 0.16431249 | O15: =((SourceDetail!E18/1000000)/12*(1.02^1))*Inputs!O135 -> 0.16431249 | P15: =((SourceDetail!E18/1000000)/12*(1.02^2))*Inputs!P135 -> 0.16759874 | Q15: =((SourceDetail!E18/1000000)/12*(1.02^2))*Inputs!Q135 -> 0.16759874 | R15: =((SourceDetail!E18/1000000)/12*(1.02^2))*Inputs!R135 -> 0.16759874 | S15: =((SourceDetail!E18/1000000)/12*(1.02^2))*Inputs!S135 -> 0.16759874 | T15: =((SourceDetail!E18/1000000)/12*(1.02^2))*Inputs!T135 -> 0.16759874 | U15: =((SourceDetail!E18/1000000)/12*(1.02^2))*Inputs!U135 -> 0.16759874 | V15: =((SourceDetail!E18/1000000)/12*(1.02^2))*Inputs!V135 -> 0.16759874 | W15: =((SourceDetail!E18/1000000)/12*(1.02^2))*Inputs!W135 -> 0.16759874 | X15: =((SourceDetail!E18/1000000)/12*(1.02^2))*Inputs!X135 -> 0.16759874 | Y15: =((SourceDetail!E18/1000000)/12*(1.02^2))*Inputs!Y135 -> 0.16759874 | Z15: =((SourceDetail!E18/1000000)/12*(1.02^2))*Inputs!Z135 -> 0.16759874 | AA15: =((SourceDetail!E18/1000000)/12*(1.02^2))*Inputs!AA135 -> 0.16759874 | AB15: =((SourceDetail!E18/1000000)/12*(1.02^3))*Inputs!AB135 -> 0.17095072 | AC15: =((SourceDetail!E18/1000000)/12*(1.02^3))*Inputs!AC135 -> 0.17095072 | AD15: =((SourceDetail!E18/1000000)/12*(1.02^3))*Inputs!AD135 -> 0.17095072 | AE15: =((SourceDetail!E18/1000000)/12*(1.02^3))*Inputs!AE135 -> 0.17095072 | AF15: =((SourceDetail!E18/1000000)/12*(1.02^3))*Inputs!AF135 -> 0.17095072 | AG15: =((SourceDetail!E18/1000000)/12*(1.02^3))*Inputs!AG135 -> 0.17095072 | AH15: =((SourceDetail!E18/1000000)/12*(1.02^3))*Inputs!AH135 -> 0.17095072 | AI15: =((SourceDetail!E18/1000000)/12*(1.02^3))*Inputs!AI135 -> 0.17095072 | AJ15: =((SourceDetail!E18/1000000)/12*(1.02^3))*Inputs!AJ135 -> 0.17095072 | AK15: =((SourceDetail!E18/1000000)/12*(1.02^3))*Inputs!AK135 -> 0.17095072 | AL15: =((SourceDetail!E18/1000000)/12*(1.02^3))*Inputs!AL135 -> 0.17095072 | AM15: =((SourceDetail!E18/1000000)/12*(1.02^3))*Inputs!AM135 -> 0.17095072
C16: selling.other | J16: =((SourceDetail!E20/1000000)/12*(1.02^1))*Inputs!J136 -> 0.43646948 | K16: =((SourceDetail!E20/1000000)/12*(1.02^1))*Inputs!K136 -> 0.43646948 | L16: =((SourceDetail!E20/1000000)/12*(1.02^1))*Inputs!L136 -> 0.43646948 | M16: =((SourceDetail!E20/1000000)/12*(1.02^1))*Inputs!M136 -> 0.43646948 | N16: =((SourceDetail!E20/1000000)/12*(1.02^1))*Inputs!N136 -> 0.43646948 | O16: =((SourceDetail!E20/1000000)/12*(1.02^1))*Inputs!O136 -> 0.43646948 | P16: =((SourceDetail!E20/1000000)/12*(1.02^2))*Inputs!P136 -> 0.44519887 | Q16: =((SourceDetail!E20/1000000)/12*(1.02^2))*Inputs!Q136 -> 0.44519887 | R16: =((SourceDetail!E20/1000000)/12*(1.02^2))*Inputs!R136 -> 0.44519887 | S16: =((SourceDetail!E20/1000000)/12*(1.02^2))*Inputs!S136 -> 0.44519887 | T16: =((SourceDetail!E20/1000000)/12*(1.02^2))*Inputs!T136 -> 0.44519887 | U16: =((SourceDetail!E20/1000000)/12*(1.02^2))*Inputs!U136 -> 0.44519887 | V16: =((SourceDetail!E20/1000000)/12*(1.02^2))*Inputs!V136 -> 0.44519887 | W16: =((SourceDetail!E20/1000000)/12*(1.02^2))*Inputs!W136 -> 0.44519887 | X16: =((SourceDetail!E20/1000000)/12*(1.02^2))*Inputs!X136 -> 0.44519887 | Y16: =((SourceDetail!E20/1000000)/12*(1.02^2))*Inputs!Y136 -> 0.44519887 | Z16: =((SourceDetail!E20/1000000)/12*(1.02^2))*Inputs!Z136 -> 0.44519887 | AA16: =((SourceDetail!E20/1000000)/12*(1.02^2))*Inputs!AA136 -> 0.44519887 | AB16: =((SourceDetail!E20/1000000)/12*(1.02^3))*Inputs!AB136 -> 0.45410285 | AC16: =((SourceDetail!E20/1000000)/12*(1.02^3))*Inputs!AC136 -> 0.45410285 | AD16: =((SourceDetail!E20/1000000)/12*(1.02^3))*Inputs!AD136 -> 0.45410285 | AE16: =((SourceDetail!E20/1000000)/12*(1.02^3))*Inputs!AE136 -> 0.45410285 | AF16: =((SourceDetail!E20/1000000)/12*(1.02^3))*Inputs!AF136 -> 0.45410285 | AG16: =((SourceDetail!E20/1000000)/12*(1.02^3))*Inputs!AG136 -> 0.45410285 | AH16: =((SourceDetail!E20/1000000)/12*(1.02^3))*Inputs!AH136 -> 0.45410285 | AI16: =((SourceDetail!E20/1000000)/12*(1.02^3))*Inputs!AI136 -> 0.45410285 | AJ16: =((SourceDetail!E20/1000000)/12*(1.02^3))*Inputs!AJ136 -> 0.45410285 | AK16: =((SourceDetail!E20/1000000)/12*(1.02^3))*Inputs!AK136 -> 0.45410285 | AL16: =((SourceDetail!E20/1000000)/12*(1.02^3))*Inputs!AL136 -> 0.45410285 | AM16: =((SourceDetail!E20/1000000)/12*(1.02^3))*Inputs!AM136 -> 0.45410285
C17: selling total | J17: =J10+J11+J12+J13+J14+J15+J16 -> 100.56811 | K17: =K10+K11+K12+K13+K14+K15+K16 -> 100.56811 | L17: =L10+L11+L12+L13+L14+L15+L16 -> 100.56811 | M17: =M10+M11+M12+M13+M14+M15+M16 -> 100.56811 | N17: =N10+N11+N12+N13+N14+N15+N16 -> 100.56811 | O17: =O10+O11+O12+O13+O14+O15+O16 -> 100.56811 | P17: =P10+P11+P12+P13+P14+P15+P16 -> 104.98134 | Q17: =Q10+Q11+Q12+Q13+Q14+Q15+Q16 -> 104.98134 | ... AM17: =AM10+AM11+AM12+AM13+AM14+AM15+AM16 -> 106.57812
C20: admin
C21: admin.payroll | J21: =Payroll!J52 -> 36.809315 | K21: =Payroll!K52 -> 36.809315 | L21: =Payroll!L52 -> 36.809315 | M21: =Payroll!M52 -> 36.809315 | N21: =Payroll!N52 -> 36.809315 | O21: =Payroll!O52 -> 36.809315 | P21: =Payroll!P52 -> 37.913595 | Q21: =Payroll!Q52 -> 37.913595 | ... AM21: =Payroll!AM52 -> 39.051003
C22: admin.share_based_comp | J22: =MAX(0,Inputs!J58) -> 3.7670464 | K22: =MAX(0,Inputs!K58) -> 3.7670464 | L22: =MAX(0,Inputs!L58) -> 3.7670464 | M22: =MAX(0,Inputs!M58) -> 3.7670464 | N22: =MAX(0,Inputs!N58) -> 3.7670464 | O22: =MAX(0,Inputs!O58) -> 3.7670464 | P22: =MAX(0,Inputs!P58) -> 3.7670464 | Q22: =MAX(0,Inputs!Q58) -> 3.7670464 | ... AM22: =MAX(0,Inputs!AM58) -> 3.7670464
C23: admin.depreciation_amortization | J23: =Assets!J100*SourceAnalysis!D26 -> 8.7032345 | K23: =Assets!K100*SourceAnalysis!D26 -> 8.7729004 | L23: =Assets!L100*SourceAnalysis!D26 -> 8.8425663 | M23: =Assets!M100*SourceAnalysis!D26 -> 8.9122322 | N23: =Assets!N100*SourceAnalysis!D26 -> 8.9818981 | O23: =Assets!O100*SourceAnalysis!D26 -> 9.051564 | P23: =Assets!P100*SourceAnalysis!D26 -> 9.1212299 | Q23: =Assets!Q100*SourceAnalysis!D26 -> 9.1943792 | R23: =Assets!R100*SourceAnalysis!D26 -> 9.2675284 | S23: =Assets!S100*SourceAnalysis!D26 -> 9.3406776 | T23: =Assets!T100*SourceAnalysis!D26 -> 9.4138268 | U23: =Assets!U100*SourceAnalysis!D26 -> 9.486976 | V23: =Assets!V100*SourceAnalysis!D26 -> 9.5601252 | W23: =Assets!W100*SourceAnalysis!D26 -> 9.6332744 | X23: =Assets!X100*SourceAnalysis!D26 -> 9.2961271 | Y23: =Assets!Y100*SourceAnalysis!D26 -> 9.3639015 | Z23: =Assets!Z100*SourceAnalysis!D26 -> 9.4370507 | AA23: =Assets!AA100*SourceAnalysis!D26 -> 9.5101999 | AB23: =Assets!AB100*SourceAnalysis!D26 -> 9.5833491 | AC23: =Assets!AC100*SourceAnalysis!D26 -> 9.6601558 | AD23: =Assets!AD100*SourceAnalysis!D26 -> 9.7369625 | AE23: =Assets!AE100*SourceAnalysis!D26 -> 9.8137691 | AF23: =Assets!AF100*SourceAnalysis!D26 -> 9.8905758 | AG23: =Assets!AG100*SourceAnalysis!D26 -> 9.9673825 | AH23: =Assets!AH100*SourceAnalysis!D26 -> 10.044189 | AI23: =Assets!AI100*SourceAnalysis!D26 -> 10.120996 | AJ23: =Assets!AJ100*SourceAnalysis!D26 -> 10.197802 | AK23: =Assets!AK100*SourceAnalysis!D26 -> 10.274609 | AL23: =Assets!AL100*SourceAnalysis!D26 -> 10.351416 | AM23: =Assets!AM100*SourceAnalysis!D26 -> 10.428223
C24: admin.office | J24: =((SourceDetail!E30/1000000)/12/((SourceDetail!E203/1)+(SourceDetail!E204/1))*Payroll!J50)*Inputs!J144 -> 5.4376951 | K24: =((SourceDetail!E30/1000000)/12/((SourceDetail!E203/1)+(SourceDetail!E204/1))*Payroll!K50)*Inputs!K144 -> 5.4376951 | L24: =((SourceDetail!E30/1000000)/12/((SourceDetail!E203/1)+(SourceDetail!E204/1))*Payroll!L50)*Inputs!L144 -> 5.4376951 | M24: =((SourceDetail!E30/1000000)/12/((SourceDetail!E203/1)+(SourceDetail!E204/1))*Payroll!M50)*Inputs!M144 -> 5.4376951 | N24: =((SourceDetail!E30/1000000)/12/((SourceDetail!E203/1)+(SourceDetail!E204/1))*Payroll!N50)*Inputs!N144 -> 5.4376951 | O24: =((SourceDetail!E30/1000000)/12/((SourceDetail!E203/1)+(SourceDetail!E204/1))*Payroll!O50)*Inputs!O144 -> 5.4376951 | P24: =((SourceDetail!E30/1000000)/12/((SourceDetail!E203/1)+(SourceDetail!E204/1))*Payroll!P50)*Inputs!P144 -> 5.4376951 | Q24: =((SourceDetail!E30/1000000)/12/((SourceDetail!E203/1)+(SourceDetail!E204/1))*Payroll!Q50)*Inputs!Q144 -> 5.4376951 | R24: =((SourceDetail!E30/1000000)/12/((SourceDetail!E203/1)+(SourceDetail!E204/1))*Payroll!R50)*Inputs!R144 -> 5.4376951 | S24: =((SourceDetail!E30/1000000)/12/((SourceDetail!E203/1)+(SourceDetail!E204/1))*Payroll!S50)*Inputs!S144 -> 5.4376951 | T24: =((SourceDetail!E30/1000000)/12/((SourceDetail!E203/1)+(SourceDetail!E204/1))*Payroll!T50)*Inputs!T144 -> 5.4376951 | U24: =((SourceDetail!E30/1000000)/12/((SourceDetail!E203/1)+(SourceDetail!E204/1))*Payroll!U50)*Inputs!U144 -> 5.4376951 | V24: =((SourceDetail!E30/1000000)/12/((SourceDetail!E203/1)+(SourceDetail!E204/1))*Payroll!V50)*Inputs!V144 -> 5.4376951 | W24: =((SourceDetail!E30/1000000)/12/((SourceDetail!E203/1)+(SourceDetail!E204/1))*Payroll!W50)*Inputs!W144 -> 5.4376951 | X24: =((SourceDetail!E30/1000000)/12/((SourceDetail!E203/1)+(SourceDetail!E204/1))*Payroll!X50)*Inputs!X144 -> 5.4376951 | Y24: =((SourceDetail!E30/1000000)/12/((SourceDetail!E203/1)+(SourceDetail!E204/1))*Payroll!Y50)*Inputs!Y144 -> 5.4376951 | Z24: =((SourceDetail!E30/1000000)/12/((SourceDetail!E203/1)+(SourceDetail!E204/1))*Payroll!Z50)*Inputs!Z144 -> 5.4376951 | AA24: =((SourceDetail!E30/1000000)/12/((SourceDetail!E203/1)+(SourceDetail!E204/1))*Payroll!AA50)*Inputs!AA144 -> 5.4376951 | AB24: =((SourceDetail!E30/1000000)/12/((SourceDetail!E203/1)+(SourceDetail!E204/1))*Payroll!AB50)*Inputs!AB144 -> 5.4376951 | AC24: =((SourceDetail!E30/1000000)/12/((SourceDetail!E203/1)+(SourceDetail!E204/1))*Payroll!AC50)*Inputs!AC144 -> 5.4376951 | AD24: =((SourceDetail!E30/1000000)/12/((SourceDetail!E203/1)+(SourceDetail!E204/1))*Payroll!AD50)*Inputs!AD144 -> 5.4376951 | AE24: =((SourceDetail!E30/1000000)/12/((SourceDetail!E203/1)+(SourceDetail!E204/1))*Payroll!AE50)*Inputs!AE144 -> 5.4376951 | AF24: =((SourceDetail!E30/1000000)/12/((SourceDetail!E203/1)+(SourceDetail!E204/1))*Payroll!AF50)*Inputs!AF144 -> 5.4376951 | AG24: =((SourceDetail!E30/1000000)/12/((SourceDetail!E203/1)+(SourceDetail!E204/1))*Payroll!AG50)*Inputs!AG144 -> 5.4376951 | AH24: =((SourceDetail!E30/1000000)/12/((SourceDetail!E203/1)+(SourceDetail!E204/1))*Payroll!AH50)*Inputs!AH144 -> 5.4376951 | AI24: =((SourceDetail!E30/1000000)/12/((SourceDetail!E203/1)+(SourceDetail!E204/1))*Payroll!AI50)*Inputs!AI144 -> 5.4376951 | AJ24: =((SourceDetail!E30/1000000)/12/((SourceDetail!E203/1)+(SourceDetail!E204/1))*Payroll!AJ50)*Inputs!AJ144 -> 5.4376951 | AK24: =((SourceDetail!E30/1000000)/12/((SourceDetail!E203/1)+(SourceDetail!E204/1))*Payroll!AK50)*Inputs!AK144 -> 5.4376951 | AL24: =((SourceDetail!E30/1000000)/12/((SourceDetail!E203/1)+(SourceDetail!E204/1))*Payroll!AL50)*Inputs!AL144 -> 5.4376951 | AM24: =((SourceDetail!E30/1000000)/12/((SourceDetail!E203/1)+(SourceDetail!E204/1))*Payroll!AM50)*Inputs!AM144 -> 5.4376951
C25: admin.maintenance | J25: =((SourceDetail!E32/1000000)/12*(1.02^1))*Inputs!J145 -> 1.7265318 | K25: =((SourceDetail!E32/1000000)/12*(1.02^1))*Inputs!K145 -> 1.7265318 | L25: =((SourceDetail!E32/1000000)/12*(1.02^1))*Inputs!L145 -> 1.7265318 | M25: =((SourceDetail!E32/1000000)/12*(1.02^1))*Inputs!M145 -> 1.7265318 | N25: =((SourceDetail!E32/1000000)/12*(1.02^1))*Inputs!N145 -> 1.7265318 | O25: =((SourceDetail!E32/1000000)/12*(1.02^1))*Inputs!O145 -> 1.7265318 | P25: =((SourceDetail!E32/1000000)/12*(1.02^2))*Inputs!P145 -> 1.7610625 | Q25: =((SourceDetail!E32/1000000)/12*(1.02^2))*Inputs!Q145 -> 1.7610625 | R25: =((SourceDetail!E32/1000000)/12*(1.02^2))*Inputs!R145 -> 1.7610625 | S25: =((SourceDetail!E32/1000000)/12*(1.02^2))*Inputs!S145 -> 1.7610625 | T25: =((SourceDetail!E32/1000000)/12*(1.02^2))*Inputs!T145 -> 1.7610625 | U25: =((SourceDetail!E32/1000000)/12*(1.02^2))*Inputs!U145 -> 1.7610625 | V25: =((SourceDetail!E32/1000000)/12*(1.02^2))*Inputs!V145 -> 1.7610625 | W25: =((SourceDetail!E32/1000000)/12*(1.02^2))*Inputs!W145 -> 1.7610625 | X25: =((SourceDetail!E32/1000000)/12*(1.02^2))*Inputs!X145 -> 1.7610625 | Y25: =((SourceDetail!E32/1000000)/12*(1.02^2))*Inputs!Y145 -> 1.7610625 | Z25: =((SourceDetail!E32/1000000)/12*(1.02^2))*Inputs!Z145 -> 1.7610625 | AA25: =((SourceDetail!E32/1000000)/12*(1.02^2))*Inputs!AA145 -> 1.7610625 | AB25: =((SourceDetail!E32/1000000)/12*(1.02^3))*Inputs!AB145 -> 1.7962837 | AC25: =((SourceDetail!E32/1000000)/12*(1.02^3))*Inputs!AC145 -> 1.7962837 | AD25: =((SourceDetail!E32/1000000)/12*(1.02^3))*Inputs!AD145 -> 1.7962837 | AE25: =((SourceDetail!E32/1000000)/12*(1.02^3))*Inputs!AE145 -> 1.7962837 | AF25: =((SourceDetail!E32/1000000)/12*(1.02^3))*Inputs!AF145 -> 1.7962837 | AG25: =((SourceDetail!E32/1000000)/12*(1.02^3))*Inputs!AG145 -> 1.7962837 | AH25: =((SourceDetail!E32/1000000)/12*(1.02^3))*Inputs!AH145 -> 1.7962837 | AI25: =((SourceDetail!E32/1000000)/12*(1.02^3))*Inputs!AI145 -> 1.7962837 | AJ25: =((SourceDetail!E32/1000000)/12*(1.02^3))*Inputs!AJ145 -> 1.7962837 | AK25: =((SourceDetail!E32/1000000)/12*(1.02^3))*Inputs!AK145 -> 1.7962837 | AL25: =((SourceDetail!E32/1000000)/12*(1.02^3))*Inputs!AL145 -> 1.7962837 | AM25: =((SourceDetail!E32/1000000)/12*(1.02^3))*Inputs!AM145 -> 1.7962837
C26: admin.taxes | J26: =Inputs!J99 -> 0 | K26: =Inputs!K99 -> 0 | L26: =Inputs!L99 -> 0 | M26: =Inputs!M99 -> 0 | N26: =Inputs!N99 -> 0 | O26: =Inputs!O99 -> 0 | P26: =Inputs!P99 -> 0 | Q26: =Inputs!Q99 -> 0 | ... AM26: =Inputs!AM99 -> 0
C27: admin.consulting | J27: =((SourceDetail!E36/1000000)/12*(1.02^1))*Inputs!J147 -> 2.2735763 | K27: =((SourceDetail!E36/1000000)/12*(1.02^1))*Inputs!K147 -> 2.2735763 | L27: =((SourceDetail!E36/1000000)/12*(1.02^1))*Inputs!L147 -> 2.2735763 | M27: =((SourceDetail!E36/1000000)/12*(1.02^1))*Inputs!M147 -> 2.2735763 | N27: =((SourceDetail!E36/1000000)/12*(1.02^1))*Inputs!N147 -> 2.2735763 | O27: =((SourceDetail!E36/1000000)/12*(1.02^1))*Inputs!O147 -> 2.2735763 | P27: =((SourceDetail!E36/1000000)/12*(1.02^2))*Inputs!P147 -> 2.3190478 | Q27: =((SourceDetail!E36/1000000)/12*(1.02^2))*Inputs!Q147 -> 2.3190478 | R27: =((SourceDetail!E36/1000000)/12*(1.02^2))*Inputs!R147 -> 2.3190478 | S27: =((SourceDetail!E36/1000000)/12*(1.02^2))*Inputs!S147 -> 2.3190478 | T27: =((SourceDetail!E36/1000000)/12*(1.02^2))*Inputs!T147 -> 2.3190478 | U27: =((SourceDetail!E36/1000000)/12*(1.02^2))*Inputs!U147 -> 2.3190478 | V27: =((SourceDetail!E36/1000000)/12*(1.02^2))*Inputs!V147 -> 2.3190478 | W27: =((SourceDetail!E36/1000000)/12*(1.02^2))*Inputs!W147 -> 2.3190478 | X27: =((SourceDetail!E36/1000000)/12*(1.02^2))*Inputs!X147 -> 2.3190478 | Y27: =((SourceDetail!E36/1000000)/12*(1.02^2))*Inputs!Y147 -> 2.3190478 | Z27: =((SourceDetail!E36/1000000)/12*(1.02^2))*Inputs!Z147 -> 2.3190478 | AA27: =((SourceDetail!E36/1000000)/12*(1.02^2))*Inputs!AA147 -> 2.3190478 | AB27: =((SourceDetail!E36/1000000)/12*(1.02^3))*Inputs!AB147 -> 2.3654288 | AC27: =((SourceDetail!E36/1000000)/12*(1.02^3))*Inputs!AC147 -> 2.3654288 | AD27: =((SourceDetail!E36/1000000)/12*(1.02^3))*Inputs!AD147 -> 2.3654288 | AE27: =((SourceDetail!E36/1000000)/12*(1.02^3))*Inputs!AE147 -> 2.3654288 | AF27: =((SourceDetail!E36/1000000)/12*(1.02^3))*Inputs!AF147 -> 2.3654288 | AG27: =((SourceDetail!E36/1000000)/12*(1.02^3))*Inputs!AG147 -> 2.3654288 | AH27: =((SourceDetail!E36/1000000)/12*(1.02^3))*Inputs!AH147 -> 2.3654288 | AI27: =((SourceDetail!E36/1000000)/12*(1.02^3))*Inputs!AI147 -> 2.3654288 | AJ27: =((SourceDetail!E36/1000000)/12*(1.02^3))*Inputs!AJ147 -> 2.3654288 | AK27: =((SourceDetail!E36/1000000)/12*(1.02^3))*Inputs!AK147 -> 2.3654288 | AL27: =((SourceDetail!E36/1000000)/12*(1.02^3))*Inputs!AL147 -> 2.3654288 | AM27: =((SourceDetail!E36/1000000)/12*(1.02^3))*Inputs!AM147 -> 2.3654288
C28: admin.rent | J28: =((SourceDetail!E38/1000000)/12*(1.02^1))*Inputs!J148 -> 0.34907976 | K28: =((SourceDetail!E38/1000000)/12*(1.02^1))*Inputs!K148 -> 0.34907976 | L28: =((SourceDetail!E38/1000000)/12*(1.02^1))*Inputs!L148 -> 0.34907976 | M28: =((SourceDetail!E38/1000000)/12*(1.02^1))*Inputs!M148 -> 0.34907976 | N28: =((SourceDetail!E38/1000000)/12*(1.02^1))*Inputs!N148 -> 0.34907976 | O28: =((SourceDetail!E38/1000000)/12*(1.02^1))*Inputs!O148 -> 0.34907976 | P28: =((SourceDetail!E38/1000000)/12*(1.02^2))*Inputs!P148 -> 0.35606136 | Q28: =((SourceDetail!E38/1000000)/12*(1.02^2))*Inputs!Q148 -> 0.35606136 | R28: =((SourceDetail!E38/1000000)/12*(1.02^2))*Inputs!R148 -> 0.35606136 | S28: =((SourceDetail!E38/1000000)/12*(1.02^2))*Inputs!S148 -> 0.35606136 | T28: =((SourceDetail!E38/1000000)/12*(1.02^2))*Inputs!T148 -> 0.35606136 | U28: =((SourceDetail!E38/1000000)/12*(1.02^2))*Inputs!U148 -> 0.35606136 | V28: =((SourceDetail!E38/1000000)/12*(1.02^2))*Inputs!V148 -> 0.35606136 | W28: =((SourceDetail!E38/1000000)/12*(1.02^2))*Inputs!W148 -> 0.35606136 | X28: =((SourceDetail!E38/1000000)/12*(1.02^2))*Inputs!X148 -> 0.35606136 | Y28: =((SourceDetail!E38/1000000)/12*(1.02^2))*Inputs!Y148 -> 0.35606136 | Z28: =((SourceDetail!E38/1000000)/12*(1.02^2))*Inputs!Z148 -> 0.35606136 | AA28: =((SourceDetail!E38/1000000)/12*(1.02^2))*Inputs!AA148 -> 0.35606136 | AB28: =((SourceDetail!E38/1000000)/12*(1.02^3))*Inputs!AB148 -> 0.36318259 | AC28: =((SourceDetail!E38/1000000)/12*(1.02^3))*Inputs!AC148 -> 0.36318259 | AD28: =((SourceDetail!E38/1000000)/12*(1.02^3))*Inputs!AD148 -> 0.36318259 | AE28: =((SourceDetail!E38/1000000)/12*(1.02^3))*Inputs!AE148 -> 0.36318259 | AF28: =((SourceDetail!E38/1000000)/12*(1.02^3))*Inputs!AF148 -> 0.36318259 | AG28: =((SourceDetail!E38/1000000)/12*(1.02^3))*Inputs!AG148 -> 0.36318259 | AH28: =((SourceDetail!E38/1000000)/12*(1.02^3))*Inputs!AH148 -> 0.36318259 | AI28: =((SourceDetail!E38/1000000)/12*(1.02^3))*Inputs!AI148 -> 0.36318259 | AJ28: =((SourceDetail!E38/1000000)/12*(1.02^3))*Inputs!AJ148 -> 0.36318259 | AK28: =((SourceDetail!E38/1000000)/12*(1.02^3))*Inputs!AK148 -> 0.36318259 | AL28: =((SourceDetail!E38/1000000)/12*(1.02^3))*Inputs!AL148 -> 0.36318259 | AM28: =((SourceDetail!E38/1000000)/12*(1.02^3))*Inputs!AM148 -> 0.36318259
C29: admin.entertainment | J29: =((SourceDetail!E40/1000000)/12*(1.02^1))*Inputs!J149 -> 0.69323743 | K29: =((SourceDetail!E40/1000000)/12*(1.02^1))*Inputs!K149 -> 0.69323743 | L29: =((SourceDetail!E40/1000000)/12*(1.02^1))*Inputs!L149 -> 0.69323743 | M29: =((SourceDetail!E40/1000000)/12*(1.02^1))*Inputs!M149 -> 0.69323743 | N29: =((SourceDetail!E40/1000000)/12*(1.02^1))*Inputs!N149 -> 0.69323743 | O29: =((SourceDetail!E40/1000000)/12*(1.02^1))*Inputs!O149 -> 0.69323743 | P29: =((SourceDetail!E40/1000000)/12*(1.02^2))*Inputs!P149 -> 0.70710218 | Q29: =((SourceDetail!E40/1000000)/12*(1.02^2))*Inputs!Q149 -> 0.70710218 | R29: =((SourceDetail!E40/1000000)/12*(1.02^2))*Inputs!R149 -> 0.70710218 | S29: =((SourceDetail!E40/1000000)/12*(1.02^2))*Inputs!S149 -> 0.70710218 | T29: =((SourceDetail!E40/1000000)/12*(1.02^2))*Inputs!T149 -> 0.70710218 | U29: =((SourceDetail!E40/1000000)/12*(1.02^2))*Inputs!U149 -> 0.70710218 | V29: =((SourceDetail!E40/1000000)/12*(1.02^2))*Inputs!V149 -> 0.70710218 | W29: =((SourceDetail!E40/1000000)/12*(1.02^2))*Inputs!W149 -> 0.70710218 | X29: =((SourceDetail!E40/1000000)/12*(1.02^2))*Inputs!X149 -> 0.70710218 | Y29: =((SourceDetail!E40/1000000)/12*(1.02^2))*Inputs!Y149 -> 0.70710218 | Z29: =((SourceDetail!E40/1000000)/12*(1.02^2))*Inputs!Z149 -> 0.70710218 | AA29: =((SourceDetail!E40/1000000)/12*(1.02^2))*Inputs!AA149 -> 0.70710218 | AB29: =((SourceDetail!E40/1000000)/12*(1.02^3))*Inputs!AB149 -> 0.72124423 | AC29: =((SourceDetail!E40/1000000)/12*(1.02^3))*Inputs!AC149 -> 0.72124423 | AD29: =((SourceDetail!E40/1000000)/12*(1.02^3))*Inputs!AD149 -> 0.72124423 | AE29: =((SourceDetail!E40/1000000)/12*(1.02^3))*Inputs!AE149 -> 0.72124423 | AF29: =((SourceDetail!E40/1000000)/12*(1.02^3))*Inputs!AF149 -> 0.72124423 | AG29: =((SourceDetail!E40/1000000)/12*(1.02^3))*Inputs!AG149 -> 0.72124423 | AH29: =((SourceDetail!E40/1000000)/12*(1.02^3))*Inputs!AH149 -> 0.72124423 | AI29: =((SourceDetail!E40/1000000)/12*(1.02^3))*Inputs!AI149 -> 0.72124423 | AJ29: =((SourceDetail!E40/1000000)/12*(1.02^3))*Inputs!AJ149 -> 0.72124423 | AK29: =((SourceDetail!E40/1000000)/12*(1.02^3))*Inputs!AK149 -> 0.72124423 | AL29: =((SourceDetail!E40/1000000)/12*(1.02^3))*Inputs!AL149 -> 0.72124423 | AM29: =((SourceDetail!E40/1000000)/12*(1.02^3))*Inputs!AM149 -> 0.72124423
C30: admin.other | J30: =((SourceDetail!E42/1000000)/12*(1.02^1))*Inputs!J150 -> 0.37710589 | K30: =((SourceDetail!E42/1000000)/12*(1.02^1))*Inputs!K150 -> 0.37710589 | L30: =((SourceDetail!E42/1000000)/12*(1.02^1))*Inputs!L150 -> 0.37710589 | M30: =((SourceDetail!E42/1000000)/12*(1.02^1))*Inputs!M150 -> 0.37710589 | N30: =((SourceDetail!E42/1000000)/12*(1.02^1))*Inputs!N150 -> 0.37710589 | O30: =((SourceDetail!E42/1000000)/12*(1.02^1))*Inputs!O150 -> 0.37710589 | P30: =((SourceDetail!E42/1000000)/12*(1.02^2))*Inputs!P150 -> 0.38464801 | Q30: =((SourceDetail!E42/1000000)/12*(1.02^2))*Inputs!Q150 -> 0.38464801 | R30: =((SourceDetail!E42/1000000)/12*(1.02^2))*Inputs!R150 -> 0.38464801 | S30: =((SourceDetail!E42/1000000)/12*(1.02^2))*Inputs!S150 -> 0.38464801 | T30: =((SourceDetail!E42/1000000)/12*(1.02^2))*Inputs!T150 -> 0.38464801 | U30: =((SourceDetail!E42/1000000)/12*(1.02^2))*Inputs!U150 -> 0.38464801 | V30: =((SourceDetail!E42/1000000)/12*(1.02^2))*Inputs!V150 -> 0.38464801 | W30: =((SourceDetail!E42/1000000)/12*(1.02^2))*Inputs!W150 -> 0.38464801 | X30: =((SourceDetail!E42/1000000)/12*(1.02^2))*Inputs!X150 -> 0.38464801 | Y30: =((SourceDetail!E42/1000000)/12*(1.02^2))*Inputs!Y150 -> 0.38464801 | Z30: =((SourceDetail!E42/1000000)/12*(1.02^2))*Inputs!Z150 -> 0.38464801 | AA30: =((SourceDetail!E42/1000000)/12*(1.02^2))*Inputs!AA150 -> 0.38464801 | AB30: =((SourceDetail!E42/1000000)/12*(1.02^3))*Inputs!AB150 -> 0.39234097 | AC30: =((SourceDetail!E42/1000000)/12*(1.02^3))*Inputs!AC150 -> 0.39234097 | AD30: =((SourceDetail!E42/1000000)/12*(1.02^3))*Inputs!AD150 -> 0.39234097 | AE30: =((SourceDetail!E42/1000000)/12*(1.02^3))*Inputs!AE150 -> 0.39234097 | AF30: =((SourceDetail!E42/1000000)/12*(1.02^3))*Inputs!AF150 -> 0.39234097 | AG30: =((SourceDetail!E42/1000000)/12*(1.02^3))*Inputs!AG150 -> 0.39234097 | AH30: =((SourceDetail!E42/1000000)/12*(1.02^3))*Inputs!AH150 -> 0.39234097 | AI30: =((SourceDetail!E42/1000000)/12*(1.02^3))*Inputs!AI150 -> 0.39234097 | AJ30: =((SourceDetail!E42/1000000)/12*(1.02^3))*Inputs!AJ150 -> 0.39234097 | AK30: =((SourceDetail!E42/1000000)/12*(1.02^3))*Inputs!AK150 -> 0.39234097 | AL30: =((SourceDetail!E42/1000000)/12*(1.02^3))*Inputs!AL150 -> 0.39234097 | AM30: =((SourceDetail!E42/1000000)/12*(1.02^3))*Inputs!AM150 -> 0.39234097
C31: admin total | J31: =J21+J22+J23+J24+J25+J26+J27+J28+J29+J30 -> 60.136822 | K31: =K21+K22+K23+K24+K25+K26+K27+K28+K29+K30 -> 60.206488 | L31: =L21+L22+L23+L24+L25+L26+L27+L28+L29+L30 -> 60.276154 | M31: =M21+M22+M23+M24+M25+M26+M27+M28+M29+M30 -> 60.34582 | N31: =N21+N22+N23+N24+N25+N26+N27+N28+N29+N30 -> 60.415486 | O31: =O21+O22+O23+O24+O25+O26+O27+O28+O29+O30 -> 60.485152 | P31: =P21+P22+P23+P24+P25+P26+P27+P28+P29+P30 -> 61.767488 | Q31: =Q21+Q22+Q23+Q24+Q25+Q26+Q27+Q28+Q29+Q30 -> 61.840637 | ... AM31: =AM21+AM22+AM23+AM24+AM25+AM26+AM27+AM28+AM29+AM30 -> 64.322447
C34: rnd_nature
C35: rnd_nature.payroll | J35: =Payroll!J40 -> 33.099966 | K35: =Payroll!K40 -> 33.099966 | L35: =Payroll!L40 -> 33.099966 | M35: =Payroll!M40 -> 33.099966 | N35: =Payroll!N40 -> 33.099966 | O35: =Payroll!O40 -> 33.099966 | P35: =Payroll!P40 -> 34.092965 | Q35: =Payroll!Q40 -> 34.092965 | ... AM35: =Payroll!AM40 -> 35.115754
C36: rnd_nature.direct_inputs | J36: =(Revenue!J40*(SourceDetail!E48/1000000)/SourceHistory!F9)*Inputs!J156 -> 15.635621 | K36: =(Revenue!K40*(SourceDetail!E48/1000000)/SourceHistory!F9)*Inputs!K156 -> 15.635621 | L36: =(Revenue!L40*(SourceDetail!E48/1000000)/SourceHistory!F9)*Inputs!L156 -> 15.635621 | M36: =(Revenue!M40*(SourceDetail!E48/1000000)/SourceHistory!F9)*Inputs!M156 -> 15.635621 | N36: =(Revenue!N40*(SourceDetail!E48/1000000)/SourceHistory!F9)*Inputs!N156 -> 15.635621 | O36: =(Revenue!O40*(SourceDetail!E48/1000000)/SourceHistory!F9)*Inputs!O156 -> 15.635621 | P36: =(Revenue!P40*(SourceDetail!E48/1000000)/SourceHistory!F9)*Inputs!P156 -> 16.699276 | Q36: =(Revenue!Q40*(SourceDetail!E48/1000000)/SourceHistory!F9)*Inputs!Q156 -> 16.699276 | R36: =(Revenue!R40*(SourceDetail!E48/1000000)/SourceHistory!F9)*Inputs!R156 -> 16.699276 | S36: =(Revenue!S40*(SourceDetail!E48/1000000)/SourceHistory!F9)*Inputs!S156 -> 16.699276 | T36: =(Revenue!T40*(SourceDetail!E48/1000000)/SourceHistory!F9)*Inputs!T156 -> 16.699276 | U36: =(Revenue!U40*(SourceDetail!E48/1000000)/SourceHistory!F9)*Inputs!U156 -> 16.699276 | V36: =(Revenue!V40*(SourceDetail!E48/1000000)/SourceHistory!F9)*Inputs!V156 -> 16.20292 | W36: =(Revenue!W40*(SourceDetail!E48/1000000)/SourceHistory!F9)*Inputs!W156 -> 16.20292 | X36: =(Revenue!X40*(SourceDetail!E48/1000000)/SourceHistory!F9)*Inputs!X156 -> 16.20292 | Y36: =(Revenue!Y40*(SourceDetail!E48/1000000)/SourceHistory!F9)*Inputs!Y156 -> 16.20292 | Z36: =(Revenue!Z40*(SourceDetail!E48/1000000)/SourceHistory!F9)*Inputs!Z156 -> 16.20292 | AA36: =(Revenue!AA40*(SourceDetail!E48/1000000)/SourceHistory!F9)*Inputs!AA156 -> 16.20292 | AB36: =(Revenue!AB40*(SourceDetail!E48/1000000)/SourceHistory!F9)*Inputs!AB156 -> 17.303516 | AC36: =(Revenue!AC40*(SourceDetail!E48/1000000)/SourceHistory!F9)*Inputs!AC156 -> 17.303516 | AD36: =(Revenue!AD40*(SourceDetail!E48/1000000)/SourceHistory!F9)*Inputs!AD156 -> 17.303516 | AE36: =(Revenue!AE40*(SourceDetail!E48/1000000)/SourceHistory!F9)*Inputs!AE156 -> 17.303516 | AF36: =(Revenue!AF40*(SourceDetail!E48/1000000)/SourceHistory!F9)*Inputs!AF156 -> 17.303516 | AG36: =(Revenue!AG40*(SourceDetail!E48/1000000)/SourceHistory!F9)*Inputs!AG156 -> 17.303516 | AH36: =(Revenue!AH40*(SourceDetail!E48/1000000)/SourceHistory!F9)*Inputs!AH156 -> 16.799936 | AI36: =(Revenue!AI40*(SourceDetail!E48/1000000)/SourceHistory!F9)*Inputs!AI156 -> 16.799936 | AJ36: =(Revenue!AJ40*(SourceDetail!E48/1000000)/SourceHistory!F9)*Inputs!AJ156 -> 16.799936 | AK36: =(Revenue!AK40*(SourceDetail!E48/1000000)/SourceHistory!F9)*Inputs!AK156 -> 16.799936 | AL36: =(Revenue!AL40*(SourceDetail!E48/1000000)/SourceHistory!F9)*Inputs!AL156 -> 16.799936 | AM36: =(Revenue!AM40*(SourceDetail!E48/1000000)/SourceHistory!F9)*Inputs!AM156 -> 16.799936
C37: rnd_nature.depreciation_amortization | J37: =Assets!J100*SourceAnalysis!D27 -> 1.205819 | K37: =Assets!K100*SourceAnalysis!D27 -> 1.2154711 | L37: =Assets!L100*SourceAnalysis!D27 -> 1.2251232 | M37: =Assets!M100*SourceAnalysis!D27 -> 1.2347753 | N37: =Assets!N100*SourceAnalysis!D27 -> 1.2444274 | O37: =Assets!O100*SourceAnalysis!D27 -> 1.2540795 | P37: =Assets!P100*SourceAnalysis!D27 -> 1.2637316 | Q37: =Assets!Q100*SourceAnalysis!D27 -> 1.2738663 | R37: =Assets!R100*SourceAnalysis!D27 -> 1.284001 | S37: =Assets!S100*SourceAnalysis!D27 -> 1.2941357 | T37: =Assets!T100*SourceAnalysis!D27 -> 1.3042704 | U37: =Assets!U100*SourceAnalysis!D27 -> 1.3144051 | V37: =Assets!V100*SourceAnalysis!D27 -> 1.3245398 | W37: =Assets!W100*SourceAnalysis!D27 -> 1.3346745 | X37: =Assets!X100*SourceAnalysis!D27 -> 1.2879633 | Y37: =Assets!Y100*SourceAnalysis!D27 -> 1.2973533 | Z37: =Assets!Z100*SourceAnalysis!D27 -> 1.307488 | AA37: =Assets!AA100*SourceAnalysis!D27 -> 1.3176227 | AB37: =Assets!AB100*SourceAnalysis!D27 -> 1.3277575 | AC37: =Assets!AC100*SourceAnalysis!D27 -> 1.3383989 | AD37: =Assets!AD100*SourceAnalysis!D27 -> 1.3490403 | AE37: =Assets!AE100*SourceAnalysis!D27 -> 1.3596818 | AF37: =Assets!AF100*SourceAnalysis!D27 -> 1.3703232 | AG37: =Assets!AG100*SourceAnalysis!D27 -> 1.3809646 | AH37: =Assets!AH100*SourceAnalysis!D27 -> 1.3916061 | AI37: =Assets!AI100*SourceAnalysis!D27 -> 1.4022475 | AJ37: =Assets!AJ100*SourceAnalysis!D27 -> 1.412889 | AK37: =Assets!AK100*SourceAnalysis!D27 -> 1.4235304 | AL37: =Assets!AL100*SourceAnalysis!D27 -> 1.4341718 | AM37: =Assets!AM100*SourceAnalysis!D27 -> 1.4448133
C38: rnd_nature.other | J38: =((SourceDetail!E52/1000000)/12*(1.02^1))*Inputs!J158 -> 4.9699059 | K38: =((SourceDetail!E52/1000000)/12*(1.02^1))*Inputs!K158 -> 4.9699059 | L38: =((SourceDetail!E52/1000000)/12*(1.02^1))*Inputs!L158 -> 4.9699059 | M38: =((SourceDetail!E52/1000000)/12*(1.02^1))*Inputs!M158 -> 4.9699059 | N38: =((SourceDetail!E52/1000000)/12*(1.02^1))*Inputs!N158 -> 4.9699059 | O38: =((SourceDetail!E52/1000000)/12*(1.02^1))*Inputs!O158 -> 4.9699059 | P38: =((SourceDetail!E52/1000000)/12*(1.02^2))*Inputs!P158 -> 5.0693041 | Q38: =((SourceDetail!E52/1000000)/12*(1.02^2))*Inputs!Q158 -> 5.0693041 | R38: =((SourceDetail!E52/1000000)/12*(1.02^2))*Inputs!R158 -> 5.0693041 | S38: =((SourceDetail!E52/1000000)/12*(1.02^2))*Inputs!S158 -> 5.0693041 | T38: =((SourceDetail!E52/1000000)/12*(1.02^2))*Inputs!T158 -> 5.0693041 | U38: =((SourceDetail!E52/1000000)/12*(1.02^2))*Inputs!U158 -> 5.0693041 | V38: =((SourceDetail!E52/1000000)/12*(1.02^2))*Inputs!V158 -> 5.0693041 | W38: =((SourceDetail!E52/1000000)/12*(1.02^2))*Inputs!W158 -> 5.0693041 | X38: =((SourceDetail!E52/1000000)/12*(1.02^2))*Inputs!X158 -> 5.0693041 | Y38: =((SourceDetail!E52/1000000)/12*(1.02^2))*Inputs!Y158 -> 5.0693041 | Z38: =((SourceDetail!E52/1000000)/12*(1.02^2))*Inputs!Z158 -> 5.0693041 | AA38: =((SourceDetail!E52/1000000)/12*(1.02^2))*Inputs!AA158 -> 5.0693041 | AB38: =((SourceDetail!E52/1000000)/12*(1.02^3))*Inputs!AB158 -> 5.1706901 | AC38: =((SourceDetail!E52/1000000)/12*(1.02^3))*Inputs!AC158 -> 5.1706901 | AD38: =((SourceDetail!E52/1000000)/12*(1.02^3))*Inputs!AD158 -> 5.1706901 | AE38: =((SourceDetail!E52/1000000)/12*(1.02^3))*Inputs!AE158 -> 5.1706901 | AF38: =((SourceDetail!E52/1000000)/12*(1.02^3))*Inputs!AF158 -> 5.1706901 | AG38: =((SourceDetail!E52/1000000)/12*(1.02^3))*Inputs!AG158 -> 5.1706901 | AH38: =((SourceDetail!E52/1000000)/12*(1.02^3))*Inputs!AH158 -> 5.1706901 | AI38: =((SourceDetail!E52/1000000)/12*(1.02^3))*Inputs!AI158 -> 5.1706901 | AJ38: =((SourceDetail!E52/1000000)/12*(1.02^3))*Inputs!AJ158 -> 5.1706901 | AK38: =((SourceDetail!E52/1000000)/12*(1.02^3))*Inputs!AK158 -> 5.1706901 | AL38: =((SourceDetail!E52/1000000)/12*(1.02^3))*Inputs!AL158 -> 5.1706901 | AM38: =((SourceDetail!E52/1000000)/12*(1.02^3))*Inputs!AM158 -> 5.1706901
C39: rnd_nature total | J39: =J35+J36+J37+J38 -> 54.911311 | K39: =K35+K36+K37+K38 -> 54.920963 | L39: =L35+L36+L37+L38 -> 54.930615 | M39: =M35+M36+M37+M38 -> 54.940268 | N39: =N35+N36+N37+N38 -> 54.94992 | O39: =O35+O36+O37+O38 -> 54.959572 | P39: =P35+P36+P37+P38 -> 57.125277 | Q39: =Q35+Q36+Q37+Q38 -> 57.135412 | ... AM39: =AM35+AM36+AM37+AM38 -> 58.531193
